Workbook
Name AER: Convencionales!#REF!
Name ASC: Convencionales!#REF!
Name BIN: Convencionales!#REF!
Name EST: Convencionales!#REF!
Name FIN: Convencionales!#REF!
Name ICA: Convencionales!#REF!
Name IMS: Convencionales!#REF!
Name MIS: Convencionales!#REF!
Name OBE: Convencionales!$I$3:$I$17
Name OGA: Convencionales!#REF!
Name PAC: Convencionales!#REF!
Name PRF: Convencionales!#REF!
Name RAI: Convencionales!#REF!
Name THM: Convencionales!#REF!
Name VNI: Convencionales!#REF!

Sheet Convencionales
G1: fup*
B2: Elija | D2: DD | E2: MM | F2: AAAA | G2: Elija | I2: OBE | K2: LOCALIDAD | M2: Descripcion ccosto | O2: Nombres
A3: Elija | B3: SI | C3: Elija | D3: 1 | E3: Ene | F3: 2019 | G3: ANALISTA DE SISTEMAS | I3: Elija | K3: Elija | M3: Elija | O3: Elija
A4: Pregrado | B4: NO | C4: 4 Meses Semestre 1 | D4: 2 | E4: Feb | F4: 2020 | G4: APRENDIZ SENA | I4: 1. Misión y Proyecto Educativo Institucional | K4: POPAYÁN | M4: ADMINISTRACION DE EMPRESAS | O4: DIAZ CARMONA DANILO MANZILLER
A5: Especialización Profesional | B5: TRASLADO | C5: 4 Meses Semestre 2 | D5: 3 | E5: Mar | F5: 2021 | G5: ASESOR | I5: 2. Estudiantes | K5: SANTANDER DE QUILICHAO | M5: ADMINISTRACION DE EMPRESAS / MOD. VIRTUAL | O5: SOLIS ESCOBAR FERNANDO
A6: Maestría | C6: 8 Meses | D6: 4 | E6: Abr | F6: 2022 | G6: ASISTENTE ADMINISTRATIVO | I6: 3. Talento Humano | M6: ADMINISTRACION DE EMPRESAS AGROPECUARIAS | O6: IBARRA SOTELO MARYEM ROCIO
A7: Doctorado | C7: 10 meses | D7: 5 | E7: May | F7: 2023 | G7: ASISTENTE ACADEMICO | I7: 4. Profesores | M7: ADMINISTRACION DE EMPRESAS AGROPECUARIAS / MOD. VIRTUAL | O7: GARCIA BUITRON JULIO CESAR
C8: 11 meses | D8: 6 | E8: Jun | G8: AUXILIAR ACADEMICO | I8: 5. Procesos académicos | M8: ARQUITECTURA | O8: COBO POTOSI YISEL
C9: 1 año | D9: 7 | E9: Jul | G9: AUXILIAR ADMINISTRATIVO | I9: 6. Visibilidad Nacional e Internacional | M9: ASEGURAMIENTO DE LA CALIDAD | O9: DULCEY MUJICA INGRITH TATIANA
A10: Elija | C10: Indefinido | D10: 8 | E10: Ago | G10: AUXILIAR CONTABLE | I10: 7. Investigación y Creación Artística | M10: AUTOEVALUACION | O10: VALVERDE ROJAS ERICA ANDREA
A11: Especialización Profesional | D11: 9 | E11: Sep | G11: AUXILIAR DE CAMPO | I11: 8. Impacto social | M11: BIBLIOTECA | O11: URBANO GALLEGO ANDREA CECILIA
A12: Maestría | C12: Elija | D12: 10 | E12: Oct | G12: AUXILIAR DE ENFERMERIA | I12: 9. Autoevaluación y Autorregulación | M12: BIENESTAR INSTITUCIONAL | O12: LOZANO NIÑO SERGIO
A13: Doctorado | C13: Semestre 1 | D13: 11 | E13: Nov | G13: AUXILIAR DE INVESTIGACION | I13: 10. Bienestar Institucional | M13: CALIDAD INSTITUCIONAL | O13: CASTRO DOMINGUEZ GLORIA PATRICIA
C14: Semestre 2 | D14: 12 | E14: Dic | G14: AUXILIAR DE LABORATORIO | I14: 11. Organización, gestión y administración | M14: CENTRO DE INFORMATICA | O14: FERIZ GARCIA DANIEL ANDRES
A15: Elija | C15: Ambos | D15: 13 | G15: AUXILIAR DE MANTENIMIENTO | I15: 12. Recursos de apoyo académico e infraestructura física | M15: CICMA | O15: DURAN LOPEZ JULIAN ANDRES
A16: TRANSVERSAL | D16: 14 | G16: AUXILIAR DE MANTENIMIENTO TI | I16: 13. Recursos financieros | M16: COORDINACION DE PROYECTOS | O16: QUINTERO ROJAS ANGELA MARIA
A17: CONVENCIONAL | D17: 15 | G17: AUXILIAR DE SOPORTE | I17: 14. Aseguramiento de la Calidad | M17: COMUNICACIÓN SOCIAL | O17: URREA PANTOJA WILMER JAIR
D18: 16 | G18: AUXILIAR SERVICIOS GENERALES | M18: COMUNICACIÓN SOCIAL / MOD. VIRTUAL | O18: MOSQUERA SANCHEZ LUIS EMIRO
A19: Tipo | D19: 17 | G19: BIBLIOTECOLOGA | M19: COMUNICACIONES | O19: GAVIRIA ARMERO SONIA DEL CONSUELO
A20: PMI | D20: 18 | G20: CAMAROGRAFO AUDIOVISUALES | M20: CONTABILIDAD | O20: ROJAS GIRALDO JUAN CARLOS
A21: PMC | D21: 19 | G21: CAPELLAN | M21: CONTADURIA | O21: PASAJE BURBANO FABIAN FERNANDO
A22: PMP | D22: 20 | G22: COMMUNITY MANAGER | M22: DECANATURA | O22: ZUÑIGA MUÑOZ YADY VANESSA
A23: PGR | D23: 21 | G23: CONDUCTOR | M23: DERECHO | O23: CLEVES SUAZA LUIS GUILLERMO
A24: EST | D24: 22 | G24: CONTADOR | M24: ECOLOGIA | O24: MEDINA LLANTEN JESUS ANTONIO
A25: DM | D25: 23 | G25: COORDINADOR | M25: ECONOMIA | O25: ARIAS HOYOS ARNOL
D26: 24 | G26: COORDINADOR - LOGISTICA, COMPRAS Y ALMACEN | M26: EGRESADOS | O26: DURAN ENRIQUEZ CARLOS ANDRES
D27: 25 | G27: COORDINADOR ACADEMICO | M27: ESCUELA DE DESARROLLO PROFESORAL | O27: MONTOYA BONILLA BIBIANA PATRICIA
D28: 26 | G28: COORDINADOR ACADEMICO GENERAL | M28: ESCUELA DE IDIOMAS | O28: BETANCOURT LOPEZ JOSE GREGORIO
D29: 27 | G29: COORDINADOR ADMISIONES | M29: ESCUELA DE LECTO-ESCRITURA | O29: VALENCIA PALOMINO DAISY XIMENA
D30: 28 | G30: COORDINADOR CULTURA Y DEPORTES | M30: ESCUELA DE MATEMATICAS | O30: MINA ZAPE CARLOS FERNANDO
D31: 29 | G31: COORDINADOR DE EMPRENDIMIENTO | M31: ESCUELA DE MUSICA | O31: MOSQUERA CERON JUAN PABLO
D32: 30 | G32: COORDINADOR DE MEDIOS EDUCATIVOS | M32: EXTENSIÓN Y PROYECCIÓN SOCIAL | O32: JOAQUI ESCOBAR PAOLA ANDREA
D33: 31 | G33: COORDINADOR DE PROYECTOS | M33: FINCA | O33: BOLAÑOS SARRIA DIEGO FABIAN
G34: COORDINADOR GESTION CURRICULAR | M34: INGENIERIA DE SISTEMAS | O34: SATIZABAL SERNA CLARA EUGENIA
G35: COORDINADOR GESTION DOCUMENTAL | M35: INGENIERIA INDUSTRIAL | O35: ACOSTA CAICEDO OMAR ANDRES
G36: COORDINADOR PERMANENCIA | M36: INTERNACIONALIZACION | O36: PRADO QUINTERO JUAN MANUEL
G37: COORDINADOR REGISTRO ACADEMICO | M37: LABORATORIOS | O37: RONCANCIO ANDREA CAICEDO
G38: COORDINADOR SERVICIOS DE SALUD | M38: LEAC | O38: AGUILAR BURBANO ANDRES FELIPE
G39: COORDINADOR SG - SST | M39: MERCADEO - ADMISIONES | O39: ERAZO MEDINA MONICA ADRIANA
G40: DESARROLLADOR | M40: PASTORAL | O40: CARDONA CHAVEZ CARLOS MANUEL
G41: DIRECTOR | M41: PLANEACION | O41: ARBOLEDA GAETH ANDRES FELIPE
G42: DIRECTOR CONTROL INTERNO | M42: POSGRADOS / COMUNICACIÓN PARA EL DESARROLLO TERRITORIAL | O42: GOMEZ DURAN DIANA CAROLINA
G43: DIRECTOR DE EXTENCIÓN Y PROYECCIÓN SOCIAL | M43: POSGRADOS / DATA ANALYTICS PARA MARKETING DIGITAL | O43: POTES GALARZA MANUEL JULIAN CAMILO
G44: DIRECTOR DE INVESTIGACIÓN | M44: POSGRADOS / DERECHO CONSTITUCIONAL | O44: MOLANO CASTRO MARIA ALEJANDRA
G45: DIRECTOR DE POSTGRADOS | M45: POSGRADOS / DERECHO PROCESAL | O45: OCAMPO GUZMAN GINNA FERNANDA
... G55: DOCENTE COORDINADOR TRABAJOS DE GRADO TIEMPO COMPLETO | M55: SEDE NORTE | O55: VELANDIA DÍAZ DIANA ISABEL
G56: DOCENTE INVESTIGADOR | M56: REGISTRO ACADEMICO
G57: DOCENTE MEDIO TIEMPO | M57: SECRETARIA GENERAL
G58: DOCENTE TIEMPO COMPLETO | M58: SEGUIMIENTO INSTITUCIONAL
G59: JOVEN INVESTIGADOR | M59: SERVICIOS GENERALES
G60: MAYORDOMO | M60: SIDI
G61: MEDICO | M61: SISTEMA DE GESTION DE SST
G62: MENSAJERO | M62: TESORERIA
G63: ODONTOLOGO | M63: TRABAJO SOCIAL
G64: PERIODISTA | M64: UNIDAD AUDIOVISUALES
G65: PROFESIONAL | M65: UNIVIDA
G66: PROFESIONAL BIENESTAR INSTITUCIONAL | M66: VICERECTORIA ACADEMICA
G67: PROFESIONAL CONTRATOS Y CERTIFICACIONES | M67: VICERECTORIA ADMINISTRATIVA Y FINANCIERA
G68: PROFESIONAL DE APOYO
G69: PROFESIONAL DE APOYO OPCIONES DE GRADO
G70: PROFESIONAL DE NOMINA
G71: PROFESIONAL DISEÑADOR
G72: PROFESIONAL SEGURIDAD SOCIAL
G73: PROFESIONAL SELECCION Y CAPACITACION
G74: PROFESIONAL UNIVERSITARIO
G75: PROFESIONAL VIRTUALIZACION REDES
G76: RECTOR
G77: SECRETARIA GENERAL | M77: TIPO RECURSOS
G78: SUPERNUMERARIO | M78: Elija
G79: TESORERO | M79: Fisicos
G80: VICERRECTOR | M80: Financieros
G81: WEBMASTER | M81: Tecnológicos
M82: Humanos
M85: PROYECTOS
M86: Elija
M87: 1. APROPIACIÓN: IDENTIDAD INSTITUCIONAL
M88: 2. SISTEMA INTERNO DE ASEGURAMIENTO DE LA CALIDAD
M89: 3. ACOMPAÑAMIENTO Y ÉXITO ESTUDIANTIL
M90: 4. NUEVOS ESCENARIOS DE APRENDIZAJE Y RECURSOS INSTITUCIONALES
M91: 5. ECOSISTEMA DE INNOVACIÓN
M92: 6. RELACIONAMIENTO CON EL MEDIO EXTERNO
M93: 7. DESARROLLO Y GESTIÓN ORGANIZACIONAL
N95: METAS
N96: Elija
N97: 1. Intervenciones a estudiantes y docentes en sensibilizaciones en temáticas institucionales.
N98: 1. Actualización del Proyecto Educativo Institucional
N99: 1. Evaluación de los resultados de aprendizaje (Evaluación de las rubricas de enseñanza)
N100: 1. Implementar instrumentos de comunicación y divulgación, con el fin de promover un novedoso acercamiento hacia la comunidad educativa,
N101: 1. Construir un Plan Estratégico de Comunicación y Relacionamiento adecuado que permita establecer un contacto permanente y consecutivo con los grupos de interés.
N102: 1. Actualizar de manera permanente los contenidos en medios de comunicación institucional en línea, tales como portal web y perfiles de redes sociales institucionales para brindar a la ciudadanía información oportuna, veraz y confiable.
N103: 1. Difundir la información institucional a los diferentes grupos objetivos y públicos de interés sobre la gestión a través de acciones de comunicación externa, con el fin de propiciar el flujo adecuado y el acceso a la información.
N104: 1. Generar impacto social mendiante la creación del boletin institucional.
N105: 1. Garantizar el despliegue oportuno a las diferentes audiencias y estamentos universitarios, de los planes, proyectos, iniciativas y actividades puestas en marcha en el marco de los eventos que se realicen internos y externos.
N106: 1. Establecer mecanismos de acción en materia de comunicación que permita responder a los diferentes retos institucionales.
... N289: 7. La apreciación de la docencia por parte de los estudiantes La autoevaluación del profesor La valoración por parte del jefe inmediato. Trazar planes de mejora

Sheet BaseSalarial
B2: Incremento | D2: 1.09
B3: Carga prestacional | D3: 1.52
B4: Salario Mínimo | D4: 1200000
B5: Supsidio de transporte | D5: 140606
B6: Horas Laborales Tiempo Completo | D6: 40
B7: Horas Laborales Medio Tiempo | D7: =D6/2 -> 20
B8: Horas Laborales TP | D8: =D7/2 -> 10
B9: Vr. Hora por docente | D9: =(D2*D4)/30 -> 43600
B12: CUALIFICACIÓN DOCENTE | C12: SALARIO 2021 TC | D12: SALARIO CON INCREMENTO TC | E12: CON CARGA PRESTACIONAL TC | F12: Vr. Hora por docente TC | G12: SALARIO 2021 MT | H12: SALARIO CON INCREMENTO MT | I12: CON CARGA PRESTACIONAL MT | J12: Vr. Hora por docente MT | K12: Vr. Hora por docente TP
B13: Pregrado | C13: 2531429 | D13: =C13*$D$2 -> 2759257.6 | E13: =+D13*$D$3 -> 4194071.6 | F13: =E13/$D$6 -> 104851.79 | G13: =C13/2 -> 1265714.5 | H13: =G13*$D$2 -> 1379628.8 | I13: =(H13*$D$3)+$D$5 -> 2237641.8 | J13: =I13/$D$7 -> 111882.09 | K13: =I13/$D$8 -> 223764.18
B14: Especialización Profesional | C14: 2703909 | D14: =C14*$D$2 -> 2947260.8 | E14: =+D14*$D$3 -> 4479836.4 | F14: =E14/$D$6 -> 111995.91 | G14: =C14/2 -> 1351954.5 | H14: =G14*$D$2 -> 1473630.4 | I14: =(H14*$D$3)+$D$5 -> 2380524.2 | J14: =I14/$D$7 -> 119026.21 | K14: =I14/$D$8 -> 238052.42
B15: Maestría | C15: 2876389 | D15: =C15*$D$2 -> 3135264 | E15: =+D15*$D$3 -> 4765601.3 | F15: =E15/$D$6 -> 119140.03 | G15: =C15/2 -> 1438194.5 | H15: =G15*$D$2 -> 1567632 | I15: =(H15*$D$3)+$D$5 -> 2523406.6 | J15: =I15/$D$7 -> 126170.33 | K15: =I15/$D$8 -> 252340.66
B16: Doctorado | C16: 3048868 | D16: =C16*$D$2 -> 3323266.1 | E16: =+D16*$D$3 -> 5051364.5 | F16: =E16/$D$6 -> 126284.11 | G16: =C16/2 -> 1524434 | H16: =G16*$D$2 -> 1661633.1 | I16: =(H16*$D$3)+$D$5 -> 2666288.3 | J16: =I16/$D$7 -> 133314.41 | K16: =I16/$D$8 -> 266628.83
B19: CÓDIGO SALARIO | C19: SALARIO 2022 | D19: SALARIO CON INCREMENTO | E19: CON CARGA PRESTACIONAL | G19: CUALIFICACIÓN DOCENTE | H19: COSTO HORA
B20: CS01 | C20: 4476389 | D20: =C20*$D$2 -> 4879264 | E20: =+D20*$D$3 -> 7416481.3 | G20: Especialización Profesional | H20: 100000
B21: CS02 | C21: 4303910 | D21: =C21*$D$2 -> 4691261.9 | E21: =+D21*$D$3 -> 7130718.1 | G21: Maestría | H21: 120000
B22: CS03 | C22: 4273788 | D22: =C22*$D$2 -> 4658428.9 | E22: =+D22*$D$3 -> 7080812 | G22: Doctorado | H22: 150000
B23: CS04 | C23: 4131429 | D23: =C23*$D$2 -> 4503257.6 | E23: =+D23*$D$3 -> 6844951.6
B24: CS05 | C24: 3900489 | D24: =C24*$D$2 -> 4251533 | E24: =+D24*$D$3 -> 6462330.2
B25: CS06 | C25: 3720033 | D25: =C25*$D$2 -> 4054836 | E25: =+D25*$D$3 -> 6163350.7
B26: CS07 | C26: 3676389 | D26: =C26*$D$2 -> 4007264 | E26: =+D26*$D$3 -> 6091041.3
B27: CS08 | C27: 3578221 | D27: =C27*$D$2 -> 3900260.9 | E27: =+D27*$D$3 -> 5928396.6
B28: CS09 | C28: 3503910 | D28: =C28*$D$2 -> 3819261.9 | E28: =+D28*$D$3 -> 5805278.1
B29: CS10 | C29: 3473868 | D29: =C29*$D$2 -> 3786516.1 | E29: =+D29*$D$3 -> 5755504.5
B30: CS11 | C30: 3458389 | D30: =C30*$D$2 -> 3769644 | E30: =+D30*$D$3 -> 5729858.9
B31: CS12 | C31: 3331429 | D31: =C31*$D$2 -> 3631257.6 | E31: =+D31*$D$3 -> 5519511.6
B32: CS13 | C32: 3285910 | D32: =C32*$D$2 -> 3581641.9 | E32: =+D32*$D$3 -> 5444095.7
B33: CS14 | C33: 3126389 | D33: =C33*$D$2 -> 3407764 | E33: =+D33*$D$3 -> 5179801.3
B34: CS15 | C34: 3113429 | D34: =C34*$D$2 -> 3393637.6 | E34: =+D34*$D$3 -> 5158329.2
... B58: CS39 | C58: 500000 | D58: =C58*$D$2 -> 545000 | E58: =+D58*$D$3 -> 828400

Sheet ADM
B2: Nombre del colaborador | C2: Seleccione el Cargo | D2: Código Salario | E2: Cantidad Personal | F2: Periodo de contratación | G2: Meses de contratación | H2: Totales | I2: Costo por Semestre I | J2: Costo por Semestre II | K2: Aprobado SI-NO | L2: Costo Semestre 1 | M2: Costo Semestre 2 | N2: Observaciones | O2: Ejecución | P2: Observaciones de la Ejecución
C3: Elija | F3: Elija | G3: =IF(F3="4 MESES Semestre 1",4,IF(F3="4 MESES Semestre 2",4,IF(F3="8 Meses",4,IF(F3="10 Meses",5,IF(F3="11 Meses",5.5,IF(F3="1 año",6,IF(F3="Indefinido",6,0))))))) -> 0 | H3: =(E3*G3*(IFERROR(VLOOKUP(D3,BaseSalarial!$B$20:$E$58,4,0)/G3,"0"))) -> 0 | I3: =IF(F3="4 MESES Semestre 1",H3*G3,IF(F3="4 MESES Semestre 2",0,IF(F3="8 Meses",H3*G3,IF(F3="10 Meses",H3*G3,IF(F3="11 Meses",H3*G3,IF(F3="1 Año",H3*G3,IF(F3="Indefinido",H3*G3,0))))))) -> 0 | J3: =IF(F3="4 MESES Semestre 1",0,IF(F3="4 MESES Semestre 2",H3*G3,IF(F3="8 Meses",H3*G3,IF(F3="10 Meses",H3*G3,IF(F3="11 Meses",H3*G3,IF(F3="1 Año",H3*G3,IF(F3="Indefinido",H3*G3,0))))))) -> 0 | K3: NO | L3: =IF(K3="SI",I3,IF(K3="NO",0,"Sin comprobar")) -> 0 | M3: =IF(K3="SI",J3,IF(K3="NO",0,"Sin comprobar")) -> 0
C4: Elija | F4: Elija | G4: =IF(F4="4 MESES Semestre 1",4,IF(F4="4 MESES Semestre 2",4,IF(F4="8 Meses",4,IF(F4="10 Meses",5,IF(F4="11 Meses",5.5,IF(F4="1 año",6,IF(F4="Indefinido",6,0))))))) -> 0 | H4: =(E4*G4*(IFERROR(VLOOKUP(D4,BaseSalarial!$B$20:$E$58,4,0)/G4,"0"))) -> 0 | I4: =IF(F4="4 MESES Semestre 1",H4*G4,IF(F4="4 MESES Semestre 2",0,IF(F4="8 Meses",H4*G4,IF(F4="10 Meses",H4*G4,IF(F4="11 Meses",H4*G4,IF(F4="1 Año",H4*G4,IF(F4="Indefinido",H4*G4,0))))))) -> 0 | J4: =IF(F4="4 MESES Semestre 1",0,IF(F4="4 MESES Semestre 2",H4*G4,IF(F4="8 Meses",H4*G4,IF(F4="10 Meses",H4*G4,IF(F4="11 Meses",H4*G4,IF(F4="1 Año",H4*G4,IF(F4="Indefinido",H4*G4,0))))))) -> 0 | K4: NO | L4: =IF(K4="SI",I4,IF(K4="NO",0,"Sin comprobar")) -> 0 | M4: =IF(K4="SI",J4,IF(K4="NO",0,"Sin comprobar")) -> 0
C5: Elija | F5: Elija | G5: =IF(F5="4 MESES Semestre 1",4,IF(F5="4 MESES Semestre 2",4,IF(F5="8 Meses",4,IF(F5="10 Meses",5,IF(F5="11 Meses",5.5,IF(F5="1 año",6,IF(F5="Indefinido",6,0))))))) -> 0 | H5: =(E5*G5*(IFERROR(VLOOKUP(D5,BaseSalarial!$B$20:$E$58,4,0)/G5,"0"))) -> 0 | I5: =IF(F5="4 MESES Semestre 1",H5*G5,IF(F5="4 MESES Semestre 2",0,IF(F5="8 Meses",H5*G5,IF(F5="10 Meses",H5*G5,IF(F5="11 Meses",H5*G5,IF(F5="1 Año",H5*G5,IF(F5="Indefinido",H5*G5,0))))))) -> 0 | J5: =IF(F5="4 MESES Semestre 1",0,IF(F5="4 MESES Semestre 2",H5*G5,IF(F5="8 Meses",H5*G5,IF(F5="10 Meses",H5*G5,IF(F5="11 Meses",H5*G5,IF(F5="1 Año",H5*G5,IF(F5="Indefinido",H5*G5,0))))))) -> 0 | K5: NO | L5: =IF(K5="SI",I5,IF(K5="NO",0,"Sin comprobar")) -> 0 | M5: =IF(K5="SI",J5,IF(K5="NO",0,"Sin comprobar")) -> 0
C6: Elija | F6: Elija | G6: =IF(F6="4 MESES Semestre 1",4,IF(F6="4 MESES Semestre 2",4,IF(F6="8 Meses",4,IF(F6="10 Meses",5,IF(F6="11 Meses",5.5,IF(F6="1 año",6,IF(F6="Indefinido",6,0))))))) -> 0 | H6: =(E6*G6*(IFERROR(VLOOKUP(D6,BaseSalarial!$B$20:$E$58,4,0)/G6,"0"))) -> 0 | I6: =IF(F6="4 MESES Semestre 1",H6*G6,IF(F6="4 MESES Semestre 2",0,IF(F6="8 Meses",H6*G6,IF(F6="10 Meses",H6*G6,IF(F6="11 Meses",H6*G6,IF(F6="1 Año",H6*G6,IF(F6="Indefinido",H6*G6,0))))))) -> 0 | J6: =IF(F6="4 MESES Semestre 1",0,IF(F6="4 MESES Semestre 2",H6*G6,IF(F6="8 Meses",H6*G6,IF(F6="10 Meses",H6*G6,IF(F6="11 Meses",H6*G6,IF(F6="1 Año",H6*G6,IF(F6="Indefinido",H6*G6,0))))))) -> 0 | K6: NO | L6: =IF(K6="SI",I6,IF(K6="NO",0,"Sin comprobar")) -> 0 | M6: =IF(K6="SI",J6,IF(K6="NO",0,"Sin comprobar")) -> 0
C7: Elija | F7: Elija | G7: =IF(F7="4 MESES Semestre 1",4,IF(F7="4 MESES Semestre 2",4,IF(F7="8 Meses",4,IF(F7="10 Meses",5,IF(F7="11 Meses",5.5,IF(F7="1 año",6,IF(F7="Indefinido",6,0))))))) -> 0 | H7: =(E7*G7*(IFERROR(VLOOKUP(D7,BaseSalarial!$B$20:$E$58,4,0)/G7,"0"))) -> 0 | I7: =IF(F7="4 MESES Semestre 1",H7*G7,IF(F7="4 MESES Semestre 2",0,IF(F7="8 Meses",H7*G7,IF(F7="10 Meses",H7*G7,IF(F7="11 Meses",H7*G7,IF(F7="1 Año",H7*G7,IF(F7="Indefinido",H7*G7,0))))))) -> 0 | J7: =IF(F7="4 MESES Semestre 1",0,IF(F7="4 MESES Semestre 2",H7*G7,IF(F7="8 Meses",H7*G7,IF(F7="10 Meses",H7*G7,IF(F7="11 Meses",H7*G7,IF(F7="1 Año",H7*G7,IF(F7="Indefinido",H7*G7,0))))))) -> 0 | K7: NO | L7: =IF(K7="SI",I7,IF(K7="NO",0,"Sin comprobar")) -> 0 | M7: =IF(K7="SI",J7,IF(K7="NO",0,"Sin comprobar")) -> 0
C8: Elija | F8: Elija | G8: =IF(F8="4 MESES Semestre 1",4,IF(F8="4 MESES Semestre 2",4,IF(F8="8 Meses",4,IF(F8="10 Meses",5,IF(F8="11 Meses",5.5,IF(F8="1 año",6,IF(F8="Indefinido",6,0))))))) -> 0 | H8: =(E8*G8*(IFERROR(VLOOKUP(D8,BaseSalarial!$B$20:$E$58,4,0)/G8,"0"))) -> 0 | I8: =IF(F8="4 MESES Semestre 1",H8*G8,IF(F8="4 MESES Semestre 2",0,IF(F8="8 Meses",H8*G8,IF(F8="10 Meses",H8*G8,IF(F8="11 Meses",H8*G8,IF(F8="1 Año",H8*G8,IF(F8="Indefinido",H8*G8,0))))))) -> 0 | J8: =IF(F8="4 MESES Semestre 1",0,IF(F8="4 MESES Semestre 2",H8*G8,IF(F8="8 Meses",H8*G8,IF(F8="10 Meses",H8*G8,IF(F8="11 Meses",H8*G8,IF(F8="1 Año",H8*G8,IF(F8="Indefinido",H8*G8,0))))))) -> 0 | K8: NO | L8: =IF(K8="SI",I8,IF(K8="NO",0,"Sin comprobar")) -> 0 | M8: =IF(K8="SI",J8,IF(K8="NO",0,"Sin comprobar")) -> 0
C9: Elija | F9: Elija | G9: =IF(F9="4 MESES Semestre 1",4,IF(F9="4 MESES Semestre 2",4,IF(F9="8 Meses",4,IF(F9="10 Meses",5,IF(F9="11 Meses",5.5,IF(F9="1 año",6,IF(F9="Indefinido",6,0))))))) -> 0 | H9: =(E9*G9*(IFERROR(VLOOKUP(D9,BaseSalarial!$B$20:$E$58,4,0)/G9,"0"))) -> 0 | I9: =IF(F9="4 MESES Semestre 1",H9*G9,IF(F9="4 MESES Semestre 2",0,IF(F9="8 Meses",H9*G9,IF(F9="10 Meses",H9*G9,IF(F9="11 Meses",H9*G9,IF(F9="1 Año",H9*G9,IF(F9="Indefinido",H9*G9,0))))))) -> 0 | J9: =IF(F9="4 MESES Semestre 1",0,IF(F9="4 MESES Semestre 2",H9*G9,IF(F9="8 Meses",H9*G9,IF(F9="10 Meses",H9*G9,IF(F9="11 Meses",H9*G9,IF(F9="1 Año",H9*G9,IF(F9="Indefinido",H9*G9,0))))))) -> 0 | K9: NO | L9: =IF(K9="SI",I9,IF(K9="NO",0,"Sin comprobar")) -> 0 | M9: =IF(K9="SI",J9,IF(K9="NO",0,"Sin comprobar")) -> 0
C10: Elija | F10: Elija | G10: =IF(F10="4 MESES Semestre 1",4,IF(F10="4 MESES Semestre 2",4,IF(F10="8 Meses",4,IF(F10="10 Meses",5,IF(F10="11 Meses",5.5,IF(F10="1 año",6,IF(F10="Indefinido",6,0))))))) -> 0 | H10: =(E10*G10*(IFERROR(VLOOKUP(D10,BaseSalarial!$B$20:$E$58,4,0)/G10,"0"))) -> 0 | I10: =IF(F10="4 MESES Semestre 1",H10*G10,IF(F10="4 MESES Semestre 2",0,IF(F10="8 Meses",H10*G10,IF(F10="10 Meses",H10*G10,IF(F10="11 Meses",H10*G10,IF(F10="1 Año",H10*G10,IF(F10="Indefinido",H10*G10,0))))))) -> 0 | J10: =IF(F10="4 MESES Semestre 1",0,IF(F10="4 MESES Semestre 2",H10*G10,IF(F10="8 Meses",H10*G10,IF(F10="10 Meses",H10*G10,IF(F10="11 Meses",H10*G10,IF(F10="1 Año",H10*G10,IF(F10="Indefinido",H10*G10,0))))))) -> 0 | K10: NO | L10: =IF(K10="SI",I10,IF(K10="NO",0,"Sin comprobar")) -> 0 | M10: =IF(K10="SI",J10,IF(K10="NO",0,"Sin comprobar")) -> 0
C11: Elija | F11: Elija | G11: =IF(F11="4 MESES Semestre 1",4,IF(F11="4 MESES Semestre 2",4,IF(F11="8 Meses",4,IF(F11="10 Meses",5,IF(F11="11 Meses",5.5,IF(F11="1 año",6,IF(F11="Indefinido",6,0))))))) -> 0 | H11: =(E11*G11*(IFERROR(VLOOKUP(D11,BaseSalarial!$B$20:$E$58,4,0)/G11,"0"))) -> 0 | I11: =IF(F11="4 MESES Semestre 1",H11*G11,IF(F11="4 MESES Semestre 2",0,IF(F11="8 Meses",H11*G11,IF(F11="10 Meses",H11*G11,IF(F11="11 Meses",H11*G11,IF(F11="1 Año",H11*G11,IF(F11="Indefinido",H11*G11,0))))))) -> 0 | J11: =IF(F11="4 MESES Semestre 1",0,IF(F11="4 MESES Semestre 2",H11*G11,IF(F11="8 Meses",H11*G11,IF(F11="10 Meses",H11*G11,IF(F11="11 Meses",H11*G11,IF(F11="1 Año",H11*G11,IF(F11="Indefinido",H11*G11,0))))))) -> 0 | K11: NO | L11: =IF(K11="SI",I11,IF(K11="NO",0,"Sin comprobar")) -> 0 | M11: =IF(K11="SI",J11,IF(K11="NO",0,"Sin comprobar")) -> 0
C12: Elija | F12: Elija | G12: =IF(F12="4 MESES Semestre 1",4,IF(F12="4 MESES Semestre 2",4,IF(F12="8 Meses",4,IF(F12="10 Meses",5,IF(F12="11 Meses",5.5,IF(F12="1 año",6,IF(F12="Indefinido",6,0))))))) -> 0 | H12: =(E12*G12*(IFERROR(VLOOKUP(D12,BaseSalarial!$B$20:$E$58,4,0)/G12,"0"))) -> 0 | I12: =IF(F12="4 MESES Semestre 1",H12*G12,IF(F12="4 MESES Semestre 2",0,IF(F12="8 Meses",H12*G12,IF(F12="10 Meses",H12*G12,IF(F12="11 Meses",H12*G12,IF(F12="1 Año",H12*G12,IF(F12="Indefinido",H12*G12,0))))))) -> 0 | J12: =IF(F12="4 MESES Semestre 1",0,IF(F12="4 MESES Semestre 2",H12*G12,IF(F12="8 Meses",H12*G12,IF(F12="10 Meses",H12*G12,IF(F12="11 Meses",H12*G12,IF(F12="1 Año",H12*G12,IF(F12="Indefinido",H12*G12,0))))))) -> 0 | K12: NO | L12: =IF(K12="SI",I12,IF(K12="NO",0,"Sin comprobar")) -> 0 | M12: =IF(K12="SI",J12,IF(K12="NO",0,"Sin comprobar")) -> 0
C13: Elija | F13: Elija | G13: =IF(F13="4 MESES Semestre 1",4,IF(F13="4 MESES Semestre 2",4,IF(F13="8 Meses",4,IF(F13="10 Meses",5,IF(F13="11 Meses",5.5,IF(F13="1 año",6,IF(F13="Indefinido",6,0))))))) -> 0 | H13: =(E13*G13*(IFERROR(VLOOKUP(D13,BaseSalarial!$B$20:$E$58,4,0)/G13,"0"))) -> 0 | I13: =IF(F13="4 MESES Semestre 1",H13*G13,IF(F13="4 MESES Semestre 2",0,IF(F13="8 Meses",H13*G13,IF(F13="10 Meses",H13*G13,IF(F13="11 Meses",H13*G13,IF(F13="1 Año",H13*G13,IF(F13="Indefinido",H13*G13,0))))))) -> 0 | J13: =IF(F13="4 MESES Semestre 1",0,IF(F13="4 MESES Semestre 2",H13*G13,IF(F13="8 Meses",H13*G13,IF(F13="10 Meses",H13*G13,IF(F13="11 Meses",H13*G13,IF(F13="1 Año",H13*G13,IF(F13="Indefinido",H13*G13,0))))))) -> 0 | K13: NO | L13: =IF(K13="SI",I13,IF(K13="NO",0,"Sin comprobar")) -> 0 | M13: =IF(K13="SI",J13,IF(K13="NO",0,"Sin comprobar")) -> 0
C14: Elija | F14: Elija | G14: =IF(F14="4 MESES Semestre 1",4,IF(F14="4 MESES Semestre 2",4,IF(F14="8 Meses",4,IF(F14="10 Meses",5,IF(F14="11 Meses",5.5,IF(F14="1 año",6,IF(F14="Indefinido",6,0))))))) -> 0 | H14: =(E14*G14*(IFERROR(VLOOKUP(D14,BaseSalarial!$B$20:$E$58,4,0)/G14,"0"))) -> 0 | I14: =IF(F14="4 MESES Semestre 1",H14*G14,IF(F14="4 MESES Semestre 2",0,IF(F14="8 Meses",H14*G14,IF(F14="10 Meses",H14*G14,IF(F14="11 Meses",H14*G14,IF(F14="1 Año",H14*G14,IF(F14="Indefinido",H14*G14,0))))))) -> 0 | J14: =IF(F14="4 MESES Semestre 1",0,IF(F14="4 MESES Semestre 2",H14*G14,IF(F14="8 Meses",H14*G14,IF(F14="10 Meses",H14*G14,IF(F14="11 Meses",H14*G14,IF(F14="1 Año",H14*G14,IF(F14="Indefinido",H14*G14,0))))))) -> 0 | K14: NO | L14: =IF(K14="SI",I14,IF(K14="NO",0,"Sin comprobar")) -> 0 | M14: =IF(K14="SI",J14,IF(K14="NO",0,"Sin comprobar")) -> 0
... C17: Elija | F17: Elija | G17: =IF(F17="4 MESES Semestre 1",4,IF(F17="4 MESES Semestre 2",4,IF(F17="8 Meses",4,IF(F17="10 Meses",5,IF(F17="11 Meses",5.5,IF(F17="1 año",6,IF(F17="Indefinido",6,0))))))) -> 0 | H17: =(E17*G17*(IFERROR(VLOOKUP(D17,BaseSalarial!$B$20:$E$58,4,0)/G17,"0"))) -> 0 | I17: =IF(F17="4 MESES Semestre 1",H17*G17,IF(F17="4 MESES Semestre 2",0,IF(F17="8 Meses",H17*G17,IF(F17="10 Meses",H17*G17,IF(F17="11 Meses",H17*G17,IF(F17="1 Año",H17*G17,IF(F17="Indefinido",H17*G17,0))))))) -> 0 | J17: =IF(F17="4 MESES Semestre 1",0,IF(F17="4 MESES Semestre 2",H17*G17,IF(F17="8 Meses",H17*G17,IF(F17="10 Meses",H17*G17,IF(F17="11 Meses",H17*G17,IF(F17="1 Año",H17*G17,IF(F17="Indefinido",H17*G17,0))))))) -> 0 | K17: NO | L17: =IF(K17="SI",I17,IF(K17="NO",0,"Sin comprobar")) -> 0 | M17: =IF(K17="SI",J17,IF(K17="NO",0,"Sin comprobar")) -> 0
I18: =SUM(I3:I17) -> 0 | J18: =SUM(J3:J17) -> 0 | L18: =SUM(L3:L17) -> 0 | M18: =SUM(M3:M17) -> 0 | O18: =SUM(O3:O17) -> 0

Sheet PRE
E1: Docentes Tiempo Completo
B2: Cantidad de Docentes | C2: Cualificación | D2: Función(Buscar) | E2: Periodo de contratación | F2: Costo por Semestre I | G2: Costo por Semestre II | H2: Aprobado SI-NO | I2: Costo Semestre 1 | J2: Costo Semestre 2 | K2: Observaciones | L2: Ejecución | M2: Observaciones de la Ejecución
B3: 0 | C3: Elija | D3: =IFERROR(VLOOKUP(C3,BaseSalarial!$B$13:$E$16,4,FALSE),0) -> 0 | E3: Elija | F3: =B3*(IF(E3="4 MESES Semestre 1",D3*4,IF(E3="4 MESES Semestre 2",0,IF(E3="8 Meses",D3*4,IF(E3="10 Meses",D3*5,IF(E3="11 Meses",D3*5.5,IF(E3="1 Año",D3*6,IF(E3="Indefinido",D3*6,0)))))))) -> 0 | G3: =B3*(IF(E3="4 MESES Semestre 1",0,IF(E3="4 MESES Semestre 2",D3*4,IF(E3="8 Meses",D3*4,IF(E3="10 Meses",D3*5,IF(E3="11 Meses",D3*5.5,IF(E3="1 Año",D3*6,IF(E3="Indefinido",D3*6,0)))))))) -> 0 | H3: NO | I3: =IF(H3="SI",F3,IF(H3="NO",0,"Sin comprobar")) -> 0 | J3: =IF(H3="SI",G3,IF(H3="NO",0,"Sin comprobar")) -> 0
B4: 0 | C4: Elija | D4: =IFERROR(VLOOKUP(C4,BaseSalarial!$B$13:$E$16,4,FALSE),0) -> 0 | E4: Elija | F4: =B4*(IF(E4="4 MESES Semestre 1",D4*4,IF(E4="4 MESES Semestre 2",0,IF(E4="8 Meses",D4*4,IF(E4="10 Meses",D4*5,IF(E4="11 Meses",D4*5.5,IF(E4="1 Año",D4*6,IF(E4="Indefinido",D4*6,0)))))))) -> 0 | G4: =B4*(IF(E4="4 MESES Semestre 1",0,IF(E4="4 MESES Semestre 2",D4*4,IF(E4="8 Meses",D4*4,IF(E4="10 Meses",D4*5,IF(E4="11 Meses",D4*5.5,IF(E4="1 Año",D4*6,IF(E4="Indefinido",D4*6,0)))))))) -> 0 | H4: NO | I4: =IF(H4="SI",F4,IF(H4="NO",0,"Sin comprobar")) -> 0 | J4: =IF(H4="SI",G4,IF(H4="NO",0,"Sin comprobar")) -> 0
B5: 0 | C5: Elija | D5: =IFERROR(VLOOKUP(C5,BaseSalarial!$B$13:$E$16,4,FALSE),0) -> 0 | E5: Elija | F5: =B5*(IF(E5="4 MESES Semestre 1",D5*4,IF(E5="4 MESES Semestre 2",0,IF(E5="8 Meses",D5*4,IF(E5="10 Meses",D5*5,IF(E5="11 Meses",D5*5.5,IF(E5="1 Año",D5*6,IF(E5="Indefinido",D5*6,0)))))))) -> 0 | G5: =B5*(IF(E5="4 MESES Semestre 1",0,IF(E5="4 MESES Semestre 2",D5*4,IF(E5="8 Meses",D5*4,IF(E5="10 Meses",D5*5,IF(E5="11 Meses",D5*5.5,IF(E5="1 Año",D5*6,IF(E5="Indefinido",D5*6,0)))))))) -> 0 | H5: NO | I5: =IF(H5="SI",F5,IF(H5="NO",0,"Sin comprobar")) -> 0 | J5: =IF(H5="SI",G5,IF(H5="NO",0,"Sin comprobar")) -> 0
B6: 0 | C6: Elija | D6: =IFERROR(VLOOKUP(C6,BaseSalarial!$B$13:$E$16,4,FALSE),0) -> 0 | E6: Elija | F6: =B6*(IF(E6="4 MESES Semestre 1",D6*4,IF(E6="4 MESES Semestre 2",0,IF(E6="8 Meses",D6*4,IF(E6="10 Meses",D6*5,IF(E6="11 Meses",D6*5.5,IF(E6="1 Año",D6*6,IF(E6="Indefinido",D6*6,0)))))))) -> 0 | G6: =B6*(IF(E6="4 MESES Semestre 1",0,IF(E6="4 MESES Semestre 2",D6*4,IF(E6="8 Meses",D6*4,IF(E6="10 Meses",D6*5,IF(E6="11 Meses",D6*5.5,IF(E6="1 Año",D6*6,IF(E6="Indefinido",D6*6,0)))))))) -> 0 | H6: NO | I6: =IF(H6="SI",F6,IF(H6="NO",0,"Sin comprobar")) -> 0 | J6: =IF(H6="SI",G6,IF(H6="NO",0,"Sin comprobar")) -> 0
B7: 0 | C7: Elija | D7: =IFERROR(VLOOKUP(C7,BaseSalarial!$B$13:$E$16,4,FALSE),0) -> 0 | E7: Elija | F7: =B7*(IF(E7="4 MESES Semestre 1",D7*4,IF(E7="4 MESES Semestre 2",0,IF(E7="8 Meses",D7*4,IF(E7="10 Meses",D7*5,IF(E7="11 Meses",D7*5.5,IF(E7="1 Año",D7*6,IF(E7="Indefinido",D7*6,0)))))))) -> 0 | G7: =B7*(IF(E7="4 MESES Semestre 1",0,IF(E7="4 MESES Semestre 2",D7*4,IF(E7="8 Meses",D7*4,IF(E7="10 Meses",D7*5,IF(E7="11 Meses",D7*5.5,IF(E7="1 Año",D7*6,IF(E7="Indefinido",D7*6,0)))))))) -> 0 | H7: NO | I7: =IF(H7="SI",F7,IF(H7="NO",0,"Sin comprobar")) -> 0 | J7: =IF(H7="SI",G7,IF(H7="NO",0,"Sin comprobar")) -> 0
B8: 0 | C8: Elija | D8: =IFERROR(VLOOKUP(C8,BaseSalarial!$B$13:$E$16,4,FALSE),0) -> 0 | E8: Elija | F8: =B8*(IF(E8="4 MESES Semestre 1",D8*4,IF(E8="4 MESES Semestre 2",0,IF(E8="8 Meses",D8*4,IF(E8="10 Meses",D8*5,IF(E8="11 Meses",D8*5.5,IF(E8="1 Año",D8*6,IF(E8="Indefinido",D8*6,0)))))))) -> 0 | G8: =B8*(IF(E8="4 MESES Semestre 1",0,IF(E8="4 MESES Semestre 2",D8*4,IF(E8="8 Meses",D8*4,IF(E8="10 Meses",D8*5,IF(E8="11 Meses",D8*5.5,IF(E8="1 Año",D8*6,IF(E8="Indefinido",D8*6,0)))))))) -> 0 | H8: NO | I8: =IF(H8="SI",F8,IF(H8="NO",0,"Sin comprobar")) -> 0 | J8: =IF(H8="SI",G8,IF(H8="NO",0,"Sin comprobar")) -> 0
B9: 0 | C9: Elija | D9: =IFERROR(VLOOKUP(C9,BaseSalarial!$B$13:$E$16,4,FALSE),0) -> 0 | E9: Elija | F9: =B9*(IF(E9="4 MESES Semestre 1",D9*4,IF(E9="4 MESES Semestre 2",0,IF(E9="8 Meses",D9*4,IF(E9="10 Meses",D9*5,IF(E9="11 Meses",D9*5.5,IF(E9="1 Año",D9*6,IF(E9="Indefinido",D9*6,0)))))))) -> 0 | G9: =B9*(IF(E9="4 MESES Semestre 1",0,IF(E9="4 MESES Semestre 2",D9*4,IF(E9="8 Meses",D9*4,IF(E9="10 Meses",D9*5,IF(E9="11 Meses",D9*5.5,IF(E9="1 Año",D9*6,IF(E9="Indefinido",D9*6,0)))))))) -> 0 | H9: NO | I9: =IF(H9="SI",F9,IF(H9="NO",0,"Sin comprobar")) -> 0 | J9: =IF(H9="SI",G9,IF(H9="NO",0,"Sin comprobar")) -> 0
B10: 0 | C10: Elija | D10: =IFERROR(VLOOKUP(C10,BaseSalarial!$B$13:$E$16,4,FALSE),0) -> 0 | E10: Elija | F10: =B10*(IF(E10="4 MESES Semestre 1",D10*4,IF(E10="4 MESES Semestre 2",0,IF(E10="8 Meses",D10*4,IF(E10="10 Meses",D10*5,IF(E10="11 Meses",D10*5.5,IF(E10="1 Año",D10*6,IF(E10="Indefinido",D10*6,0)))))))) -> 0 | G10: =B10*(IF(E10="4 MESES Semestre 1",0,IF(E10="4 MESES Semestre 2",D10*4,IF(E10="8 Meses",D10*4,IF(E10="10 Meses",D10*5,IF(E10="11 Meses",D10*5.5,IF(E10="1 Año",D10*6,IF(E10="Indefinido",D10*6,0)))))))) -> 0 | H10: NO | I10: =IF(H10="SI",F10,IF(H10="NO",0,"Sin comprobar")) -> 0 | J10: =IF(H10="SI",G10,IF(H10="NO",0,"Sin comprobar")) -> 0
B11: 0 | C11: Elija | D11: =IFERROR(VLOOKUP(C11,BaseSalarial!$B$13:$E$16,4,FALSE),0) -> 0 | E11: Elija | F11: =B11*(IF(E11="4 MESES Semestre 1",D11*4,IF(E11="4 MESES Semestre 2",0,IF(E11="8 Meses",D11*4,IF(E11="10 Meses",D11*5,IF(E11="11 Meses",D11*5.5,IF(E11="1 Año",D11*6,IF(E11="Indefinido",D11*6,0)))))))) -> 0 | G11: =B11*(IF(E11="4 MESES Semestre 1",0,IF(E11="4 MESES Semestre 2",D11*4,IF(E11="8 Meses",D11*4,IF(E11="10 Meses",D11*5,IF(E11="11 Meses",D11*5.5,IF(E11="1 Año",D11*6,IF(E11="Indefinido",D11*6,0)))))))) -> 0 | H11: NO | I11: =IF(H11="SI",F11,IF(H11="NO",0,"Sin comprobar")) -> 0 | J11: =IF(H11="SI",G11,IF(H11="NO",0,"Sin comprobar")) -> 0
B12: 0 | C12: Elija | D12: =IFERROR(VLOOKUP(C12,BaseSalarial!$B$13:$E$16,4,FALSE),0) -> 0 | E12: Elija | F12: =B12*(IF(E12="4 MESES Semestre 1",D12*4,IF(E12="4 MESES Semestre 2",0,IF(E12="8 Meses",D12*4,IF(E12="10 Meses",D12*5,IF(E12="11 Meses",D12*5.5,IF(E12="1 Año",D12*6,IF(E12="Indefinido",D12*6,0)))))))) -> 0 | G12: =B12*(IF(E12="4 MESES Semestre 1",0,IF(E12="4 MESES Semestre 2",D12*4,IF(E12="8 Meses",D12*4,IF(E12="10 Meses",D12*5,IF(E12="11 Meses",D12*5.5,IF(E12="1 Año",D12*6,IF(E12="Indefinido",D12*6,0)))))))) -> 0 | H12: NO | I12: =IF(H12="SI",F12,IF(H12="NO",0,"Sin comprobar")) -> 0 | J12: =IF(H12="SI",G12,IF(H12="NO",0,"Sin comprobar")) -> 0
B13: 0 | C13: Elija | D13: =IFERROR(VLOOKUP(C13,BaseSalarial!$B$13:$E$16,4,FALSE),0) -> 0 | E13: Elija | F13: =B13*(IF(E13="4 MESES Semestre 1",D13*4,IF(E13="4 MESES Semestre 2",0,IF(E13="8 Meses",D13*4,IF(E13="10 Meses",D13*5,IF(E13="11 Meses",D13*5.5,IF(E13="1 Año",D13*6,IF(E13="Indefinido",D13*6,0)))))))) -> 0 | G13: =B13*(IF(E13="4 MESES Semestre 1",0,IF(E13="4 MESES Semestre 2",D13*4,IF(E13="8 Meses",D13*4,IF(E13="10 Meses",D13*5,IF(E13="11 Meses",D13*5.5,IF(E13="1 Año",D13*6,IF(E13="Indefinido",D13*6,0)))))))) -> 0 | H13: NO | I13: =IF(H13="SI",F13,IF(H13="NO",0,"Sin comprobar")) -> 0 | J13: =IF(H13="SI",G13,IF(H13="NO",0,"Sin comprobar")) -> 0
B14: 0 | C14: Elija | D14: =IFERROR(VLOOKUP(C14,BaseSalarial!$B$13:$E$16,4,FALSE),0) -> 0 | E14: Elija | F14: =B14*(IF(E14="4 MESES Semestre 1",D14*4,IF(E14="4 MESES Semestre 2",0,IF(E14="8 Meses",D14*4,IF(E14="10 Meses",D14*5,IF(E14="11 Meses",D14*5.5,IF(E14="1 Año",D14*6,IF(E14="Indefinido",D14*6,0)))))))) -> 0 | G14: =B14*(IF(E14="4 MESES Semestre 1",0,IF(E14="4 MESES Semestre 2",D14*4,IF(E14="8 Meses",D14*4,IF(E14="10 Meses",D14*5,IF(E14="11 Meses",D14*5.5,IF(E14="1 Año",D14*6,IF(E14="Indefinido",D14*6,0)))))))) -> 0 | H14: NO | I14: =IF(H14="SI",F14,IF(H14="NO",0,"Sin comprobar")) -> 0 | J14: =IF(H14="SI",G14,IF(H14="NO",0,"Sin comprobar")) -> 0
... B17: 0 | C17: Elija | D17: =IFERROR(VLOOKUP(C17,BaseSalarial!$B$13:$E$16,4,FALSE),0) -> 0 | E17: Elija | F17: =B17*(IF(E17="4 MESES Semestre 1",D17*4,IF(E17="4 MESES Semestre 2",0,IF(E17="8 Meses",D17*4,IF(E17="10 Meses",D17*5,IF(E17="11 Meses",D17*5.5,IF(E17="1 Año",D17*6,IF(E17="Indefinido",D17*6,0)))))))) -> 0 | G17: =B17*(IF(E17="4 MESES Semestre 1",0,IF(E17="4 MESES Semestre 2",D17*4,IF(E17="8 Meses",D17*4,IF(E17="10 Meses",D17*5,IF(E17="11 Meses",D17*5.5,IF(E17="1 Año",D17*6,IF(E17="Indefinido",D17*6,0)))))))) -> 0 | H17: NO | I17: =IF(H17="SI",F17,IF(H17="NO",0,"Sin comprobar")) -> 0 | J17: =IF(H17="SI",G17,IF(H17="NO",0,"Sin comprobar")) -> 0
F18: =SUM(F3:F17) -> 0 | G18: =SUM(G3:G17) -> 0 | I18: =SUM(I3:I17) -> 0 | J18: =SUM(J3:J17) -> 0 | L18: =SUM(L3:L17) -> 0
E20: Docentes Medio Tiempo
B22: Cantidad de Docentes | C22: Cualificación | D22: Función(Buscar) | E22: Periodo de contratación | F22: Costo por Semestre I | G22: Costo por Semestre II | H22: Aprobado SI-NO | I22: Costo Semestre 1 | J22: Costo Semestre 2 | K22: Observaciones | L22: Ejecución | M22: Observaciones de la Ejecución
B23: 0 | C23: Elija | D23: =IFERROR(VLOOKUP(C23,BaseSalarial!$B$13:$J$16,8,FALSE),0) -> 0 | E23: Elija | F23: =B23*(IF(E23="4 MESES Semestre 1",D23*4,IF(E23="4 MESES Semestre 2",0,IF(E23="8 Meses",D23*4,IF(E23="10 Meses",D23*5,IF(E23="11 Meses",D23*5.5,IF(E23="1 Año",D23*6,IF(E23="Indefinido",D23*6,0)))))))) -> 0 | G23: =B23*(IF(E23="4 MESES Semestre 1",0,IF(E23="4 MESES Semestre 2",D23*4,IF(E23="8 Meses",D23*4,IF(E23="10 Meses",D23*5,IF(E23="11 Meses",D23*5.5,IF(E23="1 Año",D23*6,IF(E23="Indefinido",D23*6,0)))))))) -> 0 | H23: NO | I23: =IF(H23="SI",F23,IF(H23="NO",0,"Sin comprobar")) -> 0 | J23: =IF(H23="SI",G23,IF(H23="NO",0,"Sin comprobar")) -> 0
B24: 0 | C24: Elija | D24: =IFERROR(VLOOKUP(C24,BaseSalarial!$B$13:$J$16,8,FALSE),0) -> 0 | E24: Elija | F24: =B24*(IF(E24="4 MESES Semestre 1",D24*4,IF(E24="4 MESES Semestre 2",0,IF(E24="8 Meses",D24*4,IF(E24="10 Meses",D24*5,IF(E24="11 Meses",D24*5.5,IF(E24="1 Año",D24*6,IF(E24="Indefinido",D24*6,0)))))))) -> 0 | G24: =B24*(IF(E24="4 MESES Semestre 1",0,IF(E24="4 MESES Semestre 2",D24*4,IF(E24="8 Meses",D24*4,IF(E24="10 Meses",D24*5,IF(E24="11 Meses",D24*5.5,IF(E24="1 Año",D24*6,IF(E24="Indefinido",D24*6,0)))))))) -> 0 | H24: NO | I24: =IF(H24="SI",F24,IF(H24="NO",0,"Sin comprobar")) -> 0 | J24: =IF(H24="SI",G24,IF(H24="NO",0,"Sin comprobar")) -> 0
B25: 0 | C25: Elija | D25: =IFERROR(VLOOKUP(C25,BaseSalarial!$B$13:$J$16,8,FALSE),0) -> 0 | E25: Elija | F25: =B25*(IF(E25="4 MESES Semestre 1",D25*4,IF(E25="4 MESES Semestre 2",0,IF(E25="8 Meses",D25*4,IF(E25="10 Meses",D25*5,IF(E25="11 Meses",D25*5.5,IF(E25="1 Año",D25*6,IF(E25="Indefinido",D25*6,0)))))))) -> 0 | G25: =B25*(IF(E25="4 MESES Semestre 1",0,IF(E25="4 MESES Semestre 2",D25*4,IF(E25="8 Meses",D25*4,IF(E25="10 Meses",D25*5,IF(E25="11 Meses",D25*5.5,IF(E25="1 Año",D25*6,IF(E25="Indefinido",D25*6,0)))))))) -> 0 | H25: NO | I25: =IF(H25="SI",F25,IF(H25="NO",0,"Sin comprobar")) -> 0 | J25: =IF(H25="SI",G25,IF(H25="NO",0,"Sin comprobar")) -> 0
B26: 0 | C26: Elija | D26: =IFERROR(VLOOKUP(C26,BaseSalarial!$B$13:$J$16,8,FALSE),0) -> 0 | E26: Elija | F26: =B26*(IF(E26="4 MESES Semestre 1",D26*4,IF(E26="4 MESES Semestre 2",0,IF(E26="8 Meses",D26*4,IF(E26="10 Meses",D26*5,IF(E26="11 Meses",D26*5.5,IF(E26="1 Año",D26*6,IF(E26="Indefinido",D26*6,0)))))))) -> 0 | G26: =B26*(IF(E26="4 MESES Semestre 1",0,IF(E26="4 MESES Semestre 2",D26*4,IF(E26="8 Meses",D26*4,IF(E26="10 Meses",D26*5,IF(E26="11 Meses",D26*5.5,IF(E26="1 Año",D26*6,IF(E26="Indefinido",D26*6,0)))))))) -> 0 | H26: NO | I26: =IF(H26="SI",F26,IF(H26="NO",0,"Sin comprobar")) -> 0 | J26: =IF(H26="SI",G26,IF(H26="NO",0,"Sin comprobar")) -> 0
B27: 0 | C27: Elija | D27: =IFERROR(VLOOKUP(C27,BaseSalarial!$B$13:$J$16,8,FALSE),0) -> 0 | E27: Elija | F27: =B27*(IF(E27="4 MESES Semestre 1",D27*4,IF(E27="4 MESES Semestre 2",0,IF(E27="8 Meses",D27*4,IF(E27="10 Meses",D27*5,IF(E27="11 Meses",D27*5.5,IF(E27="1 Año",D27*6,IF(E27="Indefinido",D27*6,0)))))))) -> 0 | G27: =B27*(IF(E27="4 MESES Semestre 1",0,IF(E27="4 MESES Semestre 2",D27*4,IF(E27="8 Meses",D27*4,IF(E27="10 Meses",D27*5,IF(E27="11 Meses",D27*5.5,IF(E27="1 Año",D27*6,IF(E27="Indefinido",D27*6,0)))))))) -> 0 | H27: NO | I27: =IF(H27="SI",F27,IF(H27="NO",0,"Sin comprobar")) -> 0 | J27: =IF(H27="SI",G27,IF(H27="NO",0,"Sin comprobar")) -> 0
B28: 0 | C28: Elija | D28: =IFERROR(VLOOKUP(C28,BaseSalarial!$B$13:$J$16,8,FALSE),0) -> 0 | E28: Elija | F28: =B28*(IF(E28="4 MESES Semestre 1",D28*4,IF(E28="4 MESES Semestre 2",0,IF(E28="8 Meses",D28*4,IF(E28="10 Meses",D28*5,IF(E28="11 Meses",D28*5.5,IF(E28="1 Año",D28*6,IF(E28="Indefinido",D28*6,0)))))))) -> 0 | G28: =B28*(IF(E28="4 MESES Semestre 1",0,IF(E28="4 MESES Semestre 2",D28*4,IF(E28="8 Meses",D28*4,IF(E28="10 Meses",D28*5,IF(E28="11 Meses",D28*5.5,IF(E28="1 Año",D28*6,IF(E28="Indefinido",D28*6,0)))))))) -> 0 | H28: NO | I28: =IF(H28="SI",F28,IF(H28="NO",0,"Sin comprobar")) -> 0 | J28: =IF(H28="SI",G28,IF(H28="NO",0,"Sin comprobar")) -> 0
B29: 0 | C29: Elija | D29: =IFERROR(VLOOKUP(C29,BaseSalarial!$B$13:$J$16,8,FALSE),0) -> 0 | E29: Elija | F29: =B29*(IF(E29="4 MESES Semestre 1",D29*4,IF(E29="4 MESES Semestre 2",0,IF(E29="8 Meses",D29*4,IF(E29="10 Meses",D29*5,IF(E29="11 Meses",D29*5.5,IF(E29="1 Año",D29*6,IF(E29="Indefinido",D29*6,0)))))))) -> 0 | G29: =B29*(IF(E29="4 MESES Semestre 1",0,IF(E29="4 MESES Semestre 2",D29*4,IF(E29="8 Meses",D29*4,IF(E29="10 Meses",D29*5,IF(E29="11 Meses",D29*5.5,IF(E29="1 Año",D29*6,IF(E29="Indefinido",D29*6,0)))))))) -> 0 | H29: NO | I29: =IF(H29="SI",F29,IF(H29="NO",0,"Sin comprobar")) -> 0 | J29: =IF(H29="SI",G29,IF(H29="NO",0,"Sin comprobar")) -> 0
B30: 0 | C30: Elija | D30: =IFERROR(VLOOKUP(C30,BaseSalarial!$B$13:$J$16,8,FALSE),0) -> 0 | E30: Elija | F30: =B30*(IF(E30="4 MESES Semestre 1",D30*4,IF(E30="4 MESES Semestre 2",0,IF(E30="8 Meses",D30*4,IF(E30="10 Meses",D30*5,IF(E30="11 Meses",D30*5.5,IF(E30="1 Año",D30*6,IF(E30="Indefinido",D30*6,0)))))))) -> 0 | G30: =B30*(IF(E30="4 MESES Semestre 1",0,IF(E30="4 MESES Semestre 2",D30*4,IF(E30="8 Meses",D30*4,IF(E30="10 Meses",D30*5,IF(E30="11 Meses",D30*5.5,IF(E30="1 Año",D30*6,IF(E30="Indefinido",D30*6,0)))))))) -> 0 | H30: NO | I30: =IF(H30="SI",F30,IF(H30="NO",0,"Sin comprobar")) -> 0 | J30: =IF(H30="SI",G30,IF(H30="NO",0,"Sin comprobar")) -> 0
B31: 0 | C31: Elija | D31: =IFERROR(VLOOKUP(C31,BaseSalarial!$B$13:$J$16,8,FALSE),0) -> 0 | E31: Elija | F31: =B31*(IF(E31="4 MESES Semestre 1",D31*4,IF(E31="4 MESES Semestre 2",0,IF(E31="8 Meses",D31*4,IF(E31="10 Meses",D31*5,IF(E31="11 Meses",D31*5.5,IF(E31="1 Año",D31*6,IF(E31="Indefinido",D31*6,0)))))))) -> 0 | G31: =B31*(IF(E31="4 MESES Semestre 1",0,IF(E31="4 MESES Semestre 2",D31*4,IF(E31="8 Meses",D31*4,IF(E31="10 Meses",D31*5,IF(E31="11 Meses",D31*5.5,IF(E31="1 Año",D31*6,IF(E31="Indefinido",D31*6,0)))))))) -> 0 | H31: NO | I31: =IF(H31="SI",F31,IF(H31="NO",0,"Sin comprobar")) -> 0 | J31: =IF(H31="SI",G31,IF(H31="NO",0,"Sin comprobar")) -> 0
B32: 0 | C32: Elija | D32: =IFERROR(VLOOKUP(C32,BaseSalarial!$B$13:$J$16,8,FALSE),0) -> 0 | E32: Elija | F32: =B32*(IF(E32="4 MESES Semestre 1",D32*4,IF(E32="4 MESES Semestre 2",0,IF(E32="8 Meses",D32*4,IF(E32="10 Meses",D32*5,IF(E32="11 Meses",D32*5.5,IF(E32="1 Año",D32*6,IF(E32="Indefinido",D32*6,0)))))))) -> 0 | G32: =B32*(IF(E32="4 MESES Semestre 1",0,IF(E32="4 MESES Semestre 2",D32*4,IF(E32="8 Meses",D32*4,IF(E32="10 Meses",D32*5,IF(E32="11 Meses",D32*5.5,IF(E32="1 Año",D32*6,IF(E32="Indefinido",D32*6,0)))))))) -> 0 | H32: NO | I32: =IF(H32="SI",F32,IF(H32="NO",0,"Sin comprobar")) -> 0 | J32: =IF(H32="SI",G32,IF(H32="NO",0,"Sin comprobar")) -> 0
F33: =SUM(F23:F32) -> 0 | G33: =SUM(G23:G32) -> 0 | I33: =SUM(I23:I32) -> 0 | J33: =SUM(J23:J32) -> 0 | L33: =SUM(L23:L32) -> 0
E35: Docentes Tiempo Parcial / Hora Cátedra
B37: Máximo 8 Horas | C37: Valor semanal | D37: Función(Buscar) | E37: Periodo de contratación | F37: Costo por Semestre I | G37: Costo por Semestre II | H37: Aprobado SI-NO | I37: Costo Semestre 1 | J37: Costo Semestre 2 | K37: Observaciones | L37: Ejecución | M37: Observaciones de la Ejecución
C38: =IF(B38>8,0,B38*BaseSalarial!$D$9) -> 0 | D38: =IF(C38<=(BaseSalarial!$D$9*8),C38,0)*4 -> 0 | E38: Elija | F38: =IF(E38="4 MESES Semestre 1",D38*4,IF(E38="4 MESES Semestre 2",0,IF(E38="8 Meses",D38*4,IF(E38="10 Meses",D38*5,IF(E38="11 Meses",D38*5.5,IF(E38="1 Año",D38*6,0)))))) -> 0 | G38: =IF(E38="4 MESES Semestre 1",0,IF(E38="4 MESES Semestre 2",D38*4,IF(E38="8 Meses",D38*4,IF(E38="10 Meses",D38*5,IF(E38="11 Meses",D38*5.5,IF(E38="1 Año",D38*6,0)))))) -> 0 | H38: NO | I38: =IF(H38="SI",F38,IF(H38="NO",0,"Sin comprobar")) -> 0 | J38: =IF(H38="SI",G38,IF(H38="NO",0,"Sin comprobar")) -> 0
C39: =IF(B39>8,0,B39*BaseSalarial!$D$9) -> 0 | D39: =IF(C39<=(BaseSalarial!$D$9*8),C39,0)*4 -> 0 | E39: Elija | F39: =IF(E39="4 MESES Semestre 1",D39*4,IF(E39="4 MESES Semestre 2",0,IF(E39="8 Meses",D39*4,IF(E39="10 Meses",D39*5,IF(E39="11 Meses",D39*5.5,IF(E39="1 Año",D39*6,0)))))) -> 0 | G39: =IF(E39="4 MESES Semestre 1",0,IF(E39="4 MESES Semestre 2",D39*4,IF(E39="8 Meses",D39*4,IF(E39="10 Meses",D39*5,IF(E39="11 Meses",D39*5.5,IF(E39="1 Año",D39*6,0)))))) -> 0 | H39: NO | I39: =IF(H39="SI",F39,IF(H39="NO",0,"Sin comprobar")) -> 0 | J39: =IF(H39="SI",G39,IF(H39="NO",0,"Sin comprobar")) -> 0
C40: =IF(B40>8,0,B40*BaseSalarial!$D$9) -> 0 | D40: =IF(C40<=(BaseSalarial!$D$9*8),C40,0)*4 -> 0 | E40: Elija | F40: =IF(E40="4 MESES Semestre 1",D40*4,IF(E40="4 MESES Semestre 2",0,IF(E40="8 Meses",D40*4,IF(E40="10 Meses",D40*5,IF(E40="11 Meses",D40*5.5,IF(E40="1 Año",D40*6,0)))))) -> 0 | G40: =IF(E40="4 MESES Semestre 1",0,IF(E40="4 MESES Semestre 2",D40*4,IF(E40="8 Meses",D40*4,IF(E40="10 Meses",D40*5,IF(E40="11 Meses",D40*5.5,IF(E40="1 Año",D40*6,0)))))) -> 0 | H40: NO | I40: =IF(H40="SI",F40,IF(H40="NO",0,"Sin comprobar")) -> 0 | J40: =IF(H40="SI",G40,IF(H40="NO",0,"Sin comprobar")) -> 0
C41: =IF(B41>8,0,B41*BaseSalarial!$D$9) -> 0 | D41: =IF(C41<=(BaseSalarial!$D$9*8),C41,0)*4 -> 0 | E41: Elija | F41: =IF(E41="4 MESES Semestre 1",D41*4,IF(E41="4 MESES Semestre 2",0,IF(E41="8 Meses",D41*4,IF(E41="10 Meses",D41*5,IF(E41="11 Meses",D41*5.5,IF(E41="1 Año",D41*6,0)))))) -> 0 | G41: =IF(E41="4 MESES Semestre 1",0,IF(E41="4 MESES Semestre 2",D41*4,IF(E41="8 Meses",D41*4,IF(E41="10 Meses",D41*5,IF(E41="11 Meses",D41*5.5,IF(E41="1 Año",D41*6,0)))))) -> 0 | H41: NO | I41: =IF(H41="SI",F41,IF(H41="NO",0,"Sin comprobar")) -> 0 | J41: =IF(H41="SI",G41,IF(H41="NO",0,"Sin comprobar")) -> 0
C42: =IF(B42>8,0,B42*BaseSalarial!$D$9) -> 0 | D42: =IF(C42<=(BaseSalarial!$D$9*8),C42,0)*4 -> 0 | E42: Elija | F42: =IF(E42="4 MESES Semestre 1",D42*4,IF(E42="4 MESES Semestre 2",0,IF(E42="8 Meses",D42*4,IF(E42="10 Meses",D42*5,IF(E42="11 Meses",D42*5.5,IF(E42="1 Año",D42*6,0)))))) -> 0 | G42: =IF(E42="4 MESES Semestre 1",0,IF(E42="4 MESES Semestre 2",D42*4,IF(E42="8 Meses",D42*4,IF(E42="10 Meses",D42*5,IF(E42="11 Meses",D42*5.5,IF(E42="1 Año",D42*6,0)))))) -> 0 | H42: NO | I42: =IF(H42="SI",F42,IF(H42="NO",0,"Sin comprobar")) -> 0 | J42: =IF(H42="SI",G42,IF(H42="NO",0,"Sin comprobar")) -> 0
C43: =IF(B43>8,0,B43*BaseSalarial!$D$9) -> 0 | D43: =IF(C43<=(BaseSalarial!$D$9*8),C43,0)*4 -> 0 | E43: Elija | F43: =IF(E43="4 MESES Semestre 1",D43*4,IF(E43="4 MESES Semestre 2",0,IF(E43="8 Meses",D43*4,IF(E43="10 Meses",D43*5,IF(E43="11 Meses",D43*5.5,IF(E43="1 Año",D43*6,0)))))) -> 0 | G43: =IF(E43="4 MESES Semestre 1",0,IF(E43="4 MESES Semestre 2",D43*4,IF(E43="8 Meses",D43*4,IF(E43="10 Meses",D43*5,IF(E43="11 Meses",D43*5.5,IF(E43="1 Año",D43*6,0)))))) -> 0 | H43: NO | I43: =IF(H43="SI",F43,IF(H43="NO",0,"Sin comprobar")) -> 0 | J43: =IF(H43="SI",G43,IF(H43="NO",0,"Sin comprobar")) -> 0
C44: =IF(B44>8,0,B44*BaseSalarial!$D$9) -> 0 | D44: =IF(C44<=(BaseSalarial!$D$9*8),C44,0)*4 -> 0 | E44: Elija | F44: =IF(E44="4 MESES Semestre 1",D44*4,IF(E44="4 MESES Semestre 2",0,IF(E44="8 Meses",D44*4,IF(E44="10 Meses",D44*5,IF(E44="11 Meses",D44*5.5,IF(E44="1 Año",D44*6,0)))))) -> 0 | G44: =IF(E44="4 MESES Semestre 1",0,IF(E44="4 MESES Semestre 2",D44*4,IF(E44="8 Meses",D44*4,IF(E44="10 Meses",D44*5,IF(E44="11 Meses",D44*5.5,IF(E44="1 Año",D44*6,0)))))) -> 0 | H44: NO | I44: =IF(H44="SI",F44,IF(H44="NO",0,"Sin comprobar")) -> 0 | J44: =IF(H44="SI",G44,IF(H44="NO",0,"Sin comprobar")) -> 0
C45: =IF(B45>8,0,B45*BaseSalarial!$D$9) -> 0 | D45: =IF(C45<=(BaseSalarial!$D$9*8),C45,0)*4 -> 0 | E45: Elija | F45: =IF(E45="4 MESES Semestre 1",D45*4,IF(E45="4 MESES Semestre 2",0,IF(E45="8 Meses",D45*4,IF(E45="10 Meses",D45*5,IF(E45="11 Meses",D45*5.5,IF(E45="1 Año",D45*6,0)))))) -> 0 | G45: =IF(E45="4 MESES Semestre 1",0,IF(E45="4 MESES Semestre 2",D45*4,IF(E45="8 Meses",D45*4,IF(E45="10 Meses",D45*5,IF(E45="11 Meses",D45*5.5,IF(E45="1 Año",D45*6,0)))))) -> 0 | H45: NO | I45: =IF(H45="SI",F45,IF(H45="NO",0,"Sin comprobar")) -> 0 | J45: =IF(H45="SI",G45,IF(H45="NO",0,"Sin comprobar")) -> 0
C46: =IF(B46>8,0,B46*BaseSalarial!$D$9) -> 0 | D46: =IF(C46<=(BaseSalarial!$D$9*8),C46,0)*4 -> 0 | E46: Elija | F46: =IF(E46="4 MESES Semestre 1",D46*4,IF(E46="4 MESES Semestre 2",0,IF(E46="8 Meses",D46*4,IF(E46="10 Meses",D46*5,IF(E46="11 Meses",D46*5.5,IF(E46="1 Año",D46*6,0)))))) -> 0 | G46: =IF(E46="4 MESES Semestre 1",0,IF(E46="4 MESES Semestre 2",D46*4,IF(E46="8 Meses",D46*4,IF(E46="10 Meses",D46*5,IF(E46="11 Meses",D46*5.5,IF(E46="1 Año",D46*6,0)))))) -> 0 | H46: NO | I46: =IF(H46="SI",F46,IF(H46="NO",0,"Sin comprobar")) -> 0 | J46: =IF(H46="SI",G46,IF(H46="NO",0,"Sin comprobar")) -> 0
C47: =IF(B47>8,0,B47*BaseSalarial!$D$9) -> 0 | D47: =IF(C47<=(BaseSalarial!$D$9*8),C47,0)*4 -> 0 | E47: Elija | F47: =IF(E47="4 MESES Semestre 1",D47*4,IF(E47="4 MESES Semestre 2",0,IF(E47="8 Meses",D47*4,IF(E47="10 Meses",D47*5,IF(E47="11 Meses",D47*5.5,IF(E47="1 Año",D47*6,0)))))) -> 0 | G47: =IF(E47="4 MESES Semestre 1",0,IF(E47="4 MESES Semestre 2",D47*4,IF(E47="8 Meses",D47*4,IF(E47="10 Meses",D47*5,IF(E47="11 Meses",D47*5.5,IF(E47="1 Año",D47*6,0)))))) -> 0 | H47: NO | I47: =IF(H47="SI",F47,IF(H47="NO",0,"Sin comprobar")) -> 0 | J47: =IF(H47="SI",G47,IF(H47="NO",0,"Sin comprobar")) -> 0
F48: =SUM(F38:F47) -> 0 | G48: =SUM(G38:G47) -> 0 | I48: =SUM(I38:I47) -> 0 | J48: =SUM(J38:J47) -> 0 | L48: =SUM(L38:L47) -> 0

Sheet POS
A2: Seleccione la cualificación | B2: Relación Salario | C2: Total Docentes | D2: Cantidad Horas | E2: Periodo de contratación | F2: Totales | G2: Costo por Semestre I | H2: Costo por Semestre II | I2: Aprobado SI-NO | J2: Costo Semestre 1 | K2: Costo Semestre 2 | L2: Observaciones | M2: Ejecución | N2: Observaciones de la Ejecución
A3: Elija | B3: =IFERROR(VLOOKUP(A3,BaseSalarial!$G$20:$H$22,2,0),"0") -> 0 | E3: Elija | F3: =C3*D3*B3 -> 0 | G3: =IF(E3="Semestre 1",F3,IF(E3="Semestre 2",0,0)) -> 0 | H3: =IF(E3="Semestre 1",0,IF(E3="Semestre 2",F3,0)) -> 0 | I3: NO | J3: =IF(I3="SI",G3,IF(I3="NO",0,"Sin comprobar")) -> 0 | K3: =IF(I3="SI",H3,IF(I3="NO",0,"Sin comprobar")) -> 0
A4: Elija | B4: =IFERROR(VLOOKUP(A4,BaseSalarial!$G$20:$H$22,2,0),"0") -> 0 | E4: Elija | F4: =C4*D4*B4 -> 0 | G4: =IF(E4="Semestre 1",F4,IF(E4="Semestre 2",0,0)) -> 0 | H4: =IF(E4="Semestre 1",0,IF(E4="Semestre 2",F4,0)) -> 0 | I4: NO | J4: =IF(I4="SI",G4,IF(I4="NO",0,"Sin comprobar")) -> 0 | K4: =IF(I4="SI",H4,IF(I4="NO",0,"Sin comprobar")) -> 0
A5: Elija | B5: =IFERROR(VLOOKUP(A5,BaseSalarial!$G$20:$H$22,2,0),"0") -> 0 | E5: Elija | F5: =C5*D5*B5 -> 0 | G5: =IF(E5="Semestre 1",F5,IF(E5="Semestre 2",0,0)) -> 0 | H5: =IF(E5="Semestre 1",0,IF(E5="Semestre 2",F5,0)) -> 0 | I5: NO | J5: =IF(I5="SI",G5,IF(I5="NO",0,"Sin comprobar")) -> 0 | K5: =IF(I5="SI",H5,IF(I5="NO",0,"Sin comprobar")) -> 0
A6: Elija | B6: =IFERROR(VLOOKUP(A6,BaseSalarial!$G$20:$H$22,2,0),"0") -> 0 | E6: Elija | F6: =C6*D6*B6 -> 0 | G6: =IF(E6="Semestre 1",F6,IF(E6="Semestre 2",0,0)) -> 0 | H6: =IF(E6="Semestre 1",0,IF(E6="Semestre 2",F6,0)) -> 0 | I6: NO | J6: =IF(I6="SI",G6,IF(I6="NO",0,"Sin comprobar")) -> 0 | K6: =IF(I6="SI",H6,IF(I6="NO",0,"Sin comprobar")) -> 0
A7: Elija | B7: =IFERROR(VLOOKUP(A7,BaseSalarial!$G$20:$H$22,2,0),"0") -> 0 | E7: Elija | F7: =C7*D7*B7 -> 0 | G7: =IF(E7="Semestre 1",F7,IF(E7="Semestre 2",0,0)) -> 0 | H7: =IF(E7="Semestre 1",0,IF(E7="Semestre 2",F7,0)) -> 0 | I7: NO | J7: =IF(I7="SI",G7,IF(I7="NO",0,"Sin comprobar")) -> 0 | K7: =IF(I7="SI",H7,IF(I7="NO",0,"Sin comprobar")) -> 0
A8: Elija | B8: =IFERROR(VLOOKUP(A8,BaseSalarial!$G$20:$H$22,2,0),"0") -> 0 | E8: Elija | F8: =C8*D8*B8 -> 0 | G8: =IF(E8="Semestre 1",F8,IF(E8="Semestre 2",0,0)) -> 0 | H8: =IF(E8="Semestre 1",0,IF(E8="Semestre 2",F8,0)) -> 0 | I8: NO | J8: =IF(I8="SI",G8,IF(I8="NO",0,"Sin comprobar")) -> 0 | K8: =IF(I8="SI",H8,IF(I8="NO",0,"Sin comprobar")) -> 0
A9: Elija | B9: =IFERROR(VLOOKUP(A9,BaseSalarial!$G$20:$H$22,2,0),"0") -> 0 | E9: Elija | F9: =C9*D9*B9 -> 0 | G9: =IF(E9="Semestre 1",F9,IF(E9="Semestre 2",0,0)) -> 0 | H9: =IF(E9="Semestre 1",0,IF(E9="Semestre 2",F9,0)) -> 0 | I9: NO | J9: =IF(I9="SI",G9,IF(I9="NO",0,"Sin comprobar")) -> 0 | K9: =IF(I9="SI",H9,IF(I9="NO",0,"Sin comprobar")) -> 0
A10: Elija | B10: =IFERROR(VLOOKUP(A10,BaseSalarial!$G$20:$H$22,2,0),"0") -> 0 | E10: Elija | F10: =C10*D10*B10 -> 0 | G10: =IF(E10="Semestre 1",F10,IF(E10="Semestre 2",0,0)) -> 0 | H10: =IF(E10="Semestre 1",0,IF(E10="Semestre 2",F10,0)) -> 0 | I10: NO | J10: =IF(I10="SI",G10,IF(I10="NO",0,"Sin comprobar")) -> 0 | K10: =IF(I10="SI",H10,IF(I10="NO",0,"Sin comprobar")) -> 0
A11: Elija | B11: =IFERROR(VLOOKUP(A11,BaseSalarial!$G$20:$H$22,2,0),"0") -> 0 | E11: Elija | F11: =C11*D11*B11 -> 0 | G11: =IF(E11="Semestre 1",F11,IF(E11="Semestre 2",0,0)) -> 0 | H11: =IF(E11="Semestre 1",0,IF(E11="Semestre 2",F11,0)) -> 0 | I11: NO | J11: =IF(I11="SI",G11,IF(I11="NO",0,"Sin comprobar")) -> 0 | K11: =IF(I11="SI",H11,IF(I11="NO",0,"Sin comprobar")) -> 0
A12: Elija | B12: =IFERROR(VLOOKUP(A12,BaseSalarial!$G$20:$H$22,2,0),"0") -> 0 | E12: Elija | F12: =C12*D12*B12 -> 0 | G12: =IF(E12="Semestre 1",F12,IF(E12="Semestre 2",0,0)) -> 0 | H12: =IF(E12="Semestre 1",0,IF(E12="Semestre 2",F12,0)) -> 0 | I12: NO | J12: =IF(I12="SI",G12,IF(I12="NO",0,"Sin comprobar")) -> 0 | K12: =IF(I12="SI",H12,IF(I12="NO",0,"Sin comprobar")) -> 0
A13: Elija | B13: =IFERROR(VLOOKUP(A13,BaseSalarial!$G$20:$H$22,2,0),"0") -> 0 | E13: Elija | F13: =C13*D13*B13 -> 0 | G13: =IF(E13="Semestre 1",F13,IF(E13="Semestre 2",0,0)) -> 0 | H13: =IF(E13="Semestre 1",0,IF(E13="Semestre 2",F13,0)) -> 0 | I13: NO | J13: =IF(I13="SI",G13,IF(I13="NO",0,"Sin comprobar")) -> 0 | K13: =IF(I13="SI",H13,IF(I13="NO",0,"Sin comprobar")) -> 0
A14: Elija | B14: =IFERROR(VLOOKUP(A14,BaseSalarial!$G$20:$H$22,2,0),"0") -> 0 | E14: Elija | F14: =C14*D14*B14 -> 0 | G14: =IF(E14="Semestre 1",F14,IF(E14="Semestre 2",0,0)) -> 0 | H14: =IF(E14="Semestre 1",0,IF(E14="Semestre 2",F14,0)) -> 0 | I14: NO | J14: =IF(I14="SI",G14,IF(I14="NO",0,"Sin comprobar")) -> 0 | K14: =IF(I14="SI",H14,IF(I14="NO",0,"Sin comprobar")) -> 0
... A17: Elija | B17: =IFERROR(VLOOKUP(A17,BaseSalarial!$G$20:$H$22,2,0),"0") -> 0 | E17: Elija | F17: =C17*D17*B17 -> 0 | G17: =IF(E17="Semestre 1",F17,IF(E17="Semestre 2",0,0)) -> 0 | H17: =IF(E17="Semestre 1",0,IF(E17="Semestre 2",F17,0)) -> 0 | I17: NO | J17: =IF(I17="SI",G17,IF(I17="NO",0,"Sin comprobar")) -> 0 | K17: =IF(I17="SI",H17,IF(I17="NO",0,"Sin comprobar")) -> 0
F18: =SUM(F3:F17) -> 0 | G18: =SUM(G3:G17) -> 0 | H18: =SUM(H3:H17) -> 0 | J18: =SUM(J3:J17) -> 0 | K18: =SUM(K3:K17) -> 0 | M18: =SUM(M3:M17) -> 0

Sheet CONSOLIDADO
A2: Programa / Area / Proceso | B2: Proceso Misional ____________ Complementario | C2: I-COD | D2: MACROPROYECTO | E2: METAS PROYECTO | F2: indicador | G2: ENTREGABLE - EVIDENCIA | H2: ACTIVIDADES | I2: TIPO | J2: CANTIDAD ESPERADA PARA 2023 | K2: SEGUIMIENTO
K3: FECHA PREVISTA DE EVALUACIÓN Y SEGUIMIENTO | N3: FECHA PREVISTA DE EVALUACIÓN Y SEGUIMIENTO | Q3: FECHA PREVISTA DE EVALUACIÓN Y SEGUIMIENTO | T3: FECHA PREVISTA DE EVALUACIÓN Y SEGUIMIENTO
K4: Del 3 al 15 de abril de 2023 | N4: Del 6 al 17 de Junio | Q4: Del 2 al 14 de Octubre | T4: Del 13 al 25 de Noviembre
K5: % de cumplimiento | L5: Evidencia | M5: Observaciones | N5: % de cumplimiento | O5: Evidencia | P5: Observaciones | Q5: % de cumplimiento | R5: Evidencia | S5: Observaciones | T5: % de cumplimiento | U5: Evidencia | V5: Observaciones
A6: ADEMAGRO VIRTAL | B6: DOCENCIA | C6: DOC-03 | D6: 3. ACOMPAÑAMIENTO Y ÉXITO ESTUDIANTIL | E6: 3. Fortalecimiento del desempeño pruebas Saber pro, a través de estrategias académicas y culturales. | G6: Documento con analisis de resultados Actas de asistencia | H6: Análisis de los resultados de Pruebas SaberPro programas virtuales Talleres extra curriculares Capacitación docente del alcance de las pruebas y elaboración de cuestionarios afines a la metodología de las pruebas saber pro. | I6: IMPACTO
A7: ADEMAGRO VIRTAL | B7: DOCENCIA | C7: DOC-04 | D7: 3. ACOMPAÑAMIENTO Y ÉXITO ESTUDIANTIL | E7: 3. Fortalecimiento segundo idioma en docentes y estudiantes | G7: Curso de ingles virtualizado | H7: Diseño y Virtualización diplomado/seminario de ingles (120h) | I7: IMPACTO
A8: ADEMAGRO VIRTAL | B8: DOCENCIA | C8: DOC-05 | D8: 3. ACOMPAÑAMIENTO Y ÉXITO ESTUDIANTIL | E8: 3. Capacitación y actualización pedagógica de los docentes | G8: Actas de asistencia Memorias | H8: Capacitación en didactica y pedagogia virtual | I8: FORMACIÓN
A9: ADEMAGRO VIRTAL | B9: DOCENCIA | C9: DOC-06 | D9: 3. ACOMPAÑAMIENTO Y ÉXITO ESTUDIANTIL | E9: 3. Rubricas de Evaluación. | G9: Rubricas de evaluación | H9: Elaboración de rubricas de evaluación de las asignaturas de los programas virtuales | I9: IMPACTO
A10: ADEMAGRO VIRTAL | B10: EXTENSIÓN Y PROYECCIÓN SOCIAL | C10: EXT-01 | D10: 3. ACOMPAÑAMIENTO Y ÉXITO ESTUDIANTIL | E10: 3. Gestionar los programas, acciones y servicios de bienestar que contribuyen a la formación integral de la comunidad estudiantil, el mejoramiento de la calidad de vida y la construcción de comunidad | F10: EN CONSTRUCCIÓN | G10: Actas (Registro) de asistencia | H10: Socialización de los servicios de bienestar para los estudiantes virtuales. Establecer un canal virtual para la atención de estudiantes virtuales. | I10: IMPACTO
A11: ADEMAGRO VIRTAL | B11: EXTENSIÓN Y PROYECCIÓN SOCIAL | C11: EXT-02 | D11: 3. ACOMPAÑAMIENTO Y ÉXITO ESTUDIANTIL | E11: 3. Implementación de estrategias para la Disminución de la deserción y ausentismo de los estudiantes. | G11: Informe y actas de seguimiento | H11: Identificación de estudiantes ausentes y posibles causas Acompañamiento académico a estudiantes que presentan dificultades en su desarrollo academico | I11: IMPACTO
A12: ADEMAGRO VIRTAL | B12: COMPLETARIOS | C12: COM-04 | D12: 3. ACOMPAÑAMIENTO Y ÉXITO ESTUDIANTIL | E12: 3. Establecer canales de contacto eficientes. | G12: Medio de comunicación alterno | H12: Establecer un medio de comunicación alterno al correo institucional y plataforma UNIVIDA para la atención a la comunidad academica (programas virtuales) | I12: IMPACTO
A13: ADMINISTRACIÓN DE EMPRESAS | B13: DOCENCIA | C13: DOC-01 | D13: 3. ACOMPAÑAMIENTO Y ÉXITO ESTUDIANTIL | E13: 3. Fortalecimiento del desempeño pruebas Saber pro, a través de estrategias académicas y culturales. | G13: Informe de resultados de pruebas saber Pro, Informe de Analsis de resultados de los simulacros y las pruebas, Plan de Mejora. | H13: Discución en comité sobre resultados y elementos a mejorar 1. Convocatoria para inscripciones | I13: GESTIÓN
A14: ADMINISTRACIÓN DE EMPRESAS | B14: DOCENCIA | D14: 3. ACOMPAÑAMIENTO Y ÉXITO ESTUDIANTIL | E14: 3. Fortalecimiento del desempeño pruebas Saber pro, a través de estrategias académicas y culturales. | H14: 2. participacion en el simulacro | I14: GESTIÓN
A15: ADMINISTRACIÓN DE EMPRESAS | B15: DOCENCIA | D15: 3. ACOMPAÑAMIENTO Y ÉXITO ESTUDIANTIL | E15: 3. Fortalecimiento del desempeño pruebas Saber pro, a través de estrategias académicas y culturales. | H15: 3. realizacion del simulacro | I15: GESTIÓN
A16: ADMINISTRACIÓN DE EMPRESAS | B16: DOCENCIA | D16: 3. ACOMPAÑAMIENTO Y ÉXITO ESTUDIANTIL | E16: 3. Fortalecimiento del desempeño pruebas Saber pro, a través de estrategias académicas y culturales. | H16: 4. presentación de la prueba | I16: IMPACTO
A17: ADMINISTRACIÓN DE EMPRESAS | B17: DOCENCIA | D17: 3. ACOMPAÑAMIENTO Y ÉXITO ESTUDIANTIL | E17: 3. Fortalecimiento del desempeño pruebas Saber pro, a través de estrategias académicas y culturales. | H17: 5. Informe con analisi de resultados tanto del simulacro como de la prueba | I17: IMPACTO
A18: ADMINISTRACIÓN DE EMPRESAS | B18: DOCENCIA | D18: 3. ACOMPAÑAMIENTO Y ÉXITO ESTUDIANTIL | E18: 3. Fortalecimiento del desempeño pruebas Saber pro, a través de estrategias académicas y culturales. | H18: 6. Elaboración plan de mejora | I18: IMPACTO
A19: ADMINISTRACIÓN DE EMPRESAS | B19: DOCENCIA | C19: DOC-04 | D19: 3. ACOMPAÑAMIENTO Y ÉXITO ESTUDIANTIL | E19: 3. Fortalecimiento segundo idioma en docentes y estudiantes | G19: Certificado | H19: Participacion de curso de ingles para docentes y directivos. | I19: FORMACIÓN
A20: ADMINISTRACIÓN DE EMPRESAS | B20: DOCENCIA | C20: DOC-05 | D20: 3. ACOMPAÑAMIENTO Y ÉXITO ESTUDIANTIL | E20: 3. Fortalecimiento segundo idioma en docentes y estudiantes | G20: Microcurriculo | H20: Incluir en el microcurriculo de almenos una materia por semestre una actividad, lectura o taller en segundo idioma | I20: IMPACTO
A21: ADMINISTRACIÓN DE EMPRESAS | B21: DOCENCIA | C21: DOC-06 | D21: 3. ACOMPAÑAMIENTO Y ÉXITO ESTUDIANTIL | E21: 3. Visitas técnicas y salidas de campo. | G21: Informe de la visita técnica o salidas de campo, Microcurriculo que evdencie el resultado de aprendizage a partir de la salida tecnica | H21: Planeación de la visita técnica | I21: GESTIÓN
A22: ADMINISTRACIÓN DE EMPRESAS | B22: DOCENCIA | D22: 3. ACOMPAÑAMIENTO Y ÉXITO ESTUDIANTIL | E22: 3. Visitas técnicas y salidas de campo. | H22: Convocatoria a estudiantes de la visita técnica | I22: GESTIÓN
A23: ADMINISTRACIÓN DE EMPRESAS | B23: DOCENCIA | D23: 3. ACOMPAÑAMIENTO Y ÉXITO ESTUDIANTIL | E23: 3. Visitas técnicas y salidas de campo. | H23: Ejecuciónd de la visita | I23: IMPACTO
A24: ADMINISTRACIÓN DE EMPRESAS | B24: DOCENCIA | C24: DOC-07 | D24: 3. ACOMPAÑAMIENTO Y ÉXITO ESTUDIANTIL | E24: 3. Aumentar el material bibliográfico actual, a través de la compra de nuevos de nuevos ejemplares. | G24: Orden de compra del material bibliográfico | H24: Ejecuciónd de la visita | I24: IMPACTO
A25: ADMINISTRACIÓN DE EMPRESAS | B25: DOCENCIA | D25: 3. ACOMPAÑAMIENTO Y ÉXITO ESTUDIANTIL | E25: 3. Aumentar el material bibliográfico actual, a través de la compra de nuevos de nuevos ejemplares. | H25: Identificar necesidades de material bibliográfico requerido en comité curricular | I25: GESTIÓN
A26: ADMINISTRACIÓN DE EMPRESAS | B26: DOCENCIA | D26: 3. ACOMPAÑAMIENTO Y ÉXITO ESTUDIANTIL | E26: 3. Aumentar el material bibliográfico actual, a través de la compra de nuevos de nuevos ejemplares. | H26: Cotizar el material con el acompañamiento de la persona encargada de la biblioteca. | I26: IMPACTO
A27: ADMINISTRACIÓN DE EMPRESAS | B27: DOCENCIA | C27: DOC-08 | D27: 3. ACOMPAÑAMIENTO Y ÉXITO ESTUDIANTIL | E27: 3. Seguimiento de los estudiantes a través del Sistema de Alertas Tempranas. | G27: Informe de seguimiento a estudiantes identificados a traves de alertas tempranas y plan de mejora para los mismos. | H27: Revisar información de sistemas de alertas tempranas para estudiantes, en discusión en comité curricular, identificando las estrategias a utilizarse con dichos estudisntes en compañia de Bienestar institucional. | I27: IMPACTO
A28: ADMINISTRACIÓN DE EMPRESAS | B28: DOCENCIA | D28: 3. ACOMPAÑAMIENTO Y ÉXITO ESTUDIANTIL | E28: 3. Seguimiento de los estudiantes a través del Sistema de Alertas Tempranas. | H28: Diseño y ejecución de plan | I28: IMPACTO
A29: ADMINISTRACIÓN DE EMPRESAS | B29: COMPLETARIOS | C29: COM-06 | D29: 3. ACOMPAÑAMIENTO Y ÉXITO ESTUDIANTIL | E29: 3. Fortalecer los procesos de seguimiento y evaluación a la deserción estudiantil y repitencia. | F29: EN CONSTRUCCIÓN | G29: INFORMES Y LISTADOS DE ASISTENCIA A CURSOS INTRODUCTORIOS Y DE REFUERZO. | H29: Realizar cursos introductorios en competencias básicas y en los principales ejes disciplinares del programa para estudiantes de primer semestre. Ofertar cursos y talleres de refuerzo obligatorios para estudiantes en bajo rendimiento; asi como en el uso de herramientas ofimaticas nivel básico e intermedio. | I29: FORMACIÓN
A30: ARQUITECTURA POPAYÁN | B30: DOCENCIA | C30: DOC-10 | D30: 3. ACOMPAÑAMIENTO Y ÉXITO ESTUDIANTIL | E30: 3. Reconocer las capacidades en el estudiante, y fomentar su convivencia con el entorno en congruencia con una personalidad reflexiva, crítica, sensible, creativa y, responsable, tocando las dimensiones que como sujeto social. | F30: EN CONSTRUCCIÓN | G30: Documento interno con la caracterización, actas y listado de asistencia en la construcción de este. | H30: Diagnosticar los diferentes aspectos del estudiante que ingresa al programa, entendiendo las debilidades y fortalezas, en comprensión del contexto y de los posibles resultados para su formación en arquitectura. Realizar análisis continuo con el sector externo para verificar la concordancia de la meta propuesta con el sector Institucional. | I30: IMPACTO
A31: ARQUITECTURA POPAYÁN | B31: DOCENCIA | C31: DOC-11 | D31: 3. ACOMPAÑAMIENTO Y ÉXITO ESTUDIANTIL | E31: 3. Proyectar la formación de estudiantes con enfoque de sostenibilidad y comprensión de distintas formas de expresión y cultura. | F31: EN CONSTRUCCIÓN | G31: Talleres, seminarios y/o cursos. | H31: Realizar espacios educación continua con las diferentes instituciones en convenio y/o instituciones que puedan ser fortaleza interinstitucional. Jornadas de formación integral, lideradas por Bienestar Institucional que permitan evidenciar el resultado de la meta. | I31: IMPACTO
A32: ARQUITECTURA POPAYÁN | B32: DOCENCIA | C32: DOC-12 | D32: 3. ACOMPAÑAMIENTO Y ÉXITO ESTUDIANTIL | E32: 3. Autosostenibilidad: Implementar el plan de mercadeo para captar mayor volumen de estudiantes. | F32: EN CONSTRUCCIÓN | G32: Documento y listado de asistencia en la construcción de este. | H32: Estrategias derivadas de la construcción del diagnostico donde incluye la caracterización de estudiante del programa de arquitectura FUP. | I32: IMPACTO
A33: ARQUITECTURA POPAYÁN | B33: DOCENCIA | C33: DOC-13 | D33: 3. ACOMPAÑAMIENTO Y ÉXITO ESTUDIANTIL | E33: 3. Fomentar las estrategias de impacto del pensamiento crítico | F33: EN CONSTRUCCIÓN | G33: Talleres, seminarios y/o cursos, actas, correos y asistencias. | H33: Talleres en articulación con ingeniería de sistemas en la construcción de pensamientos diversos. Generar una estrategia con el entorno que permita evidenciar el aporte de egresado en la solución de problemáticas. | I33: FORMACIÓN
A34: ARQUITECTURA POPAYÁN | B34: DOCENCIA | C34: DOC-14 | D34: 3. ACOMPAÑAMIENTO Y ÉXITO ESTUDIANTIL | E34: 3. Fortalecimiento del desempeño pruebas Saber pro, a través de estrategias académicas y culturales. | F34: EN CONSTRUCCIÓN | G34: 2 pruebas simulacros e informe de resultados, actas y listado de asistencia en la construcción de este. | H34: Talleres en conjunto y/o simulacro pruebas saber desde la lectura y el pensamiento crítico. Análisis de resultados tanto de simulacros como de las pruebas Saber Pro. Estructuración de mecanismos para el Plan de Mejora. | I34: FORMACIÓN
A35: ARQUITECTURA POPAYÁN | B35: DOCENCIA | C35: DOC-15 | D35: 3. ACOMPAÑAMIENTO Y ÉXITO ESTUDIANTIL | E35: 3. Fortalecimiento de las competencias de estudiantes y docentes en habilidades blandas y comunicación asertiva. | F35: EN CONSTRUCCIÓN | G35: Talleres, seminarios y/o cursos, actas, correos, asistencias y documento que evidencia el análisis de la meta. | H35: 4 Talleres en alianza con programa de comunicaciones (escuela de lectoescritura) y con Bienestar Universitario, para el fortalecimiento al estudiante y el docente en estos aspectos. | I35: FORMACIÓN
A36: ARQUITECTURA POPAYÁN | B36: DOCENCIA | C36: DOC-16 | D36: 3. ACOMPAÑAMIENTO Y ÉXITO ESTUDIANTIL | E36: 3. Definir y/o estandarizar en el cuerpo de docente, para asumir las funciones de Docencia, Investigación y Proyección Social | F36: EN CONSTRUCCIÓN | G36: Documento final como apoyo al programa, actas y listado de asistencia en la construcción de este. | H36: A partir del diagnóstico realizado para los docentes del programa en el año 2022, formular la pertinencia de ellos en cada aspecto. Y con ello consolidar la comunidad de docentes para que contribuyan en el fortalecimiento de las funciones sustantivas, soportes de la cualificación docente y la distribución de labores del programa. | I36: IMPACTO
A37: ARQUITECTURA POPAYÁN | B37: DOCENCIA | C37: DOC-17 | D37: 3. ACOMPAÑAMIENTO Y ÉXITO ESTUDIANTIL | E37: 3. Capacitación y actualización pedagógica de los docentes | F37: EN CONSTRUCCIÓN | G37: Talleres, seminarios y/o cursos, actas, correos y asistencias. | H37: Capacitación en aprendizajes y pedagogías en la arquitectura, articulado con la escuela de desarrollo profesional. | I37: FORMACIÓN
A38: ARQUITECTURA POPAYÁN | B38: DOCENCIA | C38: DOC-18 | D38: 3. ACOMPAÑAMIENTO Y ÉXITO ESTUDIANTIL | E38: 3. Rubricas de Evaluación. | F38: EN CONSTRUCCIÓN | G38: Rúbrica de evaluación | H38: Diseño y estructura de la rúbrica del Programa. De esa manera, poder estructurar un documento en consolidación de la meta requerida como parte del proceso de formación. | I38: IMPACTO
A39: ARQUITECTURA POPAYÁN | B39: DOCENCIA | C39: DOC-19 | D39: 3. ACOMPAÑAMIENTO Y ÉXITO ESTUDIANTIL | E39: 3. Visitas técnicas y salidas de campo. | F39: EN CONSTRUCCIÓN | G39: Informe final de asignatura con experiencia de aula, información necesaria en compilación para mejoramiento de estructuras pedagógicas y desarrollo de los talleres de arquitectura en la FUP. Además que evidencie la importancia en la labor docente por la pertinencia del reconocimiento de los antecedentes y referentes. | H39: Visitas de los talleres de arquitectura a diferentes espacios de aprendizaje arquitectónico, para visualizar y comprender los diferentes funcionamientos según el contexto. | I39: GESTIÓN
A40: ARQUITECTURA POPAYÁN | B40: EXTENSIÓN Y PROYECCIÓN SOCIAL | C40: EXT-01 | D40: 3. ACOMPAÑAMIENTO Y ÉXITO ESTUDIANTIL | E40: 3. Fortalecimiento de medios educativos e infraestructura tecnológica como herramienta de las actividades académicas de proyección social e investigación. | F40: EN CONSTRUCCIÓN | G40: Herramientas tecnológicas y de construcción. | H40: Fortalecimiento de Fab Lab, consultorio arquitectónico y laboratorio de construcción, desde estos espacios propender por el desarrollo del pensamiento diverso (tecnologías) del estudiante y el docente. Además, potencializar en la región en alianza con Ingeniería Industrial la prestación del servicio del Fab Lab con otras instituciones gubernamentales, privadas y demás. | I40: IMPACTO
A41: ARQUITECTURA POPAYÁN | B41: COMPLETARIOS | C41: DOC-01 | D41: 3. ACOMPAÑAMIENTO Y ÉXITO ESTUDIANTIL | E41: 3. Aumentar el material bibliográfico actual, a través de la compra de nuevos de nuevos ejemplares. | F41: EN CONSTRUCCIÓN | G41: Material bibliográfico | H41: Actualización fisica y digital de la biblioteca. | I41: IMPACTO
A42: COMUNICACIÓN SOCIAL (VIRTUAL) | B42: DOCENCIA | C42: DOC-10 | D42: 3. ACOMPAÑAMIENTO Y ÉXITO ESTUDIANTIL | E42: 3. Proyectar la formación de estudiantes con enfoque de sostenibilidad y comprensión de distintas formas de expresión y cultura. | G42: Número de estudiantes participando de actividades de cultura, artes y otros escenarios de expresión y crecimiento personal. | H42: En conjunto con Bienestar Universitario estructurar un plan o participar del institucional, frente a las actividades propuestas en torno a la expresión y cultura. | I42: IMPACTO
A43: COMUNICACIÓN SOCIAL (VIRTUAL) | B43: DOCENCIA | C43: DOC-11 | D43: 3. ACOMPAÑAMIENTO Y ÉXITO ESTUDIANTIL | E43: 3. Definir y/o estandarizar en el cuerpo de docente, para asumir las funciones de Docencia, Investigación y Proyección Social | G43: Labor docente y asignación de coordinaciones y progyectos del programa según los perfiles de los docentes y funciones sustantivas | H43: Seguimiento y control de la labor docente y asignaciones realizadas frente a las funciones sustantivas y proyectos transversales del programa | I43: GESTIÓN
A44: COMUNICACIÓN SOCIAL (VIRTUAL) | B44: DOCENCIA | C44: DOC-12 | D44: 3. ACOMPAÑAMIENTO Y ÉXITO ESTUDIANTIL | E44: 3. Fortalecimiento segundo idioma en docentes y estudiantes | G44: Capacitaciones e inclusión de material bibliográfico en los microcurrículos de las asignaturas del programa | H44: Fomentar en los docentes la capacitación en un segundo idioma. Incluir en los algunos de los microcurrículos del programa textos en un segundo idioma. | I44: FORMACIÓN
A45: COMUNICACIÓN SOCIAL (VIRTUAL) | B45: DOCENCIA | C45: DOC-13 | D45: 3. ACOMPAÑAMIENTO Y ÉXITO ESTUDIANTIL | E45: 3. Crear espacios también de formación docente desde la parte artística. | G45: Participación de docentes en actividades artísticas y de cultura. | H45: Articularnos con el plan de trabajo de bienestar institucional frente a las actividades artísticas y de cultura ofertadas para los docentes de la institución y del programa | I45: GESTIÓN
A46: COMUNICACIÓN SOCIAL (VIRTUAL) | B46: DOCENCIA | C46: DOC-14 | D46: 3. ACOMPAÑAMIENTO Y ÉXITO ESTUDIANTIL | E46: 3. Capacitación y actualización pedagógica de los docentes | G46: Capacitaciones en torno a la pedagogía, metodología y técnicas para el quehacer docente | H46: Fomentar en los docentes la asistencia a capacitaciones y actualización en pedagogía para la mejora en las prácticas o métodos de enseñanza | I46: FORMACIÓN
A47: COMUNICACIÓN SOCIAL (VIRTUAL) | B47: DOCENCIA | C47: DOC-15 | D47: 3. ACOMPAÑAMIENTO Y ÉXITO ESTUDIANTIL | E47: 3. Visitas técnicas y salidas de campo. | G47: Informe de las salidas académicas que soporte a través de imágenes y compromisos (de ser posible) la participación docente y de estudiantes | H47: Gestionar y coordinar visitas técnicas a diferentes medios y organizaciones de la comunicación social, el periodismo y afines para el aprendizaje real en el campo de trabajo | I47: GESTIÓN
A48: COMUNICACIÓN SOCIAL (VIRTUAL) | B48: DOCENCIA | C48: DOC-16 | D48: 3. ACOMPAÑAMIENTO Y ÉXITO ESTUDIANTIL | E48: 3. Aumentar el material bibliográfico actual, a través de la compra de nuevos de nuevos ejemplares. | G48: Listado de referencias bibliográficas adquiridas | H48: Organización y proceso de compra de material bibliográfico para el programa. | I48: GESTIÓN
A49: COMUNICACIÓN SOCIAL (VIRTUAL) | B49: DOCENCIA | C49: DOC-17 | D49: 3. ACOMPAÑAMIENTO Y ÉXITO ESTUDIANTIL | E49: 3. Fortalecimiento de medios educativos e infraestructura tecnológica como herramienta de las actividades académicas de proyección social e investigación. | G49: Número de bases de datos, revistas digitales o repositorios institucionales, evaluadas, revisadas y/o actualizadas | H49: Revisión y adquisión de medios educativos e infraestructura tecnológica que soporte las funciones sustantivas del programa académico | I49: IMPACTO
A50: COMUNICACIÓN SOCIAL (VIRTUAL) | B50: DOCENCIA | C50: DOC-18 | D50: 3. ACOMPAÑAMIENTO Y ÉXITO ESTUDIANTIL | E50: 3. Fortalecimiento del desempeño pruebas Saber pro, a través de estrategias académicas y culturales. | G50: Cursos cortos y asesorías frente a la preparación de las pruebas Saber PRO. | H50: Cronograma de trabajo en el marcode la presentación de las pruebas Saber PRO tanto en competencias generales como específicas. | I50: IMPACTO
A51: COMUNICACIÓN SOCIAL (VIRTUAL) | B51: DOCENCIA | C51: DOC-19 | D51: 3. ACOMPAÑAMIENTO Y ÉXITO ESTUDIANTIL | E51: 3. Seguimiento de los estudiantes a través del Sistema de Alertas Tempranas. | G51: Informe de atención y acompañamiento a aquellos estudiantes que se han identificado con posibles causas de deserción o bajo rendimiento | H51: En conjunto con Bienestar Universitario realizar el acompañamiento a aquellos estudiantes que presentan alertas frente a deserción, bajo rendiiento entre otras, y que deben ser remitidos al área de psicología, escuela de lectoescritura u otras dependencias según su especificidad | I51: GESTIÓN
A52: COMUNICACIÓN SOCIAL (VIRTUAL) | B52: DOCENCIA | C52: DOC-20 | D52: 3. ACOMPAÑAMIENTO Y ÉXITO ESTUDIANTIL | E52: 3. Implementación de estrategias para la Disminución de la deserción y ausentismo de los estudiantes. | G52: Informe de atención y acompañamiento a aquellos estudiantes que se han identificado con posibles causas de deserción o bajo rendimiento | H52: En conjunto con Bienestar Universitario realizar el acompañamiento a aquellos estudiantes que presentan alertas frente a deserción, bajo rendiiento entre otras, y que deben ser remitidos al área de psicología, escuela de lectoescritura u otras dependencias según su especificidad | I52: IMPACTO
A53: COMUNICACIÓN SOCIAL (VIRTUAL) | B53: DOCENCIA | C53: DOC-21 | D53: 3. ACOMPAÑAMIENTO Y ÉXITO ESTUDIANTIL | E53: 3. Fortalecer los procesos de seguimiento y evaluación a la deserción estudiantil y repitencia. | G53: Informe de atención y acompañamiento a aquellos estudiantes que se han identificado con posibles causas de deserción o bajo rendimiento | H53: En conjunto con Bienestar Universitario realizar el acompañamiento a aquellos estudiantes que presentan alertas frente a deserción, bajo rendiiento entre otras, y que deben ser remitidos al área de psicología, escuela de lectoescritura u otras dependencias según su especificidad | I53: IMPACTO
... A73: DERECHO POPAYÁN | B73: DOCENCIA | C73: DOC-02 | D73: 3. ACOMPAÑAMIENTO Y ÉXITO ESTUDIANTIL | E73: 3. Fortalecimiento de las competencias de estudiantes y docentes en habilidades blandas y comunicación asertiva. | G73: Actas de asistencia, análisis de impacto DOCUMENTO DONDE EVIDENCIE EL ANALISIS DE LA META. | H73: Capacitaciones para la comunidad educativa con el propósito de fortalecer las habiliades blandas y la comunicación acertiva | I73: FORMACIÓN
A74: DERECHO POPAYÁN | B74: DOCENCIA | C74: DOC-03 | D74: 3. ACOMPAÑAMIENTO Y ÉXITO ESTUDIANTIL | E74: 3. Fortalecimiento de las competencias de estudiantes y docentes en habilidades blandas y comunicación asertiva. | I74: FORMACIÓN
A75: DERECHO POPAYÁN | B75: DOCENCIA | C75: DOC-04 | D75: 3. ACOMPAÑAMIENTO Y ÉXITO ESTUDIANTIL | E75: 3. Fortalecimiento segundo idioma en docentes y estudiantes | G75: MICROCURRICULO CON EL COMPONENTE EN UN SEGUNDO IDIOMA. | H75: Formación Docente en una segunda lengua Incluir en los algunos de los microcurrículos del programa textos en un segundo idioma. | I75: IMPACTO
A76: DERECHO POPAYÁN | B76: DOCENCIA | C76: DOC-06 | D76: 3. ACOMPAÑAMIENTO Y ÉXITO ESTUDIANTIL | E76: 3. Aumentar el material bibliográfico actual, a través de la compra de nuevos de nuevos ejemplares. | G76: Factura de Compra | H76: Renovación material bibliográfico | I76: GESTIÓN
A77: DERECHO POPAYÁN | B77: COMPLETARIOS | C77: COM-03 | D77: 3. ACOMPAÑAMIENTO Y ÉXITO ESTUDIANTIL | E77: 3. Fortalecimiento del desempeño pruebas Saber pro, a través de estrategias académicas y culturales. | F77: EN CONSTRUCCIÓN | G77: Listas de asistencia, fotografías. | H77: Realizar 1 taller en pruebas Saber Pro dirigido a docentes. Realizar 1 taller en pruebas Saber Pro dirigido a estudiantes. | I77: IMPACTO
A78: DERECHO POPAYÁN | B78: COMPLETARIOS | C78: COM-04 | D78: 3. ACOMPAÑAMIENTO Y ÉXITO ESTUDIANTIL | E78: 3. Capacitación y actualización pedagógica de los docentes | F78: EN CONSTRUCCIÓN | G78: Listas de asistencia, fotografías. | H78: Realizar un evento (Seminario, Taller, Simposio) dirigido a docentes sobre: estrategias pedagógicas, resultados de aprendizaje, inclusión y diversidad y herramientas TIC. | I78: IMPACTO
A79: DERECHO POPAYÁN | B79: COMPLETARIOS | C79: COM-05 | D79: 3. ACOMPAÑAMIENTO Y ÉXITO ESTUDIANTIL | E79: 3. Fortalecimiento de las competencias de estudiantes y docentes en habilidades blandas y comunicación asertiva. | F79: EN CONSTRUCCIÓN | G79: Listas de asistencia, fotografías. | H79: Realizar un evento (Seminario, Taller, Simposio) dirigido a estudiantes sobre: habilidades blandas y comunicación asertiva. | I79: IMPACTO
A80: DERECHO SANTANDER | B80: DOCENCIA | C80: DOC-05 | D80: 3. ACOMPAÑAMIENTO Y ÉXITO ESTUDIANTIL | E80: 3. Visitas técnicas y salidas de campo. | G80: Listados asistencia, fotografías e informes de gestión | H80: Diseño y propuesta en marcha de programa de relacionamiento local, como apuesta al escenario de interacción de espacios académicos con espacios prácticos dirigidos a la comunidad estudiantil | I80: IMPACTO
A81: INGENIERÍA DE SISTEMAS | B81: EXTENSIÓN Y PROYECCIÓN SOCIAL | C81: EXT-01 | D81: 3. ACOMPAÑAMIENTO Y ÉXITO ESTUDIANTIL | E81: 3. Reconocer las capacidades en el estudiante, y fomentar su convivencia con el entorno en congruencia con una personalidad reflexiva, crítica, sensible, creativa y, responsable, tocando las dimensiones que como sujeto social. | F81: EN CONSTRUCCIÓN | G81: Actas de sensibilización, acta o informe de intervenciones psicologicas, formatos institucionales, medicion del impacto en elos estudiantes. | H81: Diseño de estrategia de acompañamiento a los estudaintes proyecto ROCKET, donde se motiva, se autosostiene a través de relacionamiento con sector externo con actividades de impacto social. Reconocimiento académico, cultural, emprendimiento, investigación de los estudiantes del Programa. Reconocimiento a los estudiantes que cursan la oferta de: 1. Proyecto social TIC del plan de estudios del programa 2. Refrigerios y brindis para los participantes des diferentes cursos de proyecto social TIC Este aspecto está considerado en el documento maestro, como desarrollo actividades de servicio social a la comunidad. | I81: IMPACTO
A82: INGENIERÍA DE SISTEMAS | B82: EXTENSIÓN Y PROYECCIÓN SOCIAL | C82: EXT-02 | D82: 3. ACOMPAÑAMIENTO Y ÉXITO ESTUDIANTIL | E82: 3. Proyectar la formación de estudiantes con enfoque de sostenibilidad y comprensión de distintas formas de expresión y cultura. | F82: EN CONSTRUCCIÓN | G82: Actas, piezas graficas, correos insitucionales | H82: Capacitación en temas de formación integral estudiantes, egresados y comunidad académica, Semana social y Cultural, articulado con Binestar Insitucional para el fortalecimiento de de la formacion integral del estudiante. | I82: FORMACIÓN
A83: INGENIERÍA DE SISTEMAS | B83: EXTENSIÓN Y PROYECCIÓN SOCIAL | C83: EXT-03 | D83: 3. ACOMPAÑAMIENTO Y ÉXITO ESTUDIANTIL | E83: 3. Proponer ejercicios de doble titulación entre los programas de pregrado | F83: EN CONSTRUCCIÓN | G83: Actas, Mesas de Trabajo, Informe de Gestión 1 documento PROPUESTA de doble titulacion para el programa | H83: Generar acercamiento con otras instituciones, a través de analisis de doble tirulacion con otras IES de esta manera fortalcer la articulación en aspectos de doble titulación y fortalecimiento de competencias, Movilidades Regional, Nacionales e Internacionales - (Internacionalización) | I83: IMPACTO
A84: INGENIERÍA DE SISTEMAS | B84: EXTENSIÓN Y PROYECCIÓN SOCIAL | C84: EXT-04 | D84: 3. ACOMPAÑAMIENTO Y ÉXITO ESTUDIANTIL | E84: 3. Definir campañas de preinscripción con beneficios. | F84: EN CONSTRUCCIÓN | G84: Actas, piezas graficas, correos insitucionales, Informe de Gestión | H84: Actividades de mercadeo del programa académico para el fortalecimiento del número de estudiantes, Participación de estudiantes de la región en actividades de la semana social (Scratch Day, Maratón del pensamiento computacional) articulado con Bienestar Insitucional para el fortalecimiento de de la formacion integral del estudiante. | I84: IMPACTO
A85: INGENIERÍA DE SISTEMAS | B85: EXTENSIÓN Y PROYECCIÓN SOCIAL | C85: EXT-06 | D85: 3. ACOMPAÑAMIENTO Y ÉXITO ESTUDIANTIL | E85: 3. Posicionamiento institucional a través del marketing educativo y la creación de valor sostenible alineando el propósito institucional a la generación de beneficios para estudiantes. | F85: EN CONSTRUCCIÓN | G85: Actas, listado de asitencia, evidencia fotográfica | H85: Encuentro con empresas e instituciones con el fin de fortalecer vinculos desde los trabajos de grado, practicas empresariales y proyectos esternos e internos. | I85: IMPACTO
A86: INGENIERÍA DE SISTEMAS | B86: EXTENSIÓN Y PROYECCIÓN SOCIAL | C86: EXT-07 | D86: 3. ACOMPAÑAMIENTO Y ÉXITO ESTUDIANTIL | E86: 3. Fomentar las estrategias de impacto del pensamiento crítico | F86: EN CONSTRUCCIÓN | G86: Actas, listado de asitencia, evidencia fotográfica, estrategia de seguimineto del egresado. | H86: Participacion en eventos nacionales e internacionales como estrategia académicas y participación en eventos como pensamiento computacional, análisis crítico, habilidades matemático. Asi mismo articularse con el sector externo y egresados en el medio a traves de estrategias para identificar el aporte del egresado en la solucion de problemas. | I86: IMPACTO
A87: INGENIERÍA DE SISTEMAS | B87: EXTENSIÓN Y PROYECCIÓN SOCIAL | C87: EXT-08 | D87: 3. ACOMPAÑAMIENTO Y ÉXITO ESTUDIANTIL | E87: 3. Fortalecimiento del desempeño pruebas Saber pro, a través de estrategias académicas y culturales. | F87: EN CONSTRUCCIÓN | G87: Actas, listado de asitencia, evidencia fotográfica, Informe de Gestión Informe de resultados de simulacro y pruebas saber pro. Plan de mejora | H87: Estrategias académicas para el desarrollo de habilidades y competencias desde 1 a 9 semestre en cuanto a las pruebas saber pro 1. Realización de pruebas internas pilotos articuladas con el sector empresarial y egresados, con el objetivo de identificar la situación del estudiante por áreas de conocimiento y competencias. Análisis de resultados tanto de simulacros como de las pruebas saber pro. Estructuración de mecanismos para el plan de mejora. | I87: IMPACTO
A88: INGENIERÍA DE SISTEMAS | B88: EXTENSIÓN Y PROYECCIÓN SOCIAL | C88: EXT-09 | D88: 3. ACOMPAÑAMIENTO Y ÉXITO ESTUDIANTIL | E88: 3. Establecer la Escuela de Lectoescritura como un espacio que brinde apoyos en asignaturas como lectoescritura sino también asesorías en procesos lectores y escritos, capacitaciones Pruebas Saber PRO, Club. | F88: EN CONSTRUCCIÓN | G88: Actas, listado de asitencia, evidencia fotográfica, documento análisis de las estrategias de capacitación y talleres de competencias lectoescritoras. | H88: Actividades de articulación con capacitaciones y talleres para los estudiantes de 1 a 9 semestre en habilidades lector escritoras y redacción científica, articulados con la escuela de desarrollo profesoral. | I88: FORMACIÓN
A89: INGENIERÍA DE SISTEMAS | B89: EXTENSIÓN Y PROYECCIÓN SOCIAL | C89: EXT-10 | D89: 3. ACOMPAÑAMIENTO Y ÉXITO ESTUDIANTIL | E89: 3. Fortalecimiento de las competencias de estudiantes y docentes en habilidades blandas y comunicación asertiva. | F89: EN CONSTRUCCIÓN | G89: Actas, listado de asitencia, evidencia fotográfica, diseño de una estretgia para medir el impacto de las conferencias y capacitaciones, a traves de una herramienta o prueba del area correspondiente. | H89: Actividades de articulación con capacitaciones y talleres para los estudiantes, egresados y docentes de 1 a 9 semestre en habilidades blandas e inteligencia emocional. Articulado con la oficina de Bienestar Institucional. | I89: FORMACIÓN
A90: INGENIERÍA DE SISTEMAS | B90: EXTENSIÓN Y PROYECCIÓN SOCIAL | C90: EXT-11 | D90: 3. ACOMPAÑAMIENTO Y ÉXITO ESTUDIANTIL | E90: 3. Permitir la conjunción de disciplinas a través de la interacción entre facultades y programas a partir de las cuales se generan nuevos perfiles de egreso. | F90: EN CONSTRUCCIÓN | G90: Actas, listado de asitencia, evidencia fotográfica. Documento PEP donde se describa la estrategia y medición del impacto de la articulación, a través de una herramienta o prueba del area correspondiente. Y Actualiacion de los perfiles de egreso a traves d ela dinamica de la estrategia. | H90: Articulación en trabajos de grado y electivas profesionales con el fin de aumentar las opciones a cursar y generar una articulación por facultad e IES a nivel nacional, regional o internacional. Realizacion de encuentros interdisciplinares del conocimiento entre los estudiantes y docentes de los programas de la Facultad | I90: IMPACTO
A91: INGENIERÍA DE SISTEMAS | B91: EXTENSIÓN Y PROYECCIÓN SOCIAL | C91: EXT-12 | D91: 3. ACOMPAÑAMIENTO Y ÉXITO ESTUDIANTIL | E91: 3. Definir y/o estandarizar en el cuerpo de docente, para asumir las funciones de Docencia, Investigación y Proyección Social | F91: EN CONSTRUCCIÓN | G91: Actas, listado de asitencia, evidencia fotográfica, Documento maestro, Documento PEP, donde se describen los perfiles en las areas misionales. | H91: Ejercicio de análisis de pertinencia de acuerdo al área disciplinar Consolidación de comunidad de docentes que contribuyan al fortalecimiento de las funciones sustantivas y soportes de la cualificación docente y la distribución de las funciones en el quehacer del programa. | I91: IMPACTO
A92: INGENIERÍA DE SISTEMAS | B92: EXTENSIÓN Y PROYECCIÓN SOCIAL | C92: EXT-13 | D92: 3. ACOMPAÑAMIENTO Y ÉXITO ESTUDIANTIL | E92: 3. Fortalecimiento segundo idioma en docentes y estudiantes | F92: EN CONSTRUCCIÓN | G92: Actas, listado de asitencia, Microcurriculos con articulos cientificos producto del proceso investigativo, bibliografía en segundo idioma y microcurrículo con al menos un contenido en segundo idioma. | H92: Estrategia de fortalcimiento de competencias en un segundo idioma a traves de procesos de investigacion, movilidades (instancias cortas y largas) en IES afines al area. Revision de microcurriculos para el fortalecimiento de un segundo idioma, articulado con la escuela de desarrollo profesoral. | I92: IMPACTO
... A107: INGENIERÍA DE SISTEMAS | B107: EXTENSIÓN Y PROYECCIÓN SOCIAL | C107: EXT-28 | D107: 3. ACOMPAÑAMIENTO Y ÉXITO ESTUDIANTIL | E107: 3. Analizar y diseñar el sistema para generar reportes de alerta temprana de potencial repitencia y deserción académica. | F107: EN CONSTRUCCIÓN | G107: Informe de gestión, Remisión a bienestar institucional | H107: Identificación de las problemáticas, Seguimiento a estudiantes, vinculación de estudiantes a estrategias del programa y bienestar institucional | I107: IMPACTO
A108: INGENIERÍA INDUSTRIAL POPAYÁN | B108: DOCENCIA | C108: DOC-05 | D108: 3. ACOMPAÑAMIENTO Y ÉXITO ESTUDIANTIL | E108: 3. Visitas técnicas y salidas de campo. | G108: Formatos de visitas técnicas, listados de asistencia, formatos de viáticos | H108: Realización de al menos 5 prácticas empresariales por semestre con estudiantes de los diferentes semestres para fortalecer su conocimiento teorico práctico. Solicitud de viáticos para los docentes. | I108: IMPACTO
A109: INGENIERÍA INDUSTRIAL POPAYÁN | B109: EXTENSIÓN Y PROYECCIÓN SOCIAL | C109: EXT-42 | D109: 3. ACOMPAÑAMIENTO Y ÉXITO ESTUDIANTIL | E109: 3. Visitas técnicas y salidas de campo. | G109: listado de aistencia - informe vista | H109: Visita empresarial con alumnos de primer semestre (empresa local) | I109: GESTIÓN
A110: INGENIERÍA INDUSTRIAL POPAYÁN | B110: EXTENSIÓN Y PROYECCIÓN SOCIAL | C110: EXT-43 | D110: 3. ACOMPAÑAMIENTO Y ÉXITO ESTUDIANTIL | E110: 3. Visitas técnicas y salidas de campo. | G110: listado de aistencia - informe vista | H110: vista empresarial con alumnos de primer semestre (empresa nacional) | I110: GESTIÓN
A111: INGENIERÍA INDUSTRIAL POPAYÁN | B111: COMPLETARIOS | C111: COM-17 | D111: 3. ACOMPAÑAMIENTO Y ÉXITO ESTUDIANTIL | E111: 3. Proponer ejercicios de doble titulación entre los programas de pregrado | G111: Convenios, actas de reunión, registros fotográficos, propuesta de doble titulación. | H111: Análisis de la pertinancia de la doble titulación. Internacionalización del curriculo con otras IES que posean programas de Ingeniería Industrial o similares. | I111: IMPACTO
A112: INGENIERÍA INDUSTRIAL POPAYÁN | B112: COMPLETARIOS | C112: COM-18 | D112: 3. ACOMPAÑAMIENTO Y ÉXITO ESTUDIANTIL | E112: 3. Autosostenibilidad: Implementar el plan de mercadeo para captar mayor volumen de estudiantes. | G112: Convenios, actas de reunión, registros fotográficos. | H112: Formular estrategias de mercadeo a través de visitas a colegios de la ciudad o colegios rurales del departamente. Participación en ferias empresariales, traslado de personal docente y administrativo para promción del programa académico. | I112: IMPACTO
A113: INGENIERÍA INDUSTRIAL POPAYÁN | B113: COMPLETARIOS | C113: COM-19 | D113: 3. ACOMPAÑAMIENTO Y ÉXITO ESTUDIANTIL | E113: 3. Definir campañas de preinscripción con beneficios. | G113: Actas de reunión, convenios, registros fotográficos. | H113: Sencibilización de estudiantes de últimos grados de bachiller con instituciones que aportan mayos numero de sus egresados en el progrma de ingeniería Industrial según el resultados de la caracterización. | I113: GESTIÓN
A114: INGENIERÍA INDUSTRIAL POPAYÁN | B114: COMPLETARIOS | C114: COM-20 | D114: 3. ACOMPAÑAMIENTO Y ÉXITO ESTUDIANTIL | E114: 3. Fortalecimiento del desempeño pruebas Saber pro, a través de estrategias académicas y culturales. | G114: Registro de simulacros, listsdos de asistencia, actas de reunión, solicitud de viáticos. | H114: Fortalecer la estrategias en función de mejorar los resultados de los estudiantes en las pruebas de estado. Articulación de buenas prácticas que hayan realizado otros programas académicos (Arquitectura) frente al análisis del desempeño en resultados Saber PRO. Análisis de la información histórica y estadística. Buscar IES pares para realizar mesas de tabajo en función de articulación de estrategias (ACOFI) | I114: IMPACTO
A115: INGENIERÍA INDUSTRIAL POPAYÁN | B115: COMPLETARIOS | C115: COM-21 | D115: 3. ACOMPAÑAMIENTO Y ÉXITO ESTUDIANTIL | E115: 3. Establecer la Escuela de Lectoescritura como un espacio que brinde apoyos en asignaturas como lectoescritura sino también asesorías en procesos lectores y escritos, capacitaciones Pruebas Saber PRO, Club. | G115: Listados de asistencia, actas de reunión, cursos certificados, documento de la propuesta | H115: Realización de cursos cortos como estrategias en pro del fortalecimento en estas competencias blandas dirigido a estudiantes y docentes. Realización de cursos de habilidades blandas con estudiantes de práctica de los programas psicología y trabajo social. Articulación con la EDP | I115: IMPACTO
A116: INGENIERÍA INDUSTRIAL POPAYÁN | B116: COMPLETARIOS | C116: COM-22 | D116: 3. ACOMPAÑAMIENTO Y ÉXITO ESTUDIANTIL | E116: 3. Definir y/o estandarizar en el cuerpo de docente, para asumir las funciones de Docencia, Investigación y Proyección Social | G116: Solicitud de viáticos, listados de asistencia y actas de reunión. | H116: Estandarización de estregias, procesos, guías y demás con el programa de Sede Santander de Q. con los docentes de los programas académicos. Consolidación de comunidad de docentes que contribuyan al fortalecimiento de las funciones sustantivas y soportes de la cualificación docente y la distribución de labores de los programas de la facultad. | I116: IMPACTO
A117: INGENIERÍA INDUSTRIAL POPAYÁN | B117: COMPLETARIOS | C117: COM-23 | D117: 3. ACOMPAÑAMIENTO Y ÉXITO ESTUDIANTIL | E117: 3. Fortalecimiento segundo idioma en docentes y estudiantes | G117: Solicitud de viáticos, listados de asistencia y actas de reunión, certificados, etc. Microcurrículos con al menos un módulo en segundo idioma. | H117: Afianzar los conocimientos y estrategias a través de cursos, insentivos y realización de mesas de trabajo con los docentes para fortalecer sus conocimientos en un segundo idioma. Articulación con la EDP | I117: GESTIÓN
A118: INGENIERÍA INDUSTRIAL POPAYÁN | B118: COMPLETARIOS | C118: COM-24 | D118: 3. ACOMPAÑAMIENTO Y ÉXITO ESTUDIANTIL | E118: 3. Capacitación y actualización pedagógica de los docentes | G118: Listados de asistencia, actas de reunión, cursos certificados. Documento que Describa las necesidades propias de autodesarrollo de los docentes y administrativos relacionado con el saber hacer, (El desarrollo) - Crecimiento personal y profesional, de acuerdo a su qué hacer (Micros - labor administrativa) | H118: Descubrir las necesidades propias de autodesarrollo de los docentes y administrativos relacionado con el saber hacer, (El desarrollo) - Crecimiento personal y profesional, de acuerdo a su qué hacer (Micros - labor administrativa) Capacitación articulada con la EDP | I118: GESTIÓN
A119: INGENIERÍA INDUSTRIAL POPAYÁN | B119: COMPLETARIOS | C119: COM-25 | D119: 3. ACOMPAÑAMIENTO Y ÉXITO ESTUDIANTIL | E119: 3. Aumentar el material bibliográfico actual, a través de la compra de nuevos de nuevos ejemplares. | G119: Formatos de solicitud de marterial bibliográfico, correos electrónicos. Se garantizará que el material bibliográfico sea suficiente y necesario para dar cumplimiento a las temáticas de los microcurrículos. | H119: Solicitar la actualización de material bibliográficos según los contenidos curriculares del programa académico. Cotización y compra de textos | I119: GESTIÓN
A120: INGENIERÍA INDUSTRIAL POPAYÁN | B120: COMPLETARIOS | C120: COM-26 | D120: 3. ACOMPAÑAMIENTO Y ÉXITO ESTUDIANTIL | E120: 3. Seguimiento de los estudiantes a través del Sistema de Alertas Tempranas. | G120: Actas de asistencia, actas de reunión de comité curriular, registros fotográficos. | H120: Aplicar estrategias en articulación con Bienestar Universitarios para prevenier el riesgo de ausentismo estudiantil. Realizar mesas de trabajo con estudiantes. Generar estrategias de comunicación con los docentes para detectar casos especiales con sus estudiantes. | I120: IMPACTO
A121: INGENIERÍA INDUSTRIAL POPAYÁN | B121: COMPLETARIOS | C121: COM-27 | D121: 3. ACOMPAÑAMIENTO Y ÉXITO ESTUDIANTIL | E121: 3. Implementación de estrategias para la Disminución de la deserción y ausentismo de los estudiantes. | H121: Realizar estrategias con el cuerpo docente y planta administrativa del programa académico para generar y articular estrategias de contactabilidad de estudiantes desertores y ausentes. Encuentros presenciales o viertuales para determinar causas y posibles causas de insersión estudiantil. | I121: IMPACTO
A122: INGENIERÍA INDUSTRIAL POPAYÁN | B122: COMPLETARIOS | C122: COM-28 | D122: 3. ACOMPAÑAMIENTO Y ÉXITO ESTUDIANTIL | E122: 3. Fortalecer los procesos de seguimiento y evaluación a la deserción estudiantil y repitencia. | H122: Fortalecer o contruir estrategias conjunatas con Bienestar para evaluar la deserción y repintencia, los cuales son indicadores del proceso de docencia y permiten realizar estudios que generen actividades en pro de estos indicadores. Realizar mesas de traajo, capacitaciones, analisis de resultados. Socializar las estrategias y los análisis para la articulación con los programa en AP. Santander de Q. | I122: IMPACTO
A123: INGENIERÍA INDUSTRIAL SANTANDER | B123: DOCENCIA | C123: DOC-04 | D123: 3. ACOMPAÑAMIENTO Y ÉXITO ESTUDIANTIL | E123: 3. Fortalecimiento segundo idioma en docentes y estudiantes | G123: Certificados finalización de cursos, listados de asistencia | H123: Brindar a los docentes del programa la accesibilidad a potenciar una segunda lengua a través de los cursos ofertados por la EDP | I123: IMPACTO
A124: INGENIERÍA INDUSTRIAL SANTANDER | B124: DOCENCIA | C124: DOC-05 | D124: 3. ACOMPAÑAMIENTO Y ÉXITO ESTUDIANTIL | E124: 3. Fortalecimiento de las competencias de estudiantes y docentes en habilidades blandas y comunicación asertiva. | G124: Certificados finalización de cursos, listados de asistencia | H124: Ofertar por parte de los programas y el área de bienestar del campus Álvaro Ulcué Chocué, espacios para el fortalecimiento de competencias en lo referido, a través de talleres o cursos. | I124: FORMACIÓN
A125: INGENIERÍA INDUSTRIAL SANTANDER | B125: DOCENCIA | C125: DOC-06 | D125: 3. ACOMPAÑAMIENTO Y ÉXITO ESTUDIANTIL | E125: 3. Capacitación y actualización pedagógica de los docentes | G125: Certificados finalización de cursos, listados de asistencia | H125: Ofertas cursos de actualización de docencia universitaria y otros cursos mas de la competencia. | I125: FORMACIÓN
A126: INGENIERÍA INDUSTRIAL SANTANDER | B126: COMPLETARIOS | C126: COM-13 | D126: 3. ACOMPAÑAMIENTO Y ÉXITO ESTUDIANTIL | E126: 3. Autosostenibilidad: Implementar el plan de mercadeo para captar mayor volumen de estudiantes. | G126: Listados de asistencia, registro fotográfico | H126: Generar estrategias de mercadeo en el área rural del municipio, a fin de llegar a toda la población | I126: IMPACTO
A127: INGENIERÍA INDUSTRIAL SANTANDER | B127: COMPLETARIOS | C127: COM-14 | D127: 3. ACOMPAÑAMIENTO Y ÉXITO ESTUDIANTIL | E127: 3. Fortalecimiento del desempeño pruebas Saber pro, a través de estrategias académicas y culturales. | G127: Actas de reunión, listados de asistencia, registro fotográfico | H127: Generar estrategias de corto, mediano y largo plazo, que asegure el aprendizaje, la calidad y el alcance de competencias desde un horizonte de Resultados del Aprendizaje. | I127: IMPACTO
A128: INGENIERÍA INDUSTRIAL SANTANDER | B128: COMPLETARIOS | C128: COM-15 | D128: 3. ACOMPAÑAMIENTO Y ÉXITO ESTUDIANTIL | E128: 3. Visitas técnicas y salidas de campo. | G128: Actas de reunión, listados de asistencia, registro fotográfico | H128: Realizar visitas técnicas a los laboratorios del programa en las sedes san josé y los robles | I128: IMPACTO
A129: INGENIERÍA INDUSTRIAL SANTANDER | B129: COMPLETARIOS | C129: COM-16 | D129: 3. ACOMPAÑAMIENTO Y ÉXITO ESTUDIANTIL | E129: 3. Aumentar el material bibliográfico actual, a través de la compra de nuevos de nuevos ejemplares. | G129: Formato de cotización y factura de compra | H129: Realizar cotizaciónes sobre la adquiscion de material bibliografico físico y/o digital. | I129: GESTIÓN
A130: INGENIERÍA INDUSTRIAL SANTANDER | B130: COMPLETARIOS | C130: COM-17 | D130: 3. ACOMPAÑAMIENTO Y ÉXITO ESTUDIANTIL | E130: 3. Aumentar el material bibliográfico actual, a través de la compra de nuevos de nuevos ejemplares. | H130: Realizar la compra de material bibliografico para el fortalecimiento académico del programa. | I130: GESTIÓN
A131: LICENCIATURA POPAYÁN | B131: DOCENCIA | C131: DOC-03 | D131: 3. ACOMPAÑAMIENTO Y ÉXITO ESTUDIANTIL | E131: 3. Aumentar el material bibliográfico actual, a través de la compra de nuevos de nuevos ejemplares. | F131: Número de Libros comprados para el centro de Consulta Pedagógico Artístico y Cultural de la Facultad de Educación San Camilo. | G131: Factura de Compra de Material Bibliográfico o formato de legalización de anticipos de material bibliográfico acorde a las áreas de formación. | H131: Compra de Material Bibliográfico en Educación Arte y Cultura acorde a las necesidades de las áreas de formación. | I131: GESTIÓN
A132: LICENCIATURA POPAYÁN | B132: DOCENCIA | C132: DOC-04 | D132: 3. ACOMPAÑAMIENTO Y ÉXITO ESTUDIANTIL | E132: 3. Capacitación y actualización pedagógica de los docentes | F132: Numero de docentes patrocinados por la FUP para estudios Posgraduales. | G132: Actas de espacios de capacitación y encuesta que describa el impacto y la evaluación de las capacitaciones. | H132: Socialización del Plan de Beneficios Institucional, en Articulación con la Escuela de desarrollo profesoral | I132: GESTIÓN
A133: LICENCIATURA POPAYÁN | B133: COMPLETARIOS | C133: COM-03 | D133: 3. ACOMPAÑAMIENTO Y ÉXITO ESTUDIANTIL | E133: 1. Implementar instrumentos de comunicación y divulgación, con el fin de promover un novedoso acercamiento hacia la comunidad educativa, | F133: Visualización del Micrositio del programa en la Página institucional. | G133: Micrositio del programa de LEAC | H133: Apoyo y acompañamiento en la divulgación de la información en nichos de Mercado y espacios publicitarios de interés en Educación, Arte y Cultura. | I133: GESTIÓN
A134: LICENCIATURA POPAYÁN | B134: COMPLETARIOS | C134: COM-10 | D134: 3. ACOMPAÑAMIENTO Y ÉXITO ESTUDIANTIL | E134: 3. Reconocer las capacidades en el estudiante, y fomentar su convivencia con el entorno en congruencia con una personalidad reflexiva, crítica, sensible, creativa y, responsable, tocando las dimensiones que como sujeto social. | F134: Listados de estudiantes asistentes a las capacitaciones de formación integral | G134: Listados de estudiantes asistentes a las capacitaciones de formación integral | H134: Capacitaciones en manejo del tiempo, técnicas de estudio, manejo de las emociones, comunicación acertiva entre otras en atención a las necesidades del estudiante del programa de LEAC. | I134: GESTIÓN
...

Sheet ANALISIS MACROS
B1: PROCESO MISIONAL | C1: N° de Actividades programadas | D1: %
B2: DOCENCIA | C2: =+COUNTIF(CONSOLIDADO!B:B,'ANALISIS MACROS'!B2) -> 171 | D2: =+C2/$C$6 -> 0.51351351
B3: INVESTIGACIÓN | C3: =+COUNTIF(CONSOLIDADO!B:B,'ANALISIS MACROS'!B3) -> 4 | D3: =+C3/$C$6 -> 0.012012012
B4: EXTENSIÓN Y PROYECCIÓN SOCIAL | C4: =+COUNTIF(CONSOLIDADO!B:B,'ANALISIS MACROS'!B4) -> 44 | D4: =+C4/$C$6 -> 0.13213213
B5: COMPLETARIOS | C5: =+COUNTIF(CONSOLIDADO!B:B,'ANALISIS MACROS'!B5) -> 114 | D5: =+C5/$C$6 -> 0.34234234
C6: =SUM(C2:C5) -> 333
C10: N° de Actividades programadas | D10: %
B11: 1. APROPIACIÓN: IDENTIDAD INSTITUCIONAL | C11: =+COUNTIF(CONSOLIDADO!D:D,'ANALISIS MACROS'!B11) -> 0 | D11: =+C11/$C$18 -> 0
B12: 2. SISTEMA INTERNO DE ASEGURAMIENTO DE LA CALIDAD | C12: =+COUNTIF(CONSOLIDADO!D:D,'ANALISIS MACROS'!B12) -> 0 | D12: =+C12/$C$18 -> 0
B13: 3. ACOMPAÑAMIENTO Y ÉXITO ESTUDIANTIL | C13: =+COUNTIF(CONSOLIDADO!D:D,'ANALISIS MACROS'!B13) -> 333 | D13: =+C13/$C$18 -> 1
B14: 4. NUEVOS ESCENARIOS DE APRENDIZAJE Y RECURSOS INSTITUCIONALES | C14: =+COUNTIF(CONSOLIDADO!D:D,'ANALISIS MACROS'!B14) -> 0 | D14: =+C14/$C$18 -> 0
B15: 5. ECOSISTEMA DE INNOVACIÓN | C15: =+COUNTIF(CONSOLIDADO!D:D,'ANALISIS MACROS'!B15) -> 0 | D15: =+C15/$C$18 -> 0
B16: 6. RELACIONAMIENTO CON EL MEDIO EXTERNO | C16: =+COUNTIF(CONSOLIDADO!D:D,'ANALISIS MACROS'!B16) -> 0 | D16: =+C16/$C$18 -> 0
B17: 7. DESARROLLO Y GESTIÓN ORGANIZACIONAL | C17: =+COUNTIF(CONSOLIDADO!D:D,'ANALISIS MACROS'!B17) -> 0 | D17: =+C17/$C$18 -> 0
C18: =SUM(C11:C17) -> 333
B22: 1. Intervenciones a estudiantes y docentes en sensibilizaciones en temáticas institucionales. | C22: =+COUNTIF(CONSOLIDADO!E:E,'ANALISIS MACROS'!B22) -> 0
B23: 1. Actualización del Proyecto Educativo Institucional | C23: =+COUNTIF(CONSOLIDADO!E:E,'ANALISIS MACROS'!B23) -> 3
B24: 1. Evaluación de los resultados de aprendizaje (Evaluación de las rubricas de enseñanza) | C24: =+COUNTIF(CONSOLIDADO!E:E,'ANALISIS MACROS'!B24) -> 1
B25: 1. Implementar instrumentos de comunicación y divulgación, con el fin de promover un novedoso acercamiento hacia la comunidad educativa, | C25: =+COUNTIF(CONSOLIDADO!E:E,'ANALISIS MACROS'!B25) -> 1
B26: 1. Construir un Plan Estratégico de Comunicación y Relacionamiento adecuado que permita establecer un contacto permanente y consecutivo con los grupos de interés. | C26: =+COUNTIF(CONSOLIDADO!E:E,'ANALISIS MACROS'!B26) -> 0
B27: 1. Actualizar de manera permanente los contenidos en medios de comunicación institucional en línea, tales como portal web y perfiles de redes sociales institucionales para brindar a la ciudadanía información oportuna, veraz y confiable. | C27: =+COUNTIF(CONSOLIDADO!E:E,'ANALISIS MACROS'!B27) -> 0
B28: 1. Difundir la información institucional a los diferentes grupos objetivos y públicos de interés sobre la gestión a través de acciones de comunicación externa, con el fin de propiciar el flujo adecuado y el acceso a la información. | C28: =+COUNTIF(CONSOLIDADO!E:E,'ANALISIS MACROS'!B28) -> 0
B29: 1. Generar impacto social mendiante la creación del boletin institucional. | C29: =+COUNTIF(CONSOLIDADO!E:E,'ANALISIS MACROS'!B29) -> 0
B30: 1. Garantizar el despliegue oportuno a las diferentes audiencias y estamentos universitarios, de los planes, proyectos, iniciativas y actividades puestas en marcha en el marco de los eventos que se realicen internos y externos. | C30: =+COUNTIF(CONSOLIDADO!E:E,'ANALISIS MACROS'!B30) -> 0
B31: 1. Establecer mecanismos de acción en materia de comunicación que permita responder a los diferentes retos institucionales. | C31: =+COUNTIF(CONSOLIDADO!E:E,'ANALISIS MACROS'!B31) -> 0
B32: 1. Construir y gestionar las relaciones internas y externas de la Universidad en procura de mejorar el prestigio institucional. | C32: =+COUNTIF(CONSOLIDADO!E:E,'ANALISIS MACROS'!B32) -> 0
B33: 1. Visibilizar la Universidad a nivel local, nacional e internacional a través de los medios masivos de comunicación y manejo estratégico de comunicación pública. | C33: =+COUNTIF(CONSOLIDADO!E:E,'ANALISIS MACROS'!B33) -> 0
... B55: 2. Autoevaluación: Revisión de la identidad institucional Evaluación de cada una de las áreas de gestión Establecimiento de las fortalezas y oportunidades de mejoramiento | C55: =+COUNTIF(CONSOLIDADO!E:E,'ANALISIS MACROS'!B55) -> 0
B56: 2. Elaboración del plan de mejoramiento: Formulación de objetivos Formulación de metas Definición de indicadores Definición de actividades y de sus responsables Elaboración del cronograma de actividades Definición de los recursos necesarios para la ejecución del plan de mejoramiento Divulgación del plan de mejoramiento a la comunidad educativa | C56: 21 | D56: REVISAR
B57: 2. Seguimiento y evaluación: Revisión del cumplimiento de los objetivos y metas del plan de mejoramiento Evaluación del plan de mejoramiento | C57: =+COUNTIF(CONSOLIDADO!E:E,'ANALISIS MACROS'!B57) -> 0
B58: 2. Procesos de autoevaluación: de orden académico (fases Renovaciones RC) y de orden administrativo. (Auditoria Interna) | C58: =+COUNTIF(CONSOLIDADO!E:E,'ANALISIS MACROS'!B58) -> 0
B59: 2. Crear una arquitectura de información que dé soporte a las metas de la Institución. | C59: =+COUNTIF(CONSOLIDADO!E:E,'ANALISIS MACROS'!B59) -> 0
B60: 2. Comunicación de los resultados de la autoevaluación y la evaluación del plan de mejoramiento. | C60: =+COUNTIF(CONSOLIDADO!E:E,'ANALISIS MACROS'!B60) -> 0
B61: 3. Política relacionada con el acceso justo a la educación superior. | C61: =+COUNTIF(CONSOLIDADO!E:E,'ANALISIS MACROS'!B61) -> 1
B62: 3. Establecer un Modelo de selección donde se identifiquen criterios incluyentes y equitativos. | C62: =+COUNTIF(CONSOLIDADO!E:E,'ANALISIS MACROS'!B62) -> 5
B63: 3. Presentar un esquema que integre lineamientos, estrategias y acciones dirigidas a mejorar la capacidad institucional y controlar el acceso de estudiantes. | C63: =+COUNTIF(CONSOLIDADO!E:E,'ANALISIS MACROS'!B63) -> 0
B64: 3. Reconocer las capacidades en el estudiante, y fomentar su convivencia con el entorno en congruencia con una personalidad reflexiva, crítica, sensible, creativa y, responsable, tocando las dimensiones que como sujeto social. | C64: =+COUNTIF(CONSOLIDADO!E:E,'ANALISIS MACROS'!B64) -> 12
B65: 3. Proyectar la formación de estudiantes con enfoque de sostenibilidad y comprensión de distintas formas de expresión y cultura. | C65: =+COUNTIF(CONSOLIDADO!E:E,'ANALISIS MACROS'!B65) -> 12
B66: 3. Establecer un Modelo Educativo Integral y Flexible que permita al estudiante conocer, hacer, ser, sentir, convivir. | C66: =+COUNTIF(CONSOLIDADO!E:E,'ANALISIS MACROS'!B66) -> 6
B67: 3. Proponer ejercicios de doble titulación entre los programas de pregrado | C67: =+COUNTIF(CONSOLIDADO!E:E,'ANALISIS MACROS'!B67) -> 6
B68: 3. Autosostenibilidad: Implementar el plan de mercadeo para captar mayor volumen de estudiantes. | C68: =+COUNTIF(CONSOLIDADO!E:E,'ANALISIS MACROS'!B68) -> 14
... B215: 7. La apreciación de la docencia por parte de los estudiantes La autoevaluación del profesor La valoración por parte del jefe inmediato. Trazar planes de mejora | C215: =+COUNTIF(CONSOLIDADO!E:E,'ANALISIS MACROS'!B215) -> 0
C216: =SUM(C22:C215) -> 332

Sheet Analisis Proyectos
B1: METAS DEL PLAN DE DESARROLLO | C1: CANTIDAD
B2: 1. Intervenciones a estudiantes y docentes en sensibilizaciones en temáticas institucionales. | C2: =+'ANALISIS MACROS'!C22 -> 0
B3: 1. Actualización del Proyecto Educativo Institucional | C3: =+'ANALISIS MACROS'!C23 -> 3
B4: 1. Evaluación de los resultados de aprendizaje (Evaluación de las rubricas de enseñanza) | C4: =+'ANALISIS MACROS'!C24 -> 1
B5: 1. Implementar instrumentos de comunicación y divulgación, con el fin de promover un novedoso acercamiento hacia la comunidad educativa, | C5: =+'ANALISIS MACROS'!C25 -> 1
B6: 1. Construir un Plan Estratégico de Comunicación y Relacionamiento adecuado que permita establecer un contacto permanente y consecutivo con los grupos de interés. | C6: =+'ANALISIS MACROS'!C26 -> 0
B7: 1. Actualizar de manera permanente los contenidos en medios de comunicación institucional en línea, tales como portal web y perfiles de redes sociales institucionales para brindar a la ciudadanía información oportuna, veraz y confiable. | C7: =+'ANALISIS MACROS'!C27 -> 0
B8: 1. Difundir la información institucional a los diferentes grupos objetivos y públicos de interés sobre la gestión a través de acciones de comunicación externa, con el fin de propiciar el flujo adecuado y el acceso a la información. | C8: =+'ANALISIS MACROS'!C28 -> 0
B9: 1. Generar impacto social mendiante la creación del boletin institucional. | C9: =+'ANALISIS MACROS'!C29 -> 0
B10: 1. Garantizar el despliegue oportuno a las diferentes audiencias y estamentos universitarios, de los planes, proyectos, iniciativas y actividades puestas en marcha en el marco de los eventos que se realicen internos y externos. | C10: =+'ANALISIS MACROS'!C30 -> 0
B11: 1. Establecer mecanismos de acción en materia de comunicación que permita responder a los diferentes retos institucionales. | C11: =+'ANALISIS MACROS'!C31 -> 0
B12: 1. Construir y gestionar las relaciones internas y externas de la Universidad en procura de mejorar el prestigio institucional. | C12: =+'ANALISIS MACROS'!C32 -> 0
B13: 1. Visibilizar la Universidad a nivel local, nacional e internacional a través de los medios masivos de comunicación y manejo estratégico de comunicación pública. | C13: =+'ANALISIS MACROS'!C33 -> 0
... B195: 7. La apreciación de la docencia por parte de los estudiantes La autoevaluación del profesor La valoración por parte del jefe inmediato. Trazar planes de mejora | C195: =+'ANALISIS MACROS'!C215 -> 0
C196: =SUM(C2:C195) -> 332

Sheet Analisis tipo de Impacto
B2: TIPO DE IMPACTO | C2: CANTIDAD
B3: FORMACIÓN | C3: =+COUNTIF(CONSOLIDADO!I:I,'Analisis tipo de Impacto'!B3) -> 39
B4: GESTIÓN | C4: =+COUNTIF(CONSOLIDADO!I:I,'Analisis tipo de Impacto'!B4) -> 123
B5: IMPACTO | C5: =+COUNTIF(CONSOLIDADO!I:I,'Analisis tipo de Impacto'!B5) -> 171
C6: =SUM(C3:C5) -> 333

Sheet M&E
C1: Otros gastos imputables al programa o al área
B2: Descripción (Archivadores, escritorios, sillas, etc.) | C2: Colaborador a cargo | F2: RESULTADO | H2: Espacio para la revisión
F3: Costo por Semestre I | G3: Costo por Semestre II | H3: Aprobado SI-NO | I3: Costo Semestre 1 | J3: Costo Semestre 2 | K3: Observaciones | L3: Ejecución | M3: Observaciones de la Ejecución
A4: Muebles y Enseres | F4: 0 | H4: NO | I4: =IF(H4="SI",F4,IF(H4="NO",0,"Sin comprobar")) -> 0 | J4: =IF(H4="SI",G4,IF(H4="NO",0,"Sin comprobar")) -> 0
H5: NO | I5: =IF(H5="SI",F5,IF(H5="NO",0,"Sin comprobar")) -> 0 | J5: =IF(H5="SI",G5,IF(H5="NO",0,"Sin comprobar")) -> 0
H6: NO | I6: =IF(H6="SI",F6,IF(H6="NO",0,"Sin comprobar")) -> 0 | J6: =IF(H6="SI",G6,IF(H6="NO",0,"Sin comprobar")) -> 0
H7: NO | I7: =IF(H7="SI",F7,IF(H7="NO",0,"Sin comprobar")) -> 0 | J7: =IF(H7="SI",G7,IF(H7="NO",0,"Sin comprobar")) -> 0
H8: NO | I8: =IF(H8="SI",F8,IF(H8="NO",0,"Sin comprobar")) -> 0 | J8: =IF(H8="SI",G8,IF(H8="NO",0,"Sin comprobar")) -> 0
H9: NO | I9: =IF(H9="SI",F9,IF(H9="NO",0,"Sin comprobar")) -> 0 | J9: =IF(H9="SI",G9,IF(H9="NO",0,"Sin comprobar")) -> 0
H10: NO | I10: =IF(H10="SI",F10,IF(H10="NO",0,"Sin comprobar")) -> 0 | J10: =IF(H10="SI",G10,IF(H10="NO",0,"Sin comprobar")) -> 0
H11: NO | I11: =IF(H11="SI",F11,IF(H11="NO",0,"Sin comprobar")) -> 0 | J11: =IF(H11="SI",G11,IF(H11="NO",0,"Sin comprobar")) -> 0
H12: NO | I12: =IF(H12="SI",F12,IF(H12="NO",0,"Sin comprobar")) -> 0 | J12: =IF(H12="SI",G12,IF(H12="NO",0,"Sin comprobar")) -> 0
H13: NO | I13: =IF(H13="SI",F13,IF(H13="NO",0,"Sin comprobar")) -> 0 | J13: =IF(H13="SI",G13,IF(H13="NO",0,"Sin comprobar")) -> 0
F14: =SUM(F4:F13) -> 0 | G14: =SUM(G4:G13) -> 0 | I14: =SUM(I4:I13) -> 0 | J14: =SUM(J4:J13) -> 0 | L14: =SUM(L4:L13) -> 0
B17: Descripción (Adecuaciones de oficina, mantenimiento, etc.) | C17: Colaborador a cargo | F17: RESULTADO | H17: Espacio para la revisión
F18: Costo por Semestre I | G18: Costo por Semestre II | H18: Aprobado SI-NO | I18: Costo Semestre 1 | J18: Costo Semestre 2 | K18: Observaciones | L18: Ejecución | M18: Observaciones de la Ejecución
A19: Adecuaciones | H19: NO | I19: =IF(H19="SI",F19,IF(H19="NO",0,"Sin comprobar")) -> 0 | J19: =IF(H19="SI",G19,IF(H19="NO",0,"Sin comprobar")) -> 0
H20: NO | I20: =IF(H20="SI",F20,IF(H20="NO",0,"Sin comprobar")) -> 0 | J20: =IF(H20="SI",G20,IF(H20="NO",0,"Sin comprobar")) -> 0
H21: NO | I21: =IF(H21="SI",F21,IF(H21="NO",0,"Sin comprobar")) -> 0 | J21: =IF(H21="SI",G21,IF(H21="NO",0,"Sin comprobar")) -> 0
H22: NO | I22: =IF(H22="SI",F22,IF(H22="NO",0,"Sin comprobar")) -> 0 | J22: =IF(H22="SI",G22,IF(H22="NO",0,"Sin comprobar")) -> 0
H23: NO | I23: =IF(H23="SI",F23,IF(H23="NO",0,"Sin comprobar")) -> 0 | J23: =IF(H23="SI",G23,IF(H23="NO",0,"Sin comprobar")) -> 0
H24: NO | I24: =IF(H24="SI",F24,IF(H24="NO",0,"Sin comprobar")) -> 0 | J24: =IF(H24="SI",G24,IF(H24="NO",0,"Sin comprobar")) -> 0
H25: NO | I25: =IF(H25="SI",F25,IF(H25="NO",0,"Sin comprobar")) -> 0 | J25: =IF(H25="SI",G25,IF(H25="NO",0,"Sin comprobar")) -> 0
H26: NO | I26: =IF(H26="SI",F26,IF(H26="NO",0,"Sin comprobar")) -> 0 | J26: =IF(H26="SI",G26,IF(H26="NO",0,"Sin comprobar")) -> 0
H27: NO | I27: =IF(H27="SI",F27,IF(H27="NO",0,"Sin comprobar")) -> 0 | J27: =IF(H27="SI",G27,IF(H27="NO",0,"Sin comprobar")) -> 0
H28: NO | I28: =IF(H28="SI",F28,IF(H28="NO",0,"Sin comprobar")) -> 0 | J28: =IF(H28="SI",G28,IF(H28="NO",0,"Sin comprobar")) -> 0
F29: =SUM(F19:F28) -> 0 | G29: =SUM(G19:G28) -> 0 | I29: =SUM(I19:I28) -> 0 | J29: =SUM(J19:J28) -> 0 | L29: =SUM(L19:L28) -> 0
B32: Descripción (Hardware y Software) | C32: Colaborador a cargo | F32: RESULTADO | H32: Espacio para la revisión
F33: Costo por Semestre I | G33: Costo por Semestre II | H33: Aprobado SI-NO | I33: Costo Semestre 1 | J33: Costo Semestre 2 | K33: Observaciones | L33: Ejecución | M33: Observaciones de la Ejecución
A34: Equipos de tecnología | G34: 0 | H34: NO | I34: =IF(H34="SI",F34,IF(H34="NO",0,"Sin comprobar")) -> 0 | J34: =IF(H34="SI",G34,IF(H34="NO",0,"Sin comprobar")) -> 0
H35: NO | I35: =IF(H35="SI",F35,IF(H35="NO",0,"Sin comprobar")) -> 0 | J35: =IF(H35="SI",G35,IF(H35="NO",0,"Sin comprobar")) -> 0
H36: NO | I36: =IF(H36="SI",F36,IF(H36="NO",0,"Sin comprobar")) -> 0 | J36: =IF(H36="SI",G36,IF(H36="NO",0,"Sin comprobar")) -> 0
H37: NO | I37: =IF(H37="SI",F37,IF(H37="NO",0,"Sin comprobar")) -> 0 | J37: =IF(H37="SI",G37,IF(H37="NO",0,"Sin comprobar")) -> 0
H38: NO | I38: =IF(H38="SI",F38,IF(H38="NO",0,"Sin comprobar")) -> 0 | J38: =IF(H38="SI",G38,IF(H38="NO",0,"Sin comprobar")) -> 0
H39: NO | I39: =IF(H39="SI",F39,IF(H39="NO",0,"Sin comprobar")) -> 0 | J39: =IF(H39="SI",G39,IF(H39="NO",0,"Sin comprobar")) -> 0
H40: NO | I40: =IF(H40="SI",F40,IF(H40="NO",0,"Sin comprobar")) -> 0 | J40: =IF(H40="SI",G40,IF(H40="NO",0,"Sin comprobar")) -> 0
H41: NO | I41: =IF(H41="SI",F41,IF(H41="NO",0,"Sin comprobar")) -> 0 | J41: =IF(H41="SI",G41,IF(H41="NO",0,"Sin comprobar")) -> 0
H42: NO | I42: =IF(H42="SI",F42,IF(H42="NO",0,"Sin comprobar")) -> 0 | J42: =IF(H42="SI",G42,IF(H42="NO",0,"Sin comprobar")) -> 0
H43: NO | I43: =IF(H43="SI",F43,IF(H43="NO",0,"Sin comprobar")) -> 0 | J43: =IF(H43="SI",G43,IF(H43="NO",0,"Sin comprobar")) -> 0
F44: =SUM(F34:F43) -> 0 | G44: =SUM(G34:G43) -> 0 | I44: =SUM(I34:I43) -> 0 | J44: =SUM(J34:J43) -> 0 | L44: =SUM(L34:L43) -> 0

Sheet RES
B2: FUNDACIÓN UNIVERSITARIA DE POPAYÁN
B3: PRESUPUESTO CONSOLIDADO
B4: VICERRECTORIA ADMINISTRATIVA Y FINANCIERA
B6: Localidad
B8: =#REF! -> #REF!
B10: Descripción costo
B12: =#REF! -> #REF!
B14: Quién elaboró:
B16: =#REF! -> #REF!
B18: Relación de costos presupuestales
B21: Gastos en personal
F22: Presupuestado | I22: Aprobado
B23: Concepto | F23: Costo por Semestre I | G23: Costo por Semestre II | H23: Total anual | I23: Costo por Semestre I | J23: Costo por Semestre II | K23: Total anual
B24: Total Gastos de personal Administrativo | F24: =ADM!I18 -> 0 | G24: =ADM!J18 -> 0 | H24: =SUM(F24:G24) -> 0 | I24: =ADM!L18 -> 0 | J24: =ADM!M18 -> 0 | K24: =SUM(I24:J24) -> 0
F27: Presupuestado | I27: Aprobado
B28: Concepto | F28: Costo por Semestre I | G28: Costo por Semestre II | H28: Total anual | I28: Costo por Semestre I | J28: Costo por Semestre II | K28: Total anual
B29: Total Gastos Docentes Tiempo Completo | F29: =PRE!F18 -> 0 | G29: =PRE!G18 -> 0 | H29: =SUM(F29:G29) -> 0 | I29: =PRE!I18 -> 0 | J29: =PRE!J18 -> 0 | K29: =SUM(I29:J29) -> 0
B30: Total Gastos Docentes Medio Tiempo | F30: =PRE!F33 -> 0 | G30: =PRE!G33 -> 0 | H30: =SUM(F30:G30) -> 0 | I30: =PRE!I33 -> 0 | J30: =PRE!J33 -> 0 | K30: =SUM(I30:J30) -> 0
B31: Total Gastos Docentes Tiempo Parcial | F31: =PRE!F48 -> 0 | G31: =PRE!G48 -> 0 | H31: =SUM(F31:G31) -> 0 | I31: =PRE!I48 -> 0 | J31: =PRE!J48 -> 0 | K31: =SUM(I31:J31) -> 0
B32: Total Gastos Docentes de POSGRADO | F32: =POS!G18 -> 0 | G32: =POS!H18 -> 0 | H32: =SUM(F32:G32) -> 0 | I32: =POS!J18 -> 0 | J32: =POS!K18 -> 0 | K32: =SUM(I32:J32) -> 0
B33: Total Gastos para la labor Docente | F33: =SUM(F29:F32) -> 0 | G33: =SUM(G29:G32) -> 0 | H33: =SUM(H29:H32) -> 0 | I33: =SUM(I29:I32) -> 0 | J33: =SUM(J29:J32) -> 0 | K33: =SUM(K29:K32) -> 0
B36: Gastos en actividades
F37: Presupuestado | I37: Aprobado
B38: Concepto | F38: Costo por Semestre I | G38: Costo por Semestre II | H38: Total anual | I38: Costo por Semestre I | J38: Costo por Semestre II | K38: Total anual
B39: Docencia | F39: =#REF! -> #REF! | G39: =#REF! -> #REF! | H39: =SUM(F39:G39) -> #REF! | I39: =#REF! -> #REF! | J39: =#REF! -> #REF! | K39: =SUM(I39:J39) -> #REF!
B40: Investigación | F40: =#REF! -> #REF! | G40: =#REF! -> #REF! | H40: =SUM(F40:G40) -> #REF! | I40: =#REF! -> #REF! | J40: =#REF! -> #REF! | K40: =SUM(I40:J40) -> #REF!
B41: Extensión o Proyección Social | F41: =#REF! -> #REF! | G41: =#REF! -> #REF! | H41: =SUM(F41:G41) -> #REF! | I41: =#REF! -> #REF! | J41: =#REF! -> #REF! | K41: =SUM(I41:J41) -> #REF!
B42: Complementarios | F42: =#REF! -> #REF! | G42: =#REF! -> #REF! | H42: =SUM(F42:G42) -> #REF! | I42: =#REF! -> #REF! | J42: =#REF! -> #REF! | K42: =SUM(I42:J42) -> #REF!
B43: Total Gastos en actividades | F43: =SUM(F39:F42) -> #REF! | G43: =SUM(G39:G42) -> #REF! | H43: =SUM(H39:H42) -> #REF! | I43: =SUM(I39:I42) -> #REF! | J43: =SUM(J39:J42) -> #REF! | K43: =SUM(K39:K42) -> #REF!
B46: Muebles y Enseres
F47: Presupuestado | I47: Aprobado
B48: Concepto | F48: Costo por Semestre I | G48: Costo por Semestre II | H48: Total anual | I48: Costo por Semestre I | J48: Costo por Semestre II | K48: Total anual
B49: Otros gastos imputables al programa o al área | F49: ='M&E'!F14 -> 0 | G49: ='M&E'!G14 -> 0 | H49: =SUM(F49:G49) -> 0 | I49: ='M&E'!I14 -> 0 | J49: ='M&E'!J14 -> 0 | K49: =SUM(I49:J49) -> 0
F52: Presupuestado | I52: Aprobado
F53: Costo por Semestre I | G53: Costo por Semestre II | H53: Total anual | I53: Costo por Semestre I | J53: Costo por Semestre II | K53: Total anual
B54: TOTALES | F54: =F24+F33+F43+F49 -> #REF! | G54: =G24+G33+G43+G49 -> #REF! | H54: =SUM(F54:G54) -> #REF! | I54: =I24+I33+I43+I49 -> #REF! | J54: =J24+J33+J43+J49 -> #REF! | K54: =SUM(I54:J54) -> #REF!
F57: PRES | G57: APRO
E58: Administrativos | F58: =H24 -> 0 | G58: =K24 -> 0
E59: Docentes | F59: =H33 -> 0 | G59: =K33 -> 0
E60: Actividades | F60: =H43 -> #REF! | G60: =K43 -> #REF!
E61: Muebles y Enseres | F61: =H49 -> 0 | G61: =K49 -> 0

Sheet velGrap
A1: Pocentaje | B1: Secuencia
A2: 0.1 | B2: 1
A3: 0.2 | B3: 1
A4: 0.3 | B4: 1
A5: 0.4 | B5: 1
A6: 0.5 | B6: 1
A7: 0.6 | B7: 1
A8: 0.7 | B8: 1
A9: 0.8 | B9: 1
A10: 0.9 | B10: 1
A11: 1 | B11: =SUM(B2:B10) -> 9
A14: Avance | B14: =#REF! -> #REF! | E14: Avance | F14: =#REF! -> #REF! | I14: Avance | J14: =#REF! -> #REF! | M14: Avance | N14: =#REF! -> #REF!
A15: Angulo | B15: =B14*PI() -> #REF! | E15: Angulo | F15: =F14*PI() -> #REF! | I15: Angulo | J15: =J14*PI() -> #REF! | M15: Angulo | N15: =N14*PI() -> #REF!
A17: Datos | B17: X | C17: Y | E17: Datos | F17: X | G17: Y | I17: Datos | J17: X | K17: Y | M17: Datos | N17: X | O17: Y
A18: Inicio | B18: 0 | C18: 0 | E18: Inicio | F18: 0 | G18: 0 | I18: Inicio | J18: 0 | K18: 0 | M18: Inicio | N18: 0 | O18: 0
A19: Fin | B19: =-(COS(B15)) -> #REF! | C19: =SIN(B15) -> #REF! | E19: Fin | F19: =-(COS(F15)) -> #REF! | G19: =SIN(F15) -> #REF! | I19: Fin | J19: =-(COS(J15)) -> #REF! | K19: =SIN(J15) -> #REF! | M19: Fin | N19: =-(COS(N15)) -> #REF! | O19: =SIN(N15) -> #REF!
