Workbook

Sheet FO-GC-015
A1: =COLUMN() -> 1 | B1: =COLUMN() -> 2 | C1: =COLUMN() -> 3 | D1: =COLUMN() -> 4 | E1: =COLUMN() -> 5 | F1: =COLUMN() -> 6 | G1: =COLUMN() -> 7 | H1: =COLUMN() -> 8 | ... AL1: =COLUMN() -> 38
I3: 2Reconocimiento 202 | AO3: Instrucciones para el diligenciamiento de la "Hoja de Verificación de Auditorías"
AO5: 1. | AP5: Registre el cilco de la Auditoría. Ejemplo: "2025" para ciclos anuales o "2025-S1" para ciclos semestrales.
AO6: 2. | AP6: Registre los criterios de auditoría establecidos en el Programa de Auditoria del ciclo correspondiente.
AO7: 3. | AP7: Seleccione la auditoria a realizar desplegando el listado de procesos y programas a auditar.
AO8: 4. | AP8: Este campo está fomulado. El ID corresponderá al mismo asignado en el Programa de Auditoría. Previamente el Auditor Líder a cargado en este formato el listado de auditorias programadas.
C10: 1. Ciclo Auditoria | E10: 2. Criterios de Auditoria | U10: 3. Proceso / Programa Académico | AB10: 4. ID | AD10: 5. Colaborador Auditado
AB11: =IFERROR(VLOOKUP(U11,Listas!C:E,3,0),"") | AD11: Nombre | AO11: 5. | AP11: Registre el día de la auditoría el colaborador de la Institución que recibió la auditoria.
AD12: Cargo | AO12: 6. | AP12: Este campo está fomulado. Una vez que se selecciona la auditoría a realizar, el formulario traerá la información correspondiente a la propuesta de valor del proceso, es decir el Objetivo del Proceso, el cual está registrado en las Caracterizaciones de Proceso.
C14: 6. Propuesta de Valor del Proceso (Objetivo del Proceso) | Z14: 8. Requisitos ISO 9001:2015 | AF14: 9. Fecha Ejecución de la Auditoría
C15: =IFERROR(VLOOKUP($U$11,'SGC-Vigente'!C:F,2,0),"***") -> *** | Z15: =IFERROR(VLOOKUP($U$11,'SGC-Vigente'!C:F,4,0),"***") -> *** | AO15: 7. | AP15: Este campo está fomulado. Una vez que se selecciona la auditoría a realizar, el formulario traerá la información correspondiente a la propuesta de valor del proceso, es decir el Objetivo del Proceso, el cual está registrado en las Caracterizaciones de Proceso.
AF16: 10. Locación
AF17: 11. Auditor Principal | AO17: 8. | AP17: Este campo está fomulado. Una vez que se selecciona la auditoría a realizar, el formulario traerá la información correspondiente a los requisitos de la ISO 9001:2015 Aplicables.
C18: 7. Requisitos de Ley Aplicables | F18: =IFERROR(VLOOKUP($U$11,'SGC-Vigente'!C:F,3,0),"***") -> ***
AF19: 12. Auditor Asistente | AO19: 9. | AP19: Registre la fecha en que se ejecutó la auditoria interna.
AO20: 10. | AP20: Seleccione la locación en donde se desarrolla la auditoria.
C22: 13. Referencia Normativa / Documento | F22: 14. Pregunta / Verificación | P22: 15. Registro / Evidencia | X22: 16. Hallazgos | AA22: 17. Req. ISO 9001 | AC22: 18. Descripción del Hallazgo Breve descripción del incumplimiento (NC) o riesgo de incumplimeinto (Obs) | AO22: 11. | AP22: Seleccione el Auditor Principal asignado, según el Programa de Auditoría para el presente ciclo.
X23: Con | Y23: NC | Z23: Obs | AO23: 12. | AP23: Seleccione el Auditor Asistente asignado, según el Programa de Auditoría para el presente ciclo.
X24: =COUNTIF(X25:X56,"X") -> 0 | Y24: =COUNTIF(Y25:Y56,"X") -> 0 | Z24: =COUNTIF(Z25:Z56,"X") -> 0
A25: =IF(Y25="X",CONCATENATE("NC-",COUNTA(Y$25:Y25)),IF(Z25="X",CONCATENATE("Obs-",COUNTA(Z$25:Z25)),"-")) -> - | AO25: 13. | AP25: Registre el requisito, referencia normativa o documental relacionada con la pregunta o verificación colocada en el el siguiente campo "14. Pregunta / Verificación". Ejemplo: Puede ser una Ley, decreto, resolución o un acto administrativo Institucional (Resolución) aplicables, un requisito específico de la nomra ISO 9001:2015, o un documento del Sistema de Gestión de Calidad relacionado con el proceso.
A26: =IF(Y26="X",CONCATENATE("NC-",COUNTA(Y$25:Y26)),IF(Z26="X",CONCATENATE("Obs-",COUNTA(Z$25:Z26)),"-")) -> - | AO26: 14. | AP26: Registre la pregunta o verificación a validar durante la auditoría.
A27: =IF(Y27="X",CONCATENATE("NC-",COUNTA(Y$25:Y27)),IF(Z27="X",CONCATENATE("Obs-",COUNTA(Z$25:Z27)),"-")) -> - | AO27: 15. | AP27: Registre la evidencia verificada durante la auditoria, especificando el nombre de la evidencia y el periodo en que se generó.
A28: =IF(Y28="X",CONCATENATE("NC-",COUNTA(Y$25:Y28)),IF(Z28="X",CONCATENATE("Obs-",COUNTA(Z$25:Z28)),"-")) -> - | AO28: 16. | AP28: Seleccione con una "X" el tipo de hallazgo de auditoría (Con: "Conforme" / NC: "No Conformidad" / Obs: "Observación") • Conforme: Cumplimiento del requisito, • No Conformidad: Incumplimiento del requisito, • Obs: Observación: Hallazgo de auditoría, el cual indica una situación que conlleva una oportunidad de mejora o un riesgo potencial de constituirse en No Conformidad.
A29: =IF(Y29="X",CONCATENATE("NC-",COUNTA(Y$25:Y29)),IF(Z29="X",CONCATENATE("Obs-",COUNTA(Z$25:Z29)),"-")) -> - | AO29: 17. | AP29: Seleccione el requisito de la ISO 9001:2015 al que se le asigna el hallazgo de auditoria. Se desea especificar mas de un requisito, proceda a escribirlos en este campo separados por un "/".
A30: =IF(Y30="X",CONCATENATE("NC-",COUNTA(Y$25:Y30)),IF(Z30="X",CONCATENATE("Obs-",COUNTA(Z$25:Z30)),"-")) -> - | AO30: 18. | AP30: Realice una breve descripción del hallazgo, especificando desde el inicio si "se cumple" o "no se cumple" con la verificación realizada según la evidencia observada frente a la referencia normativa aplicable. Esta información permitirá estructurar en el informe de auditoria la redacción de la No Conformidad u Observación, o para resaltar una fortaleza o debilidad evidenciada en el proceso / programa académico.
A31: =IF(Y31="X",CONCATENATE("NC-",COUNTA(Y$25:Y31)),IF(Z31="X",CONCATENATE("Obs-",COUNTA(Z$25:Z31)),"-")) -> - | AO31: 19. | AP31: Al realizar la verificación del desempeño del proceso o programa académico, registre en este campo el nombre del indicador del proceso validado en la auditoría.
A32: =IF(Y32="X",CONCATENATE("NC-",COUNTA(Y$25:Y32)),IF(Z32="X",CONCATENATE("Obs-",COUNTA(Z$25:Z32)),"-")) -> - | AO32: 20. | AP32: Registre la meta especificada en la hoja de vida del indicador.
A33: =IF(Y33="X",CONCATENATE("NC-",COUNTA(Y$25:Y33)),IF(Z33="X",CONCATENATE("Obs-",COUNTA(Z$25:Z33)),"-")) -> - | AO33: 21. | AP33: Registre la medición registrada en la hoja de vida del indicador.
A34: =IF(Y34="X",CONCATENATE("NC-",COUNTA(Y$25:Y34)),IF(Z34="X",CONCATENATE("Obs-",COUNTA(Z$25:Z34)),"-")) -> - | AO34: 22. | AP34: Registre el periodo al que corresponde la medición del indicador registrada en la hoja de vida correspondiente.
A35: =IF(Y35="X",CONCATENATE("NC-",COUNTA(Y$25:Y35)),IF(Z35="X",CONCATENATE("Obs-",COUNTA(Z$25:Z35)),"-")) -> - | AO35: 23. | AP35: En esta sección registre la documentación verificada en el proceso o programa académico. Inicie registrando el código del documento si este tiene asociado alguno. En caso contrario deje este campo vacío.
A36: =IF(Y36="X",CONCATENATE("NC-",COUNTA(Y$25:Y36)),IF(Z36="X",CONCATENATE("Obs-",COUNTA(Z$25:Z36)),"-")) -> - | AO36: 24. | AP36: Registre la versión del documento, si este tiene la información de la vigencia. En caso contrario deje este campo vacío.
... A38: =IF(Y38="X",CONCATENATE("NC-",COUNTA(Y$25:Y38)),IF(Z38="X",CONCATENATE("Obs-",COUNTA(Z$25:Z38)),"-")) -> - | AO38: 26. | AP38: Registre las Observaciones Generales de la Auditoria, iniciando por la fortalezas del proceso o programa académico que le permitirán dar cumplimiento a la propuesta de valo u objetivo del proceso. De igual manera, mencione las debilidades que podrían poner en riesgo el cumplimiento del Objetivo del Proceso.
A39: =IF(Y39="X",CONCATENATE("NC-",COUNTA(Y$25:Y39)),IF(Z39="X",CONCATENATE("Obs-",COUNTA(Z$25:Z39)),"-")) -> - | AP39: Mencione el equipo de colaboradores que acompañaron al Líder del Proceso o Programa Académico a recibir la auditoría y la disposición general de la misma para presentar las evidencias solicitadas y la disposición para mejorar los hallazgos identificados.
A40: =IF(Y40="X",CONCATENATE("NC-",COUNTA(Y$25:Y40)),IF(Z40="X",CONCATENATE("Obs-",COUNTA(Z$25:Z40)),"-")) -> -
A41: =IF(Y41="X",CONCATENATE("NC-",COUNTA(Y$25:Y41)),IF(Z41="X",CONCATENATE("Obs-",COUNTA(Z$25:Z41)),"-")) -> -
A42: =IF(Y42="X",CONCATENATE("NC-",COUNTA(Y$25:Y42)),IF(Z42="X",CONCATENATE("Obs-",COUNTA(Z$25:Z42)),"-")) -> -
A43: =IF(Y43="X",CONCATENATE("NC-",COUNTA(Y$25:Y43)),IF(Z43="X",CONCATENATE("Obs-",COUNTA(Z$25:Z43)),"-")) -> -
A44: =IF(Y44="X",CONCATENATE("NC-",COUNTA(Y$25:Y44)),IF(Z44="X",CONCATENATE("Obs-",COUNTA(Z$25:Z44)),"-")) -> -
A45: =IF(Y45="X",CONCATENATE("NC-",COUNTA(Y$25:Y45)),IF(Z45="X",CONCATENATE("Obs-",COUNTA(Z$25:Z45)),"-")) -> -
A46: =IF(Y46="X",CONCATENATE("NC-",COUNTA(Y$25:Y46)),IF(Z46="X",CONCATENATE("Obs-",COUNTA(Z$25:Z46)),"-")) -> -
A47: =IF(Y47="X",CONCATENATE("NC-",COUNTA(Y$25:Y47)),IF(Z47="X",CONCATENATE("Obs-",COUNTA(Z$25:Z47)),"-")) -> -
A48: =IF(Y48="X",CONCATENATE("NC-",COUNTA(Y$25:Y48)),IF(Z48="X",CONCATENATE("Obs-",COUNTA(Z$25:Z48)),"-")) -> -
A49: =IF(Y49="X",CONCATENATE("NC-",COUNTA(Y$25:Y49)),IF(Z49="X",CONCATENATE("Obs-",COUNTA(Z$25:Z49)),"-")) -> -
A50: =IF(Y50="X",CONCATENATE("NC-",COUNTA(Y$25:Y50)),IF(Z50="X",CONCATENATE("Obs-",COUNTA(Z$25:Z50)),"-")) -> -
A51: =IF(Y51="X",CONCATENATE("NC-",COUNTA(Y$25:Y51)),IF(Z51="X",CONCATENATE("Obs-",COUNTA(Z$25:Z51)),"-")) -> -
... A55: =IF(Y55="X",CONCATENATE("NC-",COUNTA(Y$25:Y55)),IF(Z55="X",CONCATENATE("Obs-",COUNTA(Z$25:Z55)),"-")) -> -
C57: * Validación del Desempeño - Proceso / Programa Académico
C58: 19. Nombre Indicador | N58: 20. Meta | P58: 21. Medición | R58: 22. Periodo | U58: 19. Nombre Indicador | AF58: 20. Meta | AH58: 21. Medición | AJ58: 22. Periodo
C63: * Documentación Verificada en el Proceso / Programa Académico
C64: 23. Código | F64: 24. Versión | H64: 25. Nombre del Documento | U64: 23. Código | X64: 24. Versión | Z64: 25. Nombre del Documento
C71: 26. Observaciones Generales de la Auditoria

Sheet Req. ISO 9001-2015
B1: Requisitos ISO 9001:2015
A2: Num. | C2: Requisito
A4: 9 | B4: 4. | C4: CONTEXTO DE LA ORGANIXZACIÓN
A5: =COUNTIF(#REF!,"X") -> #REF! | B5: 4.1. | C5: Comprensión de la Organización y de su contexto
A6: =COUNTIF(#REF!,"X") -> #REF! | B6: 4.2. | C6: Comprensión de las necesidades y expectativas de las partes interesadas
A7: =COUNTIF(#REF!,"X") -> #REF! | B7: 4.3. | C7: Determinación del alcance del Sistema de Gestión de Calidad
A8: =COUNTIF(#REF!,"X") -> #REF! | B8: 4.4. | C8: Sistema de Gestión de Calidad y sus Procesos
A9: =COUNTIF(#REF!,"X") -> #REF! | B9: 4.4.1. | C9: Establecer, implementar, mantener y mejorar el SGC, incluidos los procesos necesarios y sus interaccionas
A10: =COUNTIF(#REF!,"X") -> #REF! | B10: 4.4.2. | C10: Mantener información documentada y conservarla para tener confianza de que los procesos se realizan según lo planificado
A11: =COUNTIF(#REF!,"X") -> #REF!
A12: 9 | B12: 5. | C12: LIDERAZGO
A13: =COUNTIF(#REF!,"X") -> #REF! | B13: 5.1. | C13: Liderazgo y Compromiso
A14: =COUNTIF(#REF!,"X") -> #REF! | B14: 5.1.1. | C14: Generalidades. La Organización debe demostrar liderazgo y compromiso con respecto al SGC. (a, b, c, d, e, f, g, h, i, j.)
A15: =COUNTIF(#REF!,"X") -> #REF! | B15: 5.1.2. | C15: Enfoque al Cliente. La Alta Dirección debe asegurarse que se determinan, comprenden y cumplen los Requisitos del Cliente, los legales y reglamentarios aplicables
A16: =COUNTIF(#REF!,"X") -> #REF! | B16: 5.2. | C16: Política
A17: =COUNTIF(#REF!,"X") -> #REF! | B17: 5.2.1. | C17: Establecimiento de la Política de Calidad
A18: =COUNTIF(#REF!,"X") -> #REF! | B18: 5.2.2. | C18: Comunicación de la Política de Calidad
A19: =COUNTIF(#REF!,"X") -> #REF! | B19: 5.3. | C19: Roles, responsabilidades y autoridades en la Organización. Asegurarse que para los roles pertinentes se asignen, se comuniquen y se entiendan en la Org. (a, b, c.)
A20: =COUNTIF(#REF!,"X") -> #REF!
A21: 9 | B21: 6. | C21: PLANIFICACIÓN
A22: =COUNTIF(#REF!,"X") -> #REF! | B22: 6.1. | C22: Acciones para abordar riesgos y oportunidades
A23: =COUNTIF(#REF!,"X") -> #REF! | B23: 6.1.1. | C23: La Organización debe considerar las cuestiones referidas en (4.1.) y requisitos referidos en (4.2.)
A24: =COUNTIF(#REF!,"X") -> #REF! | B24: 6.1.2. | C24: La Organización de planificar: * Acciones para abordar riesgos y oportunidades. * La manera de integrar e implementar acciones en sus procesos del SGC y evaluar la eficacia de estas acciones. "Las acciones para abordar los riesgos y oportunidades deben ser proporcionales al impacto potencial en la conformidad de los productos y los servicios.
A25: =COUNTIF(#REF!,"X") -> #REF! | B25: 6.2. | C25: Objetivos de la Calidad y planificación para lograrlos
A26: =COUNTIF(#REF!,"X") -> #REF! | B26: 6.2.1. | C26: La Organización debe establecer Objetivos de Calidad
A27: =COUNTIF(#REF!,"X") -> #REF! | B27: 6.2.2. | C27: Al planificar como lograr los O.C. la Org. Debe determinar: a) que va a hacer, b) recursos, c) responsables, d) cuando se finalizará y e) cómo se evaluarán los resultados
A28: =COUNTIF(#REF!,"X") -> #REF! | B28: 6.3. | C28: Planificación de Cambios. Cuando la Org. Determine la necesidad de cambios al SGC, estos se deben llevar de manera planificada (4.4.), considerar a), b), c), d)
A29: =COUNTIF(#REF!,"X") -> #REF!
A30: 9 | B30: 7. | C30: APOYO
A31: =COUNTIF(#REF!,"X") -> #REF! | B31: 7.1. | C31: Recursos
A32: =COUNTIF(#REF!,"X") -> #REF! | B32: 7.1.1. | C32: Generalidades. Determinar y proporcionar los recursos necesario para el SGC. La Org. Debe considerar las capacidades y limitaciones de recursos existentes y qué se necesita obtener de los proveedores externos
A33: =COUNTIF(#REF!,"X") -> #REF! | B33: 7.1.2. | C33: Personas. La Organización debe determinar y proporcionar las personas necesarias para la implementación eficaz del SGC y para la operación y control de sus procesos
A34: =COUNTIF(#REF!,"X") -> #REF! | B34: 7.1.3. | C34: Infraestructura. La Org. debe determinar, proporcionar y mantener la infraestructura necesaria para la operación de sus procesos y lograr la conformidad del servicio
A35: =COUNTIF(#REF!,"X") -> #REF! | B35: 7.1.4. | C35: Ambiente para la operación de los procesos. La Orq. debe mantener el ambiente necesario para la operación de sus procesos y para lograr la conformidad del servicio
A36: =COUNTIF(#REF!,"X") -> #REF! | B36: 7.1.5. | C36: Recursos de seguimeinto y medición.
A37: =COUNTIF(#REF!,"X") -> #REF! | B37: 7.1.5.1. | C37: Generalidades
A38: =COUNTIF(#REF!,"X") -> #REF! | B38: 7.1.5.2. | C38: Trazabilidad de las mediciones
A39: =COUNTIF(#REF!,"X") -> #REF! | B39: 7.1.6. | C39: Conocimientos de la Organización. La Org. debe determinar los conocimeintos necesarios para la operación de sus procesos y para lograr la conformidad del servicio.
A40: =COUNTIF(#REF!,"X") -> #REF! | B40: 7.2. | C40: Competencia. a) Determinar la competencia necesaria de las personas, b) Asegurarse de que las personas sean competentes basándose en la educación, formación o experiencia apropiadas. c) Cuando sea aplicable tomar acciones para adquirir competencia necesaria y evaluar eficacia de las acciones, d) conservar la documentación apropiada como evidencia de la competencia.
A41: =COUNTIF(#REF!,"X") -> #REF! | B41: 7.3. | C41: Toma de Conciencia. Política de Calidad, Objetivos de Calidad, contribución a la eficacia del SGC.
A42: =COUNTIF(#REF!,"X") -> #REF! | B42: 7.4. | C42: Comunicación. La Org. Debe debe determinar las comunicaciones internas y externas.
... A48: =COUNTIF(#REF!,"X") -> #REF! | B48: 7.5.3.2. | C48: Asegurarse que esté disponible y sea idónea para su uso, donde y cuando se necesite
A49: =COUNTIF(#REF!,"X") -> #REF!
A50: 9 | B50: 8. | C50: OPERACIÓN
A51: =COUNTIF(#REF!,"X") -> #REF! | B51: 8.1. | C51: Planificación y control operacional. La Org. Debe planificar, implementar y controlar los procesos necesarios para cumplir los req. Para la provisión de productos y servicios. La Org. Debe controlar los cambios planificados y asegurarse de que los procesos contratados externamente estén controlados.
A52: =COUNTIF(#REF!,"X") -> #REF! | B52: 8.2. | C52: Requisitos para los productos y servicios
A53: =COUNTIF(#REF!,"X") -> #REF! | B53: 8.2.1. | C53: Comunicación con el Cliente. Información relativa a los productos y servicios. Consultas, contratos o pedidos, obtener retroalimetnación de los clientes y establecer los req. específicos para las acciones de contingencia, caundo sea pertinente.
A54: =COUNTIF(#REF!,"X") -> #REF! | B54: 8.2.2. | C54: Determinación de los requisitos para los productos y servicios.
A55: =COUNTIF(#REF!,"X") -> #REF! | B55: 8.2.3. | C55: Revisión de los requisitos para los productos y servicios.
A56: =COUNTIF(#REF!,"X") -> #REF! | B56: 8.2.3.1. | C56: La Org. Debe asegurarse que tiene la capacidad para cumplir los requisitos para los productos y servicios que se van a ofrecer a los clientes. La Org. Debe revisar antes de comprometerse a suministrar productos servicios a un cliente
A57: =COUNTIF(#REF!,"X") -> #REF! | B57: 8.2.3.2. | C57: La Org. Debe conservar la iformación documentada sobre resultados de la revisión y sobre cualquier requisito nuevo
A58: =COUNTIF(#REF!,"X") -> #REF! | B58: 8.2.4. | C58: Cambios en los requisitos para los productos y servicios
A59: =COUNTIF(#REF!,"X") -> #REF! | B59: 8.3. | C59: Diseño y desarrollo de los productos y servicios
A60: =COUNTIF(#REF!,"X") -> #REF! | B60: 8.3.1. | C60: Generalidades. La Org. debe stablecer, implementar y mantener un proceso de diseño y desarrollo que sea adecuado para asegurarse de la posterior provisión de productos y servicios
A61: =COUNTIF(#REF!,"X") -> #REF! | B61: 8.3.2. | C61: Planificación del diseño y desarrollo
A62: =COUNTIF(#REF!,"X") -> #REF! | B62: 8.3.3. | C62: Entrradas para el diseño y desarrollo
... A80: =COUNTIF(#REF!,"X") -> #REF! | B80: 8.7.2. | C80: La Org. Debe conservar información documetnada que describa: a) la no conformidad, b) las acciones tomadas, c) las concesiones obtenidas, d) identifique la autoridad que decide la acción con respecto a la No Conformidad.
A81: =COUNTIF(#REF!,"X") -> #REF!
A82: 9 | B82: 9. | C82: EVALUACIÓN DEL DESEMPEÑO
A83: =COUNTIF(#REF!,"X") -> #REF! | B83: 9.1. | C83: Seguimiento, medición, análisis y evaluación.
A84: =COUNTIF(#REF!,"X") -> #REF! | B84: 9.1.1. | C84: Generalidades. L Or. Debe determinar a) qué necesita seguimeinto y medición, b) los métodos de seguimeinto, medición, análisis y evaluación necesarios para asegurar resultados válidos, c) cuándo se deben llevar a cabo el seguimeinto y la medición, d) cuándo se deben analizar y evaluar los resultados del seguimiento y medición.
A85: =COUNTIF(#REF!,"X") -> #REF! | B85: 9.1.2. | C85: Satisfacción del cliente. La Org. Debe realizar seguimeinto a las percepciones de los clientes del grado en que se cumplen sus necesidades y expectativas. La Ortg. Debe determinar los métodos para obtener, realizar el seguimeinto y revisar esta información
A86: =COUNTIF(#REF!,"X") -> #REF! | B86: 9.1.3. | C86: Análisis y evaluación. La Org. Debe analizar y evaluar los datos y la información apropiados que surgen por el seguimeinto y la medición. Los resultados del análisis debe utilizarse para evaluar: a) la conformidad del servicio, b) el grado de satisfacción del cliente, c) el desempeño y eficacia del SGC, d) si lo planificado se ha implementado de forma eficaz, e) eficacia de las acciones tomadas para abordar los riesgos y oportunidades, f) el desempeño de los proveedores externos, g) la nececidad de mejoras en el SGC.
A87: =COUNTIF(#REF!,"X") -> #REF! | B87: 9.2. | C87: Auditoría Interna
A88: =COUNTIF(#REF!,"X") -> #REF! | B88: 9.2.1. | C88: La Org. Debe llevar a cabo auditorías internas a intérvalos planificados para proporcionar información acerca del SGC: a) es conforme con los requisitos de la Organización y esta norma, b) se implementa y mantiene efizacmente.
A89: =COUNTIF(#REF!,"X") -> #REF! | B89: 9.2.2. | C89: La Org. Debe: a) planificar, establecer, implementar y mantener un programa de auditorías, b) criterios y alcance de la auditoría, c) seleccionar auditores y llevar acabo auditorías, d) asegurarse de que los resultados de la auditorias se informan a la dirección pertinente, e) realizar las correcciones y tomar las acciones correctivas adecuadas sin demora injustificada, f) conservar información documentada.
A90: =COUNTIF(#REF!,"X") -> #REF! | B90: 9.3. | C90: Revisión por la Dirección
A91: =COUNTIF(#REF!,"X") -> #REF! | B91: 9.3.1. | C91: Generalidades. La Dirección debe revisar el SGC de la Organización a intérvalos planificados.
A92: =COUNTIF(#REF!,"X") -> #REF! | B92: 9.3.2. | C92: Entradas de la revisión por la Dirección.
A93: =COUNTIF(#REF!,"X") -> #REF! | B93: 9.3.3. | C93: Salidas de la revisión por la dirección.
A94: =COUNTIF(#REF!,"X") -> #REF!
A95: 9 | B95: 10. | C95: MEJORA
A96: =COUNTIF(#REF!,"X") -> #REF! | B96: 10.1. | C96: Generalidades. La org. debe determinar y seleccionar las oportunidades de mejora e implementar cualquier acción necesaria para cumplir los req. del cliente y aumentar la satisfacción del cliente.
A97: =COUNTIF(#REF!,"X") -> #REF! | B97: 10.2. | C97: No Conformidad y Acción Correctiva
A98: =COUNTIF(#REF!,"X") -> #REF! | B98: 10.2.1. | C98: Cuando ocurra una N, incluida cualquiera por quejas, la Org. Debe: a) reaccionar ante la NC, b) evaluar la necesidad de acciones para eliminar las causas de la NC, c) implementar cualquier cosa necesaria, d) revisar la eficacia de cualquier AC tomada, e) si fuera necesario, actualizar los riesgos y oportunidades determinadas durante la planificación, y f) si fuera necesario, hacer cambios al SGC.
A99: =COUNTIF(#REF!,"X") -> #REF! | B99: 10.2.2. | C99: La organización debe conservar información documetnada como evidencia de: a) la naturaleza de las NC y cualquier acción tomada pertinente; b) los resultados de cualquier accioón correctiva.
A100: =COUNTIF(#REF!,"X") -> #REF! | B100: 10.3 | C100: Mejroa continua

Sheet SGC-Vigente
A1: BD SGC - Vigente
A2: ID | B2: Cód. | C2: Proceso / Subproceso / Programa Académico | D2: Objetivo del Proceso | E2: Requisitos de Ley | F2: Requisito ISO 9001:2015 Aplicable | G2: Requisitos del Usuario | H2: Requisitos de la Institución | I2: Indicadores | J2: Documentación Vigente
A3: =COUNTA(C$3:C3) -> 1 | B3: DO | C3: Docencia | D3: Gestionar las diferentes actividades del currículo encaminado a la formación integral de profesionales como gestores de cambio y transformación en los diferentes contextos sociales. | E3: • Ley 30 de 1992 y decretos asociados • Ley 1740 del 2014 • Decreto único 1075 circular # 31 MEN • Decreto 1330 de 2019 del MEN • Acuerdo 02 del CESU • Ley de emprendimiento | F3: 4.4 • 5.1.2 • 6.1 • 7.1.1 • 7.1.2 • 7.1.3 • 7.1.4 • 7.1.5 • 7.1.6 • 7.4 • 7.5.1 • 7.5.2 • 7.5.3 • 8.1 • 8.2.1 • 8.2.2 • 8.2.3 • 8.2.4 • 8.3.1 • 8.3.2 • 8.3.3 • 8.3.4 • 8.3.5 • 8.3.6 • 8.5.1 • 8.5.2 • 8.5.3 • 8.5.4 • 8.5.5 • 8.5.6 • 8.6 • 8.7 • 9.1.1 • 9.1.2 • 9.1.3 • 10.2 • 10.3 | G3: • Información veraz, pertinente y oportuna • Servicio de Educación Superior acorde con los lineamientos del MEN. | H3: • Estatuto General • Estatuto Docente • Reglamento Estudiantil • Reglamento Consultorio Jurídico • Reglamento Alternativas de Grado • Reglamento Prácticas Universitarias Psicología • Reglamento Uso del Correo Institucional • Acuerdos de los Consejos Superior y Académico • Manual de Funciones • Resoluciones de Rectoría • Política de Protección de Datos Personales * Política de Educación Virtual y a Distancia | I3: Tasa técnica ( # de estudiantes / # de docentes tiempo completo) Deserción (# estudiantes desertores / # de estudiantes matriculados) Tasa de Graduación (tiempo de graduación cohorte) Bajo rendimiento (# estudiantes en bajo rendimiento /# de estudiantes matriculados) Evaluación Docente (# docentes con calificación >=4/ # de docentes evaluados) | J3: • PR-GC-004 "Acciones Correctivas"
A4: =COUNTA(C$3:C4) -> 2 | B4: RA | C4: Registro Académico | D4: Administrar el sistema de registro y control académico, asegurando el cumplimiento de los criterios institucionales en lo concerniente a los asuntos académicos basado en la normativa institucional. | E4: • Ley 594 del 2000 Bases de datos Ley 1581 de 2012. | F4: • 7.1 • 7.2 • 7.3 • 7.5 • 7.5.1 • 7.5.2 • 7.5.3 • 8.7 • 9.1 • 9.1.1 • 9.1.2 • 9.1.3 •10.2 • 10.3 | G4: • Información veraz y oportuna, confidencialidad y ética. | H4: Reglamento estudiantil, estatutos y Política de tratamiento de datos personales | I4: • Efectividad de las certificaciones expedidas | J4: • PR-RA-004 "Emisión de Constancias y Certificaciones Académicas" • PR-DO-001"Procedimiento Homologación Interna y Externa" • PR-GC-004 "Acciones Correctivas"
A5: =COUNTA(C$3:C5) -> 3 | B5: CU | C5: Gestión Curricular | D5: Garantizar la efectividad del diseño curricular de la institución atendiendo los lineamientos del Ministerio de Educación Nacional y Normativa Interna. | E5: Decreto 1330 de 2019 del MEN | F5: 4.4 • 6.1 • 7.1 • 7.2 • 7.4 • 7.5 • 7.5.1 • 7.5.2 • 7.5.3 •8.2 • 8.3 • 8.5.2 • 8.5.4 • 8.5.5 • 8.5.6 • 9.1 • 10 | G5: • Información veraz, pertinente y oportuna • Servicio de Educación Superior acorde con los lineamientos del MEN. | H5: * Política de Créditos* Política de Gestión Curricular* Lineamientos de Gestión Curricular* Acuerdos de los Consejos Superior y Académico que apliquen.* Resoluciones de Rectoría | J5: PR-CU-001 Procedimiento Gestión Curricular V1 PR-GC-004 "Acciones Correctivas"
A6: =COUNTA(C$3:C6) -> 4 | B6: IN | C6: Investigación, Desarrollo e Innovación | D6: Promover la investigación científica y formativa en la Institución impulsando el pensamiento creativo y crítico, el desarrollo tecnológico, la innovación y el desarrollo cultural aportando al fortalecimiento del proceso de enseñanza y aprendizaje en la región. | E6: • Decreto 1295 • Política de propiedad intelectual • Ley SPINOFF • Política de apropiación social de la ciencia, la tecnología y la innovación • Plan estratégico nacional de investigación ambiental • PECTIA 2017-2027 • Política Nacional de Ciencia, tecnología e innovación 2021-2030 • Decreto 1330 • CESU 02 | F6: • 4.4 • 6.1 • 7.1 • 7.1.1 • 7.1.2 • 7.1.3 • 7.1.4 • 7.1.5 • 7.1.6 • 7.4 • 7.5 • 7.5.1 • 7.5.2 • 7.5.3 • 8.7 1 • 9.1.2 • 9.1.3 • 10.2 • 10.3 | G6: • Información veraz, pertinente y oportuna. | H6: • Estatuto General • Política del Sistema de Investigación, Desarrollo e Innovación • Política de Responsabilidad y Sostenibilidad Ambiental • Reglamento Estudiantil •Política Editorial • Reglamento de Propiedad Intelectual | I6: • Docentes Investigadores • Productos de Investigación • Grupos de Investigación clasificados en Colciencias • Semilleros de Investigación | J6: •MA-IN-002"ManualdeGestióndeGruposdeInvestigación" •MA-IN-003"ManualdeGestióndeSemillerosdeInvestigación" •PR-IN-001"GestióndelasFormasOrganizativasdelaInvestigación" •PR-IN-002"ConvocatoriaInternayExternaparaProyectosdeInvestigación" •PR-IN-003"SolicituddeApoyoFinancieroalSIDI" •PR-IN-006"PresentaciónProyectosdeInvestigaciónenConvocatoriasExternas" •PR-IN-007"ElaboraciónyTrámitedelActadePropiedadIntelectual" •PR-IN-010"ContrataciónJóvenInvestigador" •PR-GC-004 "Acciones Correctivas"
A7: =COUNTA(C$3:C7) -> 5 | B7: EX | C7: Extensión y Proyección Social | D7: Aportar en el desarrollo y transformación social de la comunidad mediante la implementación de estrategias, proyectos y servicios que impacten a los grupos de interés. | E7: • Ley 115 de 1994 (Art. 1), • Ley 30 de 1992 (Art. 1 - Cap. 1º) - (Art. 120) • Decreto 1075 de 2015 • Decreto 1330 de 2019 del MEN • Ley 1014 del 26-Ene-2006. | F7: • 4.4 • 6.1 • 7.1 • 7.1.1 • 7.1.2 • 7.1.3 • 7.1.4 • 7.1.5 • 7.1.6 • 7.4 • 7.5 • 7.5.1 • 7.5.2 • 7.5.3 • 8.7 1 • 9.1.2 • 9.1.3 • 10.2 • 10.3 | G7: • Información veraz y oportuna • Asesoramiento metodológico • Seguimiento a los avances • Respuesta oportuna a problemáticas planteadas • Comunicación efectiva y • Servicio eficiente. | H7: • Acuerdo 091 de 19-may-2010 • Acuerdo 015 del 22-Nov-2009 • Acuerdo 03 del 24-Ago-2012. . | I7: • Beneficiados de los Procesos de Extensión | J7: • CP-EC-001 “Educación Continuada” • CP-GE-001 “Gestión de Egresados” • CP-EM-001 “Emprendimiento” • PR-GC-004 "Acciones Correctivas"
A8: =COUNTA(C$3:C8) -> 6 | B8: EM | C8: Emprendimiento | D8: Contribuir al desarrollo del espiritu emprendedor a través de acciones interdiscipinarias que aporten a soluciones integrales a los retos del contexto local y regional | E8: • Ley 115 de 1994 (Art. 1), • Ley 30 de 1992 (Art. 1 - Cap. 1º) - (Art. 120) •Decreto 1075 de 2015 • Decreto 1330 de 2019 del MEN • Ley 1014 del 26-Ene-2006. | F8: • 4.4 • 6.1 • 7.1 • 7.1.1 • 7.1.2 • 7.1.3 • 7.1.4 • 7.1.5 • 7.1.6 • 7.4 • 7.5 • 7.5.1 • 7.5.2 • 7.5.3 • 8.7 1 • 9.1.2 • 9.1.3 • 10.2 • 10.3 | G8: • Información veraz y oportuna • Asesoramiento metodológico • Seguimiento a los avances • Respuesta oportuna a problemáticas planteadas • Comunicación efectiva y • Servicio eficiente. | H8: • Política Institucional de Emprendimiento • Acuerdo 091 de 19-may-2010 • Acuerdo 015 del 22-Nov-2009 • Acuerdo 03 del 24-Ago-2012. | I8: • %Carcaterización de emprendimeitno atendidos • % Estudiantes atendidos en la unidad de emprendimiento | J8: • PR-GC-004 "Acciones Correctivas"
A9: =COUNTA(C$3:C9) -> 7 | B9: GE | C9: Gestión de Egresados | D9: Realizar seguimiento a los egresados de la Institución, identificando las necesidades del entorno y la correspondencia del perfil profesional frente a su ubicación laboral para generar espacios de vinculación, inclusión y participación activa de los egresados en actividades Institucionales que contribuyan con su desarrollo profesional. | E9: • Ley 30 de 1992 (Art. 1 - Cap. 1º) - (Art. 120) • Decreto 1330 de 2019 del MEN • Cesu Acuerdo 02 de 2020 | F9: •4.4 • 6.1 • 7.1 • 7.1.1 • 7.1.2 • 7.1.3 • 7.1.4 • 7.1.5 • 7.1.6 • 7.4 • 7.5 • 7.5.1 • 7.5.2 • 7.5.3 • 8.7 1 • 9.1.2 • 9.1.3 • 10.2 • 10.3 | G9: • Información veraz y oportuna • Asesoramiento metodológico • Comunicación efectiva • Servicio eficiente. | H9: "• Política de Egresados • Política de Extensión y Proyección Social" | I9: • Contactabilidad de los egresados. | J9: • PR-GC-004 "Acciones Correctivas"
A10: =COUNTA(C$3:C10) -> 8 | B10: EC | C10: Educación Continuada | D10: Promover la formación y capacitación permanente a lo largo de la vida en procesos de competencias laborales y capacitación a través de la Educación No Formal con el fin de fortalecer habilidades, destrezas y competencias que mejoren no solo la posición si no la inserción laboral de personas que deseen mejorar o actualizar sus capacidades y desarrollarse de manera integral. | E10: •Ley 30 de 1992, título VI, Capítulo I, Art. 120•Ley 115 de 1994, Capítulo II•Decreto 114 del 15 de enero de 1996, Capítulo I y II•Resolución 626 de 2007 Modificada por la Resolución 1622 de 2007 | F10: 4.1. 4.2. 4.3. 4.4. 6.1. 6.2. 6.2.2. 6.3. 7.1.3. 7.1.4. 7.2. 7.5. 7.5.3. 7.5.3.1 8.1. 8.2.1. 8.2.2. 8.2.3.1. 8.4.2. 8.5.1. 8.6. 8.7. 8.7.2. 9.1. 9.1.2. 9.3.2. 10.2.1. | G10: • Información confiable, veráz y oportuna. | H10: • Política de Extensión y Proyección Social • Acuerdo 012 del 18 de mayo de 2023 Lineamientos de Educación Continuada | I10: Tasa de participación oferta educación continuada = número de estudiantes que tomaron la oferta / número de aspirantes inscritos * 100 Cumplimiento de metas financieras = ingresos recibidos / ingresos proyectados Satisfacción de los usuarios = promedio de calificación de satisfacción de 4 en el 75% de la población a partir de un formulario en línea | J10: MA-EC-001 "Manual de Procedimientos Educación Continuada" PR-GC-004 "Acciones Correctivas"
A11: =COUNTA(C$3:C11) -> 9 | B11: PE | C11: Gestión de Proyectos de Extensión | D11: Administrar, planificar, coordinar la ejecución y realizar seguimiento y control de las actividades y recursos asignados a los proyectos de extensión y proyección social de la Institución, de manera que se cumpla el alcance en el tiempo establecido y con los costos presupuestados. | E11: • Ley 115 de 1994 (Art. 1), • Ley 30 de 1992 (Art. 1 - Cap. 1º) - (Art. 120) • Decreto 1075 de 2015 • Decreto 1330 de 2019 del MEN • Ley 1014 del 26-Ene-2006. | F11: • 4.4 • 6.1 • 7.1 • 7.1.1 • 7.1.2 • 7.1.3 • 7.1.4 • 7.1.5 • 7.1.6 • 7.4 • 7.5 • 7.5.1 • 7.5.2 • 7.5.3 • 8.7 1 • 9.1.2 • 9.1.3 • 10.2 • 10.3 | G11: • Información confiable, veráz y oportuna. | H11: Politica Extensión y Proyección Social
A12: =COUNTA(C$3:C12) -> 10 | B12: EF | C12: Escuela de Formación para el TDH | D12: Ofertar programas de educación continuada para el desarrollo laboral y fortalecimiento de competencias de la comunidad académica en general | E12: • Ley 30 de 1992 • Ley 115 de 1994 • Ley 715 de 2001 • Decreto 1075 de 2015 • Licencia de Funcionamiento • Directrices y Lineamientos de Entes Gubernamentales | F12: • 4.4 • 5.1.2 • 6.1 • 7.1.1 • 7.1.2 • 7.1.3 • 7.1.4 • 7.1.5 • 7.1.6 • 7.4 • 7.5.1 • 7.5.2 • 7.5.3 • 8.1 • 8.2.1 • 8.2.2 • 8.2.3 • 8.2.4 • 8.3.1 • 8.3.2 • 8.3.3 • 8.3.4 • 8.3.5 • 8.3.6 • 8.5.1 • 8.5.2 • 8.5.3 • 8.5.4 • 8.5.5 • 8.5.6 • 8.6 • 8.7 • 9.1.2 • 9.1.3 • 10.2 • 10.3 | G12: • Información veraz y oportuna • Cumplimiento de los horarios. | H12: • Información oportuna y confiable • Cumplimiento de funciones. | I12: • Estudiantes atendidos | J12: • MA-EF-03 "Manual de Procedimientos Escuela de Formación" • MA-EF-04 "Manual de Procedimientos Escuela Informus" • MA-EF-03 "Manual de Procedimientos Escuela de Formación" • MA-EF-04 "Manual de Procedimientos Escuela Informus" • MA-EF-03 "Manual de Procedimientos Escuela de Formación" • MA-EF-04 "Manual de Procedimientos Escuela Informus" • MA-EF-03 "Manual de Procedimientos Escuela de Formación" • MA-EF-04 "Manual de Procedimientos Escuela Informus" • PR-GC-004 "Acciones Correctivas"
A13: =COUNTA(C$3:C13) -> 11 | B13: DE | C13: Direccionamiento Estratégico | D13: Establecer los lineamientos para la estructuración del Plan de Desarrollo institucional mediante la implementación de estrategias, objetivos estratégicos y planes de mejoramiento Institucional que garanticen la satisfacción de los usuarios y las expectativas de los grupos de interés. | E13: • Ley 30 • Ley 715 • Ley 115 • Ley 30 • Decreto 1075 de 2015 • Ley 152 orgánica del plan de desarrollo | F13: • 4.1 . 4.2 . 4.3 . 4.4 . 5.1 . 5.1.1 . 5.1.2 . 5.2 . 5.2.1 . 5.2.2 . 5.3 . 6.1 . 6.2 . 7.1 . 7.1.2 . 7.1.3 . 7.1.4 . 7.5 . 7.5.1 . 7.5.2 . 7.5.3 . 9.3 . 9.3.1 . 9.3.2 . 9.3.3 . | G13: • Información veraz y oportuna | H13: • Cumplimiento Estatutos Institucionales | I13: • Cumplimiento Total del Plan de Desarrollo Institucional • Satisfacción del Usuario | J13: • PR-GC-004 "Acciones Correctivas"
A14: =COUNTA(C$3:C14) -> 12 | B14: PL | C14: Planeación Institucional | D14: Asegurar la alineación de las estrategias, objetivos estratégicos y planes de mejoramiento Institucional con el Plan de Desarrollo Institucional y Proyecto Educativo Institucional, teniendo como marco de referencia los lineamientos establecidos por la Alta Dirección, del gobierno nacional y las tendencias internacionales, nacionales y regionales . | E14: • Ley 30 • Ley 115 • Ley 152 orgánica del plan de desarrollo • Acuerdo 02 CNA | F14: • 4.1 • 4.2 • 5.1 • 5.1.1 • 5.1.2 • 5.2 • 5.2.1 . 5.2.2 5.3 • 6.1 • 6.2 . 7.1 . 7.1.2 . 7.1.3 . 7.1.4 . 7.1.5 . 7.1.6• 9.1 • 9.1.1 . 9.1.2 . 9.1.3 • 10.1 • 10.2 • 10.3 | G14: • Información veraz y oportuna | H14: •Acuerdo 019 Plan de desarrollo 2024 - 2032 • Política de Buen Gobierno y Rendición de Cuentas | I14: • Cumplimiento del Plan de Desarrollo Institucional. | J14: •PR-PL-003 "Seguimiento al Formato Único de Gestión"• PR-GC-004 "Acciones Correctivas" *PR-PL-003 "Seguimiento al Formato Único de Gestión"
A15: =COUNTA(C$3:C15) -> 13 | B15: SI | C15: Gestión de Sistemas de Información | D15: Planificar, desarrollar e implementar soluciones tecnológicas asociadas al Sistema de Información de Registro Estudiantil (SIRES), garantizando la integridad, veracidad y disponibilidad de la información por parte de la Comunidad Académica que la requiera. | E15: Ley 1581 de 2012 Ley de proteccióde datos personales | F15: • 7.1.3 • 7.5.3 • 8.2 • 8.2.1 . 8.2.2 . 8.2.3 . 8.2.4 .8.5.2 • 8.5.3 • 9.1.1 • 9.1.2 . 9.1.3 . 10.2 • 10.3 | G15: • Información veraz y oportuna | H15: • Política de protección de datos personales | I15: • Accesibilidad del Sistemas de Información (SIRES) • Avance de los desarrollos asociados al sistema de información SIRES en curso | J15: • MA-SI-001 "Manual Desarrollo Soluciones Tecnológicas Asociadas al SIRES" • PR-GC-004 "Acciones Correctivas"
A16: =COUNTA(C$3:C16) -> 14 | B16: GC | C16: Gestión de Calidad | D16: Administrar, mantener y apropiar el Sistema de Gestión de Calidad mediante la gestión por procesos para dar cumplimiento con los requisitos legales y reglamentarios aplicables basado en la norma ISO 9001:2015. | E16: • Ley 1188 del 2008 • Decreto 1330 de 2019 del MEN • Acuerdo CESU 02 de 2020 • Lineamientos para la acreditación de programas de pregrado CNA 2020 | F16: • 4.1 • 4.2 • 4.3 • 4.4 • 5.1.2 • 5.2 • 6.2 • 6.3 • 7.5 • 7.5.1 • 7.5.2 • 7.5.3 • 8.2 • 8.7 • 9.1 • 9.1.2 • 9.2 • 10.2 • 10.3 | G16: • Satisfacción del usuario | H16: • Política de Calidad • Resolución Rectoral 101 del 20 de septiembre 2022 | I16: • Índice de Quejas • Eficacia de acciones programadas | J16: • MA-GC-001 "Manual de Calidad" • PR-GC-001 "Elaboración y control de documentos" • PR-GC-002 "Control de registros" • PR-GC-003 Tratamiento Salidas No Conforme • PR-GC-004 "Acciones Correctivas" • PR-GC-005 "Auditorías internas de calidad" • PR-GC-006 "Petición, Quejas y Reclamos" • PR-GC-007 "Matriz de riesgos y oportunidades" • PR-GC-008 "Planificación de cambios al SGC"
A17: =COUNTA(C$3:C17) -> 15 | B17: AU | C17: Autoevaluación Institucional | D17: Coordinar los procesos de, Autoevaluación y Acreditación de los programas académicos e insitucional para cumplir con los requerimientos del Ministerio de Educación Nacional (MEN) y del Consejo Nacional de Acreditación (CNA), a través de la cultura del aseguramiento de la calidad. | E17: • Ley 1188 del 2008 • Decreto 1330 de 2019 del MEN • Acuerdo CESU 02 de 2020 • Lineamientos para la acreditación de programas de pregrado CNA 2020 • Resolución 15224 de 2020 • Resolución 21795 de 2020 | F17: • 7.5 * 7.5.1 * 7.5.2 * 7.5.3 * 8.1 * 8.2 * 8.2.1 * 8.2.2 * 8.2.3 * 8.3 * 8.3.1 * 8.3.2 * 8.3.3 * 8.3.4 * 8.3.5 * 8.3.6 * 8.5 * 8.5.1 * 8.5.2 * 8.5.3 * 8.5.4 * 8.5.5 * 8.5.6 * 9.1 * 9.1.3 * 10.2 | G17: • Información confiable • Soporte Institucional para desarrollar el proceso de autoevaluación • Lineamientos claros y amigables. | H17: • Sistema Interno de Aseguramiento de la Calidad - SIAC | I17: • % de cumplimiento implementación de los Planes de Mejoramiento Institucional (Derivados de la autoevaluación) • % de cumplimiento implementación de los Planes de Mejoramiento del Programa (Derivados de la autoevaluación) • # de procesos de autoevaluación realizados • # de procesos de autoevaluación con fines de acreditación realizado | J17: • PR-AU-001 "Procedimiento Autoevaluación Institucional y Programas Académicos" • Modelo de Autoevaluación Institucional" • Formato Plan de Mejora AE Institucional • Modelo de Autoevaluación Institucional" "Modelo de Autoevaluación para Programas Académicos" • Modelo de Autoevaluación para Programas Académicos" • PR-GC-004 "Acciones Correctivas"
A18: =COUNTA(C$3:C18) -> 16 | B18: RC | C18: Registro Calificado | D18: Asesorar, acompañar y gestionar los procesos de pre radicación y radicación de solicitudes para la obtención, modificación y renovación de registros calificados, atendiendo los requerimientos legales y normativos vigentes. | E18: • Ley 115 de 1994 • Ley 30 de 1992 • Decreto 1295 de 2010 •Resolución 2590 de 2012 • Resolución 12220 de 2016 • Resolución10414 de 2018 • Decreto 1330 de 2019 •Resolución 02265 de 2023• Decreto1174 de 2023, demás normas aplicables. | F18: • 7.5 • 7.5.1 • 7.5.2 • 7.5.3 • 8.1 • 8.2 • 8.2.1 • 8.2.2 • 8.2.3 • 8.3 • 8.3.1 • 8.3.2 • 8.3.3 • 8.3.4 • 8.3.5 • 8.3.6 • 8.5 • 8.5.1 * 8.5.2 * 8.53 * 8.5.4 * 8.5.5 * 8.5.6 * 9.1 • 9.1.3 • 9.1.3 * 10.2 | G18: • Vigencia de los registros calificados o duración de la acreditación | H18: • Acto administrativo otorgado por el MEN - Autorización para la oferta de programas académicos • Sistema Interno de Aseguramiento de la Calidad • Acuerdo 002 de 2012 • Acuerdo 001 de 2018 • Acuerdo 004 de 2018 • Acuerdo 001 de 2019 • Acuerdo 004 de 2019 • Acuerdo 012 de 2019 • Acuerdo 009 de 2021 • Acuerdo 019 de 2021 • Acuerdo 001 de 2023, demás normatividad interna aplicable | I18: • Solicitudes radicadas para obtención de Registros Calificados • Solicitudes radicadas para renovación de Registros Calificados • Eficacia en la radicación de solicitudes de registro calificado | J18: • MA-RC-002 "Manual de Procedimientos Registro Calificado" • MA-RC-002 "Manual de Procedimientos Registro Calificado" • PR-GC-004 "Acciones Correctivas"
A19: =COUNTA(C$3:C19) -> 17 | B19: VN | C19: Relaciones Interinstitucionales - ORI | D19: Brindar oportunidades a estudiantes, docentes, administrativos y egresados en escenarios académicos nacionales e internacionales que permitan la adquisición y/o fortalecimiento de competencias multiculturales en un dialogo global intercultural, mediante el fortalecimiento de las alianzas y redes interintitucionales. | E19: • Normatividad Vigente emanada del MEN | F19: • 7.5.1 • 7.5.2 • 5.1.2 • 5.2 • 5.3 • 7.1.1 • 7.1.3 • 7.1.4 • 9.1.1 • 9.1.3 • 10.2 • 10.3 | G19: • Vigencia de los convenios interinstitucionales | H19: • PEI • Política de Internacionalización •PDI | I19: • Actividad de los convenios Interinstitucionales vigentes (Convenios Interinstitucionales utilizados / Total de Convenios Interinstitucionales vigentes) | J19: • MA-VN-001 "Manual Relacionamiento Interinstitucional" • PR-VN-001 "Movilidad entrante y saliente" • MA-VN-001 "Manual Relacionamiento Interinstitucional" • PR-GC-004 "Acciones Correctivas"
A20: =COUNTA(C$3:C20) -> 18 | B20: MA | C20: Mercadeo - Admisiones | D20: Ofertar los servicios de la Institución con la comunidad académica de la región suministrando la orientación adecuada que garantice a los aspirantes realizar su proceso de inscripción, admisión y matrícula para su ingreso eficaz a alguno de los programas académicos de la FUP. | E20: • Resolución 12220 de 20 de junio de 2016 • Ley 1581 de 2012 de habeas datas, • Decreto reglamentario 1377 de 2013. | F20: • 5.1.2 • 7.1.1 • 7.1.3 • 7.1.4 •7.5 • 7.5.1 • 7.5.2 • 7.5.3 • 9.1 • 9.1.1 • 9.1.3 • 10.2 • 10.3 | G20: • Información confiable, veraz y oportuna | H20: • Cumplimiento del Reglamento Estudiantil y estatutos Institucionales • Política de Admisiones.. | I20: • Estudiantes matriculados en primer semestre | J20: • MA-MA-001 "Manual de Mercadeo" • MA-MA-001 "Manual de Mercadeo" • MA-MA-001 "Manual de Mercadeo" • PR-MA-001 "Inscripción y Matrícula de Estudiantes" • PR-RA-006 "Procedimiento Homologación Interna y Externa" • PR-MA-001 "Inscripción y Matrícula de Estudiantes" • PR-MA-001 "Inscripción y Matrícula de Estudiantes" • PR-GC-004 "Acciones Correctivas"
A21: =COUNTA(C$3:C21) -> 19 | B21: CO | C21: Comunicaciones Institucional | D21: Gestionar dinámicas de comunicación Institucional a nivel interno y externo, administrando los canales de comunicación garantizando el cumplimiento de los lineamientos de imagen corporativa. | E21: • Ley 1581 de 2012 - Habeas Data • Ley 23 de 1982 - Derechos de Autor • Resolución 12220 de 2016 - Regulación de publicidad de las Instituciones de Educación Superior • Sayco y Acinpro | F21: • 7.5 • 7.5.1 • 7.5.2 • 7.5.3 * 7.4 • 8.2.1 • 9.1 • 9.1.1 • 9.1.3 • 10.1 * 10.2 * 10.3 | G21: • Información veraz y oportuna | H21: • Cumplimiento de estatutos Acuerdo 011 de 29 de abril de 2003 • Acuerdo 005 de 22 de marzo de 2019 emitido por la Institución para la protección de los datos personales por la FUP | I21: • Divulgación de información en medios de comunicación | J21: • MA-CO-001 "Manual de procedimientos de Comunicaciones Institucional" • MA-CO-001 "Manual de procedimientos de Comunicaciones Institucional" • MA-CO-001 "Manual de procedimientos de Comunicaciones Institucional" • MA-CO-001 "Manual de procedimientos de Comunicaciones Institucional" • PR-GC-004 "Acciones Correctivas" • Cumplimiento de estatutos Acuerdo 011 de 29 de abril de 2003 • Acuerdo 005 de 22 de marzo de 2019 emitido por la Institución para la protección de los datos personales por la FUP
A22: =COUNTA(C$3:C22) -> 20 | B22: BI | C22: Bienestar Institucional | D22: Contribuir con la formación integral, el desarrollo humano, la cultura Institucional y la formación ciudadana de la comunidad académica para su desarrollo potencial, individual y colectivo que permitan el logro de los fines misionales. | E22: Ley 1188 de 2008 • Ley 30 de 1992 • Decreto 1075 de 2015 • Acuerdo 02 CESU 1 julio de 2020 • Ley 1188 de 2008 • Decreto 1330 de 2019 | F22: 7.1.2• 7.5 • 7.5.1 • 7.5.2 • 7.1.2 • 9.1 • 9.1.1 • 9.1.3 • 10.3 | G22: • Información veraz y oportuna • Cumplimiento de lo programado • Citas oportunas • Transporte adecuado | H22: • Política de Bienestar Institucional 16 de sep de 2022• Política de permanencia y Graduación 24 mar de 2023 | I22: • Impacto del programa de permanencia y graduación • % Participación en actividades bienestar | J22: • O-PL-007 • DS-BI-002 Programa de permanencia y graduación estudiantil • Portafolio Bienestar Universitario • S-BI-002 Programa de permanencia y graduación estudiantil • PR-GC-004 "Acciones Correctivas"
A23: =COUNTA(C$3:C23) -> 21 | B23: GH | C23: Gestión Humana | D23: Gestionar y mantener un talento humano competente para la prestación de los servicios ofertados por la Institución, identificando necesidades de formación que contribuyan al fortalecimiento de las competencias y desarrollando estrategias que permitan garantizar un clima laboral apto y unas condiciones de trabajo adecuadas. | E23: • Constitución Política de Colombia • Código sustantivo de trabajo • Ley 100 de 1993 • Ley 797 de 2003 • Ley 1010 de 2006 • Decreto 1075 de 2015 • Decreto 1443 de 2014 • Decreto 055 de 2015. ley 2414 de 2021 y ley 1822 de 2017 | F23: • 5.2.1 * 5.2.2 • 7.5.1 • 7.5.2 * 7.4.3 • 6.1 • 7.1 • 7.1.2 • 7.1.3 • 7.1.6 • 7.2 • 7.3 • 7.4 •7.5.1 * 7.5.2 * 9.1.1 •9.1.3 • 10.2 • 10.3 | G23: • Contratación oportuna y de calidad | H23: • Reglamento interno de trabajo • Estatutos Institucionales • Contratos laborales • Acuerdos del consejo superior • Resoluciones de Rectoría • Política de Gestión Humana • Política de Seguridad y Salud en el Trabajo | I23: • Clima Organizacional | J23: • CP-TH-001 "Caracterización Gestión del Talento Humano • CP-ST-001 "Caracterización Gestión de Seguridad y Salud en el Trabajo" • PR-GC-004 "Acciones Correctivas" • Reglamento interno de trabaj • Estatutos Institucionales •Contratos laborales • Acuerdos del consejo superior • Resoluciones de Rectoría • Política de Gestión Humana • Política de Seguridad y Salud en el Trabajo
... A32: =COUNTA(C$3:C32) -> 30 | B32: RT | C32: Recursos Tecnológicos | D32: Administrar una infraestructura tecnológica adecuada a la propuesta de valor Institucional, garantizando la seguridad de la información y el óptimo funcionamiento de los equipos tecnológicos. | E32: • Infraestructura física para las sedes (Bibliotecas y Laboratorios) • Infraestructura tecnológica (Computadores, internet, video beam, impresoras y software) • Recurso humano e insumos de oficina. | F32: • 7.1.2 • 7.1.3 • 8.4 • 8.4.1 • 8.4.2 • 8.4.3 • 8.5.2 • 8.5.3 • 9.1.1 • 9.1.3 • 10.2 • 10.3 | G32: • Oportunidad y cumplimiento | H32: • Política de Renovación y Actualización de Recursos Tecnológicos • Reglamento Uso de Salas de Cómputo • Reglamento Uso del Correo Institucional | I32: • Mantenimiento preventivo Seguimiento a la ejecución de las copias de seguridad. • Incidentes resueltos | J32: •MA-RT-001"ManualdeInfraestructuraTecnológica" •PR-RT-001"Mantenimientopreventivodeequipos" •PR-RT-002"CopiasdeSeguridad" •PR-RT-003"Solicituddesalasdecómputo" •DS-RT-002"Reglamentointernousodelcomputador" •PR-GC-004"AccionesCorrectivas".
A33: =COUNTA(C$3:C33) -> 31 | B33: RF | C33: Recursos Físicos | D33: Administrar y proveer los recursos físicos y de infraestructura necesarios para garantizar una prestación óptima del servicio de educación superior. | E33: • Decreto 1072 de 2015 | F33: • 7.5 • 7.5.1 • 7.5.2 • 7.5.3 • 7.1.2 • 7.1.3 • 7.4 • 8.4 • 8.4.1 • 8.4.2 • 8.4.3 • 9.1 • 9.1.2 • 9.1.3 • 10.3 | G33: • Infraestructura y mobiliario en buen estado Instalaciones aseadas | I33: • Ejecución del programa de mantenimiento | J33: • PR-RF-003 "Mantenimiento de Infraestructura Institucional" • PR-RF-004 "Procedimiento de limpieza Institucional" • PR-GC-004 "Acciones Correctivas"
A34: =COUNTA(C$3:C34) -> 32 | B34: PRO-1 | C34: Prog. Administración de Empresas | D34: Gestionar las diferentes actividades del currículo encaminado a la formación integral de profesionales como gestores de cambio y transformación en los diferentes contextos sociales. | E34: • Ley 30 de 1992 y decretos asociados • Ley 1740 del 2014 • Decreto único 1075 circular # 31 MEN • Decreto 1330 de 2019 del MEN • Acuerdo 02 del CESU • Ley de emprendimiento | F34: 4.4 • 5.1.2 • 6.1 • 7.1.1 • 7.1.2 • 7.1.3 • 7.1.4 • 7.1.5 • 7.1.6 • 7.4 • 7.5.1 • 7.5.2 • 7.5.3 • 8.1 • 8.2.1 • 8.2.2 • 8.2.3 • 8.2.4 • 8.3.1 • 8.3.2 • 8.3.3 • 8.3.4 • 8.3.5 • 8.3.6 • 8.5.1 • 8.5.2 • 8.5.3 • 8.5.4 • 8.5.5 • 8.5.6 • 8.6 • 8.7 • 9.1.1 • 9.1.2 • 9.1.3 • 10.2 • 10.3 | G34: • Información veraz, pertinente y oportuna • Servicio de Educación Superior acorde con los lineamientos del MEN. | H34: • Estatuto General • Estatuto Docente • Reglamento Estudiantil • Reglamento Consultorio Jurídico • Reglamento Alternativas de Grado • Reglamento Prácticas Universitarias Psicología • Reglamento Uso del Correo Institucional • Acuerdos de los Consejos Superior y Académico • Manual de Funciones • Resoluciones de Rectoría • Política de Protección de Datos Personales * Política de Educación Virtual y a Distancia | I34: Tasa técnica ( # de estudiantes / # de docentes tiempo completo) Deserción (# estudiantes desertores / # de estudiantes matriculados) Tasa de Graduación (tiempo de graduación cohorte) Bajo rendimiento (# estudiantes en bajo rendimiento /# de estudiantes matriculados) Evaluación Docente (# docentes con calificación >=4/ # de docentes evaluados) | J34: • PR-GC-004 "Acciones Correctivas"
A35: =COUNTA(C$3:C35) -> 33 | B35: PRO-2 | C35: Prog. Arquitectura | D35: Gestionar las diferentes actividades del currículo encaminado a la formación integral de profesionales como gestores de cambio y transformación en los diferentes contextos sociales. | E35: • Ley 30 de 1992 y decretos asociados • Ley 1740 del 2014 • Decreto único 1075 circular # 31 MEN • Decreto 1330 de 2019 del MEN • Acuerdo 02 del CESU • Ley de emprendimiento | F35: 4.4 • 5.1.2 • 6.1 • 7.1.1 • 7.1.2 • 7.1.3 • 7.1.4 • 7.1.5 • 7.1.6 • 7.4 • 7.5.1 • 7.5.2 • 7.5.3 • 8.1 • 8.2.1 • 8.2.2 • 8.2.3 • 8.2.4 • 8.3.1 • 8.3.2 • 8.3.3 • 8.3.4 • 8.3.5 • 8.3.6 • 8.5.1 • 8.5.2 • 8.5.3 • 8.5.4 • 8.5.5 • 8.5.6 • 8.6 • 8.7 • 9.1.1 • 9.1.2 • 9.1.3 • 10.2 • 10.3 | G35: • Información veraz, pertinente y oportuna • Servicio de Educación Superior acorde con los lineamientos del MEN. | H35: • Estatuto General • Estatuto Docente • Reglamento Estudiantil • Reglamento Consultorio Jurídico • Reglamento Alternativas de Grado • Reglamento Prácticas Universitarias Psicología • Reglamento Uso del Correo Institucional • Acuerdos de los Consejos Superior y Académico • Manual de Funciones • Resoluciones de Rectoría • Política de Protección de Datos Personales * Política de Educación Virtual y a Distancia | I35: Tasa técnica ( # de estudiantes / # de docentes tiempo completo) Deserción (# estudiantes desertores / # de estudiantes matriculados) Tasa de Graduación (tiempo de graduación cohorte) Bajo rendimiento (# estudiantes en bajo rendimiento /# de estudiantes matriculados) Evaluación Docente (# docentes con calificación >=4/ # de docentes evaluados) | J35: • PR-GC-004 "Acciones Correctivas"
A36: =COUNTA(C$3:C36) -> 34 | B36: PRO-3 | C36: Prog. Derecho | D36: Gestionar las diferentes actividades del currículo encaminado a la formación integral de profesionales como gestores de cambio y transformación en los diferentes contextos sociales. | E36: • Ley 30 de 1992 y decretos asociados • Ley 1740 del 2014 • Decreto único 1075 circular # 31 MEN • Decreto 1330 de 2019 del MEN • Acuerdo 02 del CESU • Ley de emprendimiento | F36: 4.4 • 5.1.2 • 6.1 • 7.1.1 • 7.1.2 • 7.1.3 • 7.1.4 • 7.1.5 • 7.1.6 • 7.4 • 7.5.1 • 7.5.2 • 7.5.3 • 8.1 • 8.2.1 • 8.2.2 • 8.2.3 • 8.2.4 • 8.3.1 • 8.3.2 • 8.3.3 • 8.3.4 • 8.3.5 • 8.3.6 • 8.5.1 • 8.5.2 • 8.5.3 • 8.5.4 • 8.5.5 • 8.5.6 • 8.6 • 8.7 • 9.1.1 • 9.1.2 • 9.1.3 • 10.2 • 10.3 | G36: • Información veraz, pertinente y oportuna • Servicio de Educación Superior acorde con los lineamientos del MEN. | H36: • Estatuto General • Estatuto Docente • Reglamento Estudiantil • Reglamento Consultorio Jurídico • Reglamento Alternativas de Grado • Reglamento Prácticas Universitarias Psicología • Reglamento Uso del Correo Institucional • Acuerdos de los Consejos Superior y Académico • Manual de Funciones • Resoluciones de Rectoría • Política de Protección de Datos Personales * Política de Educación Virtual y a Distancia | I36: Tasa técnica ( # de estudiantes / # de docentes tiempo completo) Deserción (# estudiantes desertores / # de estudiantes matriculados) Tasa de Graduación (tiempo de graduación cohorte) Bajo rendimiento (# estudiantes en bajo rendimiento /# de estudiantes matriculados) Evaluación Docente (# docentes con calificación >=4/ # de docentes evaluados) | J36: • PR-GC-004 "Acciones Correctivas"
A37: =COUNTA(C$3:C37) -> 35 | B37: PRO-4 | C37: Prog. Licenciatura Ed. Art. y Cultural | D37: Gestionar las diferentes actividades del currículo encaminado a la formación integral de profesionales como gestores de cambio y transformación en los diferentes contextos sociales. | E37: • Ley 30 de 1992 y decretos asociados • Ley 1740 del 2014 • Decreto único 1075 circular # 31 MEN • Decreto 1330 de 2019 del MEN • Acuerdo 02 del CESU • Ley de emprendimiento | F37: 4.4 • 5.1.2 • 6.1 • 7.1.1 • 7.1.2 • 7.1.3 • 7.1.4 • 7.1.5 • 7.1.6 • 7.4 • 7.5.1 • 7.5.2 • 7.5.3 • 8.1 • 8.2.1 • 8.2.2 • 8.2.3 • 8.2.4 • 8.3.1 • 8.3.2 • 8.3.3 • 8.3.4 • 8.3.5 • 8.3.6 • 8.5.1 • 8.5.2 • 8.5.3 • 8.5.4 • 8.5.5 • 8.5.6 • 8.6 • 8.7 • 9.1.1 • 9.1.2 • 9.1.3 • 10.2 • 10.3 | G37: • Información veraz, pertinente y oportuna • Servicio de Educación Superior acorde con los lineamientos del MEN. | H37: • Estatuto General • Estatuto Docente • Reglamento Estudiantil • Reglamento Consultorio Jurídico • Reglamento Alternativas de Grado • Reglamento Prácticas Universitarias Psicología • Reglamento Uso del Correo Institucional • Acuerdos de los Consejos Superior y Académico • Manual de Funciones • Resoluciones de Rectoría • Política de Protección de Datos Personales * Política de Educación Virtual y a Distancia | I37: Tasa técnica ( # de estudiantes / # de docentes tiempo completo) Deserción (# estudiantes desertores / # de estudiantes matriculados) Tasa de Graduación (tiempo de graduación cohorte) Bajo rendimiento (# estudiantes en bajo rendimiento /# de estudiantes matriculados) Evaluación Docente (# docentes con calificación >=4/ # de docentes evaluados) | J37: • PR-GC-004 "Acciones Correctivas"
A38: =COUNTA(C$3:C38) -> 36 | B38: PRO-5 | C38: Prog. Psicología | D38: Gestionar las diferentes actividades del currículo encaminado a la formación integral de profesionales como gestores de cambio y transformación en los diferentes contextos sociales. | E38: • Ley 30 de 1992 y decretos asociados • Ley 1740 del 2014 • Decreto único 1075 circular # 31 MEN • Decreto 1330 de 2019 del MEN • Acuerdo 02 del CESU • Ley de emprendimiento | F38: 4.4 • 5.1.2 • 6.1 • 7.1.1 • 7.1.2 • 7.1.3 • 7.1.4 • 7.1.5 • 7.1.6 • 7.4 • 7.5.1 • 7.5.2 • 7.5.3 • 8.1 • 8.2.1 • 8.2.2 • 8.2.3 • 8.2.4 • 8.3.1 • 8.3.2 • 8.3.3 • 8.3.4 • 8.3.5 • 8.3.6 • 8.5.1 • 8.5.2 • 8.5.3 • 8.5.4 • 8.5.5 • 8.5.6 • 8.6 • 8.7 • 9.1.1 • 9.1.2 • 9.1.3 • 10.2 • 10.3 | G38: • Información veraz, pertinente y oportuna • Servicio de Educación Superior acorde con los lineamientos del MEN. | H38: • Estatuto General • Estatuto Docente • Reglamento Estudiantil • Reglamento Consultorio Jurídico • Reglamento Alternativas de Grado • Reglamento Prácticas Universitarias Psicología • Reglamento Uso del Correo Institucional • Acuerdos de los Consejos Superior y Académico • Manual de Funciones • Resoluciones de Rectoría • Política de Protección de Datos Personales * Política de Educación Virtual y a Distancia | I38: Tasa técnica ( # de estudiantes / # de docentes tiempo completo) Deserción (# estudiantes desertores / # de estudiantes matriculados) Tasa de Graduación (tiempo de graduación cohorte) Bajo rendimiento (# estudiantes en bajo rendimiento /# de estudiantes matriculados) Evaluación Docente (# docentes con calificación >=4/ # de docentes evaluados) | J38: • PR-GC-004 "Acciones Correctivas"
A39: =COUNTA(C$3:C39) -> 37 | B39: PRO-6 | C39: Prog. Trabajo Social | D39: Gestionar las diferentes actividades del currículo encaminado a la formación integral de profesionales como gestores de cambio y transformación en los diferentes contextos sociales. | E39: • Ley 30 de 1992 y decretos asociados • Ley 1740 del 2014 • Decreto único 1075 circular # 31 MEN • Decreto 1330 de 2019 del MEN • Acuerdo 02 del CESU • Ley de emprendimiento | F39: 4.4 • 5.1.2 • 6.1 • 7.1.1 • 7.1.2 • 7.1.3 • 7.1.4 • 7.1.5 • 7.1.6 • 7.4 • 7.5.1 • 7.5.2 • 7.5.3 • 8.1 • 8.2.1 • 8.2.2 • 8.2.3 • 8.2.4 • 8.3.1 • 8.3.2 • 8.3.3 • 8.3.4 • 8.3.5 • 8.3.6 • 8.5.1 • 8.5.2 • 8.5.3 • 8.5.4 • 8.5.5 • 8.5.6 • 8.6 • 8.7 • 9.1.1 • 9.1.2 • 9.1.3 • 10.2 • 10.3 | G39: • Información veraz, pertinente y oportuna • Servicio de Educación Superior acorde con los lineamientos del MEN. | H39: • Estatuto General • Estatuto Docente • Reglamento Estudiantil • Reglamento Consultorio Jurídico • Reglamento Alternativas de Grado • Reglamento Prácticas Universitarias Psicología • Reglamento Uso del Correo Institucional • Acuerdos de los Consejos Superior y Académico • Manual de Funciones • Resoluciones de Rectoría • Política de Protección de Datos Personales * Política de Educación Virtual y a Distancia | I39: Tasa técnica ( # de estudiantes / # de docentes tiempo completo) Deserción (# estudiantes desertores / # de estudiantes matriculados) Tasa de Graduación (tiempo de graduación cohorte) Bajo rendimiento (# estudiantes en bajo rendimiento /# de estudiantes matriculados) Evaluación Docente (# docentes con calificación >=4/ # de docentes evaluados) | J39: • PR-GC-004 "Acciones Correctivas"
A40: =COUNTA(C$3:C40) -> 38 | B40: PRO-7 | C40: PPN - Prog. Ecología | D40: Gestionar las diferentes actividades del currículo encaminado a la formación integral de profesionales como gestores de cambio y transformación en los diferentes contextos sociales. | E40: • Ley 30 de 1992 y decretos asociados • Ley 1740 del 2014 • Decreto único 1075 circular # 31 MEN • Decreto 1330 de 2019 del MEN • Acuerdo 02 del CESU • Ley de emprendimiento | F40: 4.4 • 5.1.2 • 6.1 • 7.1.1 • 7.1.2 • 7.1.3 • 7.1.4 • 7.1.5 • 7.1.6 • 7.4 • 7.5.1 • 7.5.2 • 7.5.3 • 8.1 • 8.2.1 • 8.2.2 • 8.2.3 • 8.2.4 • 8.3.1 • 8.3.2 • 8.3.3 • 8.3.4 • 8.3.5 • 8.3.6 • 8.5.1 • 8.5.2 • 8.5.3 • 8.5.4 • 8.5.5 • 8.5.6 • 8.6 • 8.7 • 9.1.1 • 9.1.2 • 9.1.3 • 10.2 • 10.3 | G40: • Información veraz, pertinente y oportuna • Servicio de Educación Superior acorde con los lineamientos del MEN. | H40: • Estatuto General • Estatuto Docente • Reglamento Estudiantil • Reglamento Consultorio Jurídico • Reglamento Alternativas de Grado • Reglamento Prácticas Universitarias Psicología • Reglamento Uso del Correo Institucional • Acuerdos de los Consejos Superior y Académico • Manual de Funciones • Resoluciones de Rectoría • Política de Protección de Datos Personales * Política de Educación Virtual y a Distancia | I40: • Tasa técnica (Docentes por estudiante) • Deserción (x Periodo - x Cohorte) • Tasa de Graduación (Graduados por Cohorte) • Estudiantes en Investigación (Semilleros) • # de actualizaciones del PEP • Nivel de cualificación • Cumplimiento de matrículas académicas asociada al calendario académico • Cumplimiento de fechas del Calendario ICFES • Cumplimiento con el Registro de Notas • Entrega oportuna de informes • Cumplimiento de compromisos docentes • Resultados del período T-1 (Evaluación Docente) | J40: • PR-GC-004 "Acciones Correctivas"
A41: =COUNTA(C$3:C41) -> 39 | B41: PRO-8 | C41: PPN - Prog. Ingeniería de Sistemas | D41: Gestionar las diferentes actividades del currículo encaminado a la formación integral de profesionales como gestores de cambio y transformación en los diferentes contextos sociales. | E41: • Ley 30 de 1992 y decretos asociados • Ley 1740 del 2014 • Decreto único 1075 circular # 31 MEN • Decreto 1330 de 2019 del MEN • Acuerdo 02 del CESU • Ley de emprendimiento | F41: 4.4 • 5.1.2 • 6.1 • 7.1.1 • 7.1.2 • 7.1.3 • 7.1.4 • 7.1.5 • 7.1.6 • 7.4 • 7.5.1 • 7.5.2 • 7.5.3 • 8.1 • 8.2.1 • 8.2.2 • 8.2.3 • 8.2.4 • 8.3.1 • 8.3.2 • 8.3.3 • 8.3.4 • 8.3.5 • 8.3.6 • 8.5.1 • 8.5.2 • 8.5.3 • 8.5.4 • 8.5.5 • 8.5.6 • 8.6 • 8.7 • 9.1.1 • 9.1.2 • 9.1.3 • 10.2 • 10.3 | G41: • Información veraz, pertinente y oportuna • Servicio de Educación Superior acorde con los lineamientos del MEN. | H41: • Estatuto General • Estatuto Docente • Reglamento Estudiantil • Reglamento Consultorio Jurídico • Reglamento Alternativas de Grado • Reglamento Prácticas Universitarias Psicología • Reglamento Uso del Correo Institucional • Acuerdos de los Consejos Superior y Académico • Manual de Funciones • Resoluciones de Rectoría • Política de Protección de Datos Personales * Política de Educación Virtual y a Distancia | I41: • Tasa técnica (Docentes por estudiante) • Deserción (x Periodo - x Cohorte) • Tasa de Graduación (Graduados por Cohorte) • Estudiantes en Investigación (Semilleros) • # de actualizaciones del PEP • Nivel de cualificación • Cumplimiento de matrículas académicas asociada al calendario académico • Cumplimiento de fechas del Calendario ICFES • Cumplimiento con el Registro de Notas • Entrega oportuna de informes • Cumplimiento de compromisos docentes • Resultados del período T-1 (Evaluación Docente) | J41: • PR-GC-004 "Acciones Correctivas"
A42: =COUNTA(C$3:C42) -> 40 | B42: PRO-9 | C42: PPN - Prog. Ingeneiría Industrial | D42: Gestionar las diferentes actividades del currículo encaminado a la formación integral de profesionales como gestores de cambio y transformación en los diferentes contextos sociales. | E42: • Ley 30 de 1992 y decretos asociados • Ley 1740 del 2014 • Decreto único 1075 circular # 31 MEN • Decreto 1330 de 2019 del MEN • Acuerdo 02 del CESU • Ley de emprendimiento | F42: 4.4 • 5.1.2 • 6.1 • 7.1.1 • 7.1.2 • 7.1.3 • 7.1.4 • 7.1.5 • 7.1.6 • 7.4 • 7.5.1 • 7.5.2 • 7.5.3 • 8.1 • 8.2.1 • 8.2.2 • 8.2.3 • 8.2.4 • 8.3.1 • 8.3.2 • 8.3.3 • 8.3.4 • 8.3.5 • 8.3.6 • 8.5.1 • 8.5.2 • 8.5.3 • 8.5.4 • 8.5.5 • 8.5.6 • 8.6 • 8.7 • 9.1.1 • 9.1.2 • 9.1.3 • 10.2 • 10.3 | G42: • Información veraz, pertinente y oportuna • Servicio de Educación Superior acorde con los lineamientos del MEN. | H42: • Estatuto General • Estatuto Docente • Reglamento Estudiantil • Reglamento Consultorio Jurídico • Reglamento Alternativas de Grado • Reglamento Prácticas Universitarias Psicología • Reglamento Uso del Correo Institucional • Acuerdos de los Consejos Superior y Académico • Manual de Funciones • Resoluciones de Rectoría • Política de Protección de Datos Personales * Política de Educación Virtual y a Distancia | I42: • Tasa técnica (Docentes por estudiante) • Deserción (x Periodo - x Cohorte) • Tasa de Graduación (Graduados por Cohorte) • Estudiantes en Investigación (Semilleros) • # de actualizaciones del PEP • Nivel de cualificación • Cumplimiento de matrículas académicas asociada al calendario académico • Cumplimiento de fechas del Calendario ICFES • Cumplimiento con el Registro de Notas • Entrega oportuna de informes • Cumplimiento de compromisos docentes • Resultados del período T-1 (Evaluación Docente) | J42: • PR-GC-004 "Acciones Correctivas"
A43: =COUNTA(C$3:C43) -> 41 | B43: PRO-10 | C43: PPN - Prog. Licenciatura Ed. Art. y Cultural | D43: Gestionar las diferentes actividades del currículo encaminado a la formación integral de profesionales como gestores de cambio y transformación en los diferentes contextos sociales. | E43: • Ley 30 de 1992 y decretos asociados • Ley 1740 del 2014 • Decreto único 1075 circular # 31 MEN • Decreto 1330 de 2019 del MEN • Acuerdo 02 del CESU • Ley de emprendimiento | F43: 4.4 • 5.1.2 • 6.1 • 7.1.1 • 7.1.2 • 7.1.3 • 7.1.4 • 7.1.5 • 7.1.6 • 7.4 • 7.5.1 • 7.5.2 • 7.5.3 • 8.1 • 8.2.1 • 8.2.2 • 8.2.3 • 8.2.4 • 8.3.1 • 8.3.2 • 8.3.3 • 8.3.4 • 8.3.5 • 8.3.6 • 8.5.1 • 8.5.2 • 8.5.3 • 8.5.4 • 8.5.5 • 8.5.6 • 8.6 • 8.7 • 9.1.1 • 9.1.2 • 9.1.3 • 10.2 • 10.3 | G43: • Información veraz, pertinente y oportuna • Servicio de Educación Superior acorde con los lineamientos del MEN. | H43: • Estatuto General • Estatuto Docente • Reglamento Estudiantil • Reglamento Consultorio Jurídico • Reglamento Alternativas de Grado • Reglamento Prácticas Universitarias Psicología • Reglamento Uso del Correo Institucional • Acuerdos de los Consejos Superior y Académico • Manual de Funciones • Resoluciones de Rectoría • Política de Protección de Datos Personales * Política de Educación Virtual y a Distancia | I43: • Tasa técnica (Docentes por estudiante) • Deserción (x Periodo - x Cohorte) • Tasa de Graduación (Graduados por Cohorte) • Estudiantes en Investigación (Semilleros) • # de actualizaciones del PEP • Nivel de cualificación • Cumplimiento de matrículas académicas asociada al calendario académico • Cumplimiento de fechas del Calendario ICFES • Cumplimiento con el Registro de Notas • Entrega oportuna de informes • Cumplimiento de compromisos docentes • Resultados del período T-1 (Evaluación Docente) | J43: • PR-GC-004 "Acciones Correctivas"
A44: =COUNTA(C$3:C44) -> 42 | B44: PRO-11 | C44: PPN - Prog. Psicología | D44: Gestionar las diferentes actividades del currículo encaminado a la formación integral de profesionales como gestores de cambio y transformación en los diferentes contextos sociales. | E44: • Ley 30 de 1992 y decretos asociados • Ley 1740 del 2014 • Decreto único 1075 circular # 31 MEN • Decreto 1330 de 2019 del MEN • Acuerdo 02 del CESU • Ley de emprendimiento | F44: 4.4 • 5.1.2 • 6.1 • 7.1.1 • 7.1.2 • 7.1.3 • 7.1.4 • 7.1.5 • 7.1.6 • 7.4 • 7.5.1 • 7.5.2 • 7.5.3 • 8.1 • 8.2.1 • 8.2.2 • 8.2.3 • 8.2.4 • 8.3.1 • 8.3.2 • 8.3.3 • 8.3.4 • 8.3.5 • 8.3.6 • 8.5.1 • 8.5.2 • 8.5.3 • 8.5.4 • 8.5.5 • 8.5.6 • 8.6 • 8.7 • 9.1.1 • 9.1.2 • 9.1.3 • 10.2 • 10.3 | G44: • Información veraz, pertinente y oportuna • Servicio de Educación Superior acorde con los lineamientos del MEN. | H44: • Estatuto General • Estatuto Docente • Reglamento Estudiantil • Reglamento Consultorio Jurídico • Reglamento Alternativas de Grado • Reglamento Prácticas Universitarias Psicología • Reglamento Uso del Correo Institucional • Acuerdos de los Consejos Superior y Académico • Manual de Funciones • Resoluciones de Rectoría • Política de Protección de Datos Personales * Política de Educación Virtual y a Distancia | I44: • Tasa técnica (Docentes por estudiante) • Deserción (x Periodo - x Cohorte) • Tasa de Graduación (Graduados por Cohorte) • Estudiantes en Investigación (Semilleros) • # de actualizaciones del PEP • Nivel de cualificación • Cumplimiento de matrículas académicas asociada al calendario académico • Cumplimiento de fechas del Calendario ICFES • Cumplimiento con el Registro de Notas • Entrega oportuna de informes • Cumplimiento de compromisos docentes • Resultados del período T-1 (Evaluación Docente) | J44: • PR-GC-004 "Acciones Correctivas"
A45: =COUNTA(C$3:C45) -> 43 | B45: PRO-12 | C45: PPN - Prog. Trabajo Social | D45: Gestionar las diferentes actividades del currículo encaminado a la formación integral de profesionales como gestores de cambio y transformación en los diferentes contextos sociales. | E45: • Ley 30 de 1992 y decretos asociados • Ley 1740 del 2014 • Decreto único 1075 circular # 31 MEN • Decreto 1330 de 2019 del MEN • Acuerdo 02 del CESU • Ley de emprendimiento | F45: 4.4 • 5.1.2 • 6.1 • 7.1.1 • 7.1.2 • 7.1.3 • 7.1.4 • 7.1.5 • 7.1.6 • 7.4 • 7.5.1 • 7.5.2 • 7.5.3 • 8.1 • 8.2.1 • 8.2.2 • 8.2.3 • 8.2.4 • 8.3.1 • 8.3.2 • 8.3.3 • 8.3.4 • 8.3.5 • 8.3.6 • 8.5.1 • 8.5.2 • 8.5.3 • 8.5.4 • 8.5.5 • 8.5.6 • 8.6 • 8.7 • 9.1.1 • 9.1.2 • 9.1.3 • 10.2 • 10.3 | G45: • Información veraz, pertinente y oportuna • Servicio de Educación Superior acorde con los lineamientos del MEN. | H45: • Estatuto General • Estatuto Docente • Reglamento Estudiantil • Reglamento Consultorio Jurídico • Reglamento Alternativas de Grado • Reglamento Prácticas Universitarias Psicología • Reglamento Uso del Correo Institucional • Acuerdos de los Consejos Superior y Académico • Manual de Funciones • Resoluciones de Rectoría • Política de Protección de Datos Personales * Política de Educación Virtual y a Distancia | I45: • Tasa técnica (Docentes por estudiante) • Deserción (x Periodo - x Cohorte) • Tasa de Graduación (Graduados por Cohorte) • Estudiantes en Investigación (Semilleros) • # de actualizaciones del PEP • Nivel de cualificación • Cumplimiento de matrículas académicas asociada al calendario académico • Cumplimiento de fechas del Calendario ICFES • Cumplimiento con el Registro de Notas • Entrega oportuna de informes • Cumplimiento de compromisos docentes • Resultados del período T-1 (Evaluación Docente) | J45: • PR-GC-004 "Acciones Correctivas"
... A52: =COUNTA(C$3:C52) -> 50 | B52: PRO-19 | C52: STQ - Prog. Ingeniería Industrial | D52: Gestionar las diferentes actividades del currículo encaminado a la formación integral de profesionales como gestores de cambio y transformación en los diferentes contextos sociales. | E52: • Ley 30 de 1992 y decretos asociados • Ley 1740 del 2014 • Decreto único 1075 circular # 31 MEN • Decreto 1330 de 2019 del MEN • Acuerdo 02 del CESU • Ley de emprendimiento | F52: 4.4 • 5.1.2 • 6.1 • 7.1.1 • 7.1.2 • 7.1.3 • 7.1.4 • 7.1.5 • 7.1.6 • 7.4 • 7.5.1 • 7.5.2 • 7.5.3 • 8.1 • 8.2.1 • 8.2.2 • 8.2.3 • 8.2.4 • 8.3.1 • 8.3.2 • 8.3.3 • 8.3.4 • 8.3.5 • 8.3.6 • 8.5.1 • 8.5.2 • 8.5.3 • 8.5.4 • 8.5.5 • 8.5.6 • 8.6 • 8.7 • 9.1.1 • 9.1.2 • 9.1.3 • 10.2 • 10.3 | G52: • Información veraz, pertinente y oportuna • Servicio de Educación Superior acorde con los lineamientos del MEN. | H52: • Estatuto General • Estatuto Docente • Reglamento Estudiantil • Reglamento Consultorio Jurídico • Reglamento Alternativas de Grado • Reglamento Prácticas Universitarias Psicología • Reglamento Uso del Correo Institucional • Acuerdos de los Consejos Superior y Académico • Manual de Funciones • Resoluciones de Rectoría • Política de Protección de Datos Personales * Política de Educación Virtual y a Distancia | I52: • Tasa técnica (Docentes por estudiante) • Deserción (x Periodo - x Cohorte) • Tasa de Graduación (Graduados por Cohorte) • Estudiantes en Investigación (Semilleros) • # de actualizaciones del PEP • Nivel de cualificación • Cumplimiento de matrículas académicas asociada al calendario académico • Cumplimiento de fechas del Calendario ICFES • Cumplimiento con el Registro de Notas • Entrega oportuna de informes • Cumplimiento de compromisos docentes • Resultados del período T-1 (Evaluación Docente) | J52: • PR-GC-004 "Acciones Correctivas"

Sheet Resumen NC
C1: Relación de No Conformidadades Identificadas | L1: Fecha AI | M1: =CONCATENATE(DAY('FO-GC-015'!AJ14),"/",MONTH('FO-GC-015'!AJ14),"/",YEAR('FO-GC-015'!AJ14)) -> 0/1/1900
C2: Total NC: | E2: =COUNTIF('FO-GC-015'!Y:Y,"X") -> 0 | L2: Ciclo | M2: ='FO-GC-015'!C12 -> 0
B3: ID | C3: No. | D3: Req. ISO 9001 | E3: Sugerencia Redacción No Conformidad | F3: Descripción del Hallazgo | G3: Verificación Realizada | H3: Evidencia Encontrada | I3: Referencia Normativa / Documento | L3: Proceso / Programa | M3: ='FO-GC-015'!U11 -> 0
D4: ='FO-GC-015'!AA1 -> 27 | F4: ='FO-GC-015'!AC1 -> 29 | G4: ='FO-GC-015'!F1 -> 6 | H4: ='FO-GC-015'!P1 -> 16 | I4: ='FO-GC-015'!C1 -> 3
B5: 1 | C5: =IF(B5<=$E$2,CONCATENATE("NC-",B5),"") | D5: =IFERROR(VLOOKUP($C5,'FO-GC-015'!$A:$AL,D$4,0),"") | E5: =IF(C5="","",CONCATENATE($N$6,$M$2,$N$7,$M$1," al ",$N$8,$M$3,$N$9,G5,$N$10,"""",H5,""",",$N$11,I5,$N$12,F5,$N$13,D5,$N$14)) | F5: =IFERROR(VLOOKUP($C5,'FO-GC-015'!$A:$AL,F$4,0),"") | G5: =IFERROR(VLOOKUP($C5,'FO-GC-015'!$A:$AL,G$4,0),"") | H5: =IFERROR(VLOOKUP($C5,'FO-GC-015'!$A:$AL,H$4,0),"") | I5: =IFERROR(VLOOKUP($C5,'FO-GC-015'!$A:$AL,I$4,0),"") | L5: Personalización Hallazgo
B6: =B5+1 -> 2 | C6: =IF(B6<=$E$2,CONCATENATE("NC-",B6),"") | D6: =IFERROR(VLOOKUP($C6,'FO-GC-015'!$A:$AL,D$4,0),"") | E6: =IF(C6="","",CONCATENATE($N$6,$M$2,$N$7,$M$1," al ",$N$8,$M$3,$N$9,G6,$N$10,"""",H6,""",",$N$11,I6,$N$12,F6,$N$13,D6,$N$14)) | F6: =IFERROR(VLOOKUP($C6,'FO-GC-015'!$A:$AL,F$4,0),"") | G6: =IFERROR(VLOOKUP($C6,'FO-GC-015'!$A:$AL,G$4,0),"") | H6: =IFERROR(VLOOKUP($C6,'FO-GC-015'!$A:$AL,H$4,0),"") | I6: =IFERROR(VLOOKUP($C6,'FO-GC-015'!$A:$AL,I$4,0),"") | L6: Contexto | M6: Incio | N6: En auditoría interna correspondiente al ciclo
B7: =B6+1 -> 3 | C7: =IF(B7<=$E$2,CONCATENATE("NC-",B7),"") | D7: =IFERROR(VLOOKUP($C7,'FO-GC-015'!$A:$AL,D$4,0),"") | E7: =IF(C7="","",CONCATENATE($N$6,$M$2,$N$7,$M$1," al ",$N$8,$M$3,$N$9,G7,$N$10,"""",H7,""",",$N$11,I7,$N$12,F7,$N$13,D7,$N$14)) | F7: =IFERROR(VLOOKUP($C7,'FO-GC-015'!$A:$AL,F$4,0),"") | G7: =IFERROR(VLOOKUP($C7,'FO-GC-015'!$A:$AL,G$4,0),"") | H7: =IFERROR(VLOOKUP($C7,'FO-GC-015'!$A:$AL,H$4,0),"") | I7: =IFERROR(VLOOKUP($C7,'FO-GC-015'!$A:$AL,I$4,0),"") | M7: Ejecución | N7: , realizada el dia
B8: =B7+1 -> 4 | C8: =IF(B8<=$E$2,CONCATENATE("NC-",B8),"") | D8: =IFERROR(VLOOKUP($C8,'FO-GC-015'!$A:$AL,D$4,0),"") | E8: =IF(C8="","",CONCATENATE($N$6,$M$2,$N$7,$M$1," al ",$N$8,$M$3,$N$9,G8,$N$10,"""",H8,""",",$N$11,I8,$N$12,F8,$N$13,D8,$N$14)) | F8: =IFERROR(VLOOKUP($C8,'FO-GC-015'!$A:$AL,F$4,0),"") | G8: =IFERROR(VLOOKUP($C8,'FO-GC-015'!$A:$AL,G$4,0),"") | H8: =IFERROR(VLOOKUP($C8,'FO-GC-015'!$A:$AL,H$4,0),"") | I8: =IFERROR(VLOOKUP($C8,'FO-GC-015'!$A:$AL,I$4,0),"") | M8: Categoría | N8: =CONCATENATE(VLOOKUP(M3,Listas!C:F,4,0)," ") -> #N/A
B9: =B8+1 -> 5 | C9: =IF(B9<=$E$2,CONCATENATE("NC-",B9),"") | D9: =IFERROR(VLOOKUP($C9,'FO-GC-015'!$A:$AL,D$4,0),"") | E9: =IF(C9="","",CONCATENATE($N$6,$M$2,$N$7,$M$1," al ",$N$8,$M$3,$N$9,G9,$N$10,"""",H9,""",",$N$11,I9,$N$12,F9,$N$13,D9,$N$14)) | F9: =IFERROR(VLOOKUP($C9,'FO-GC-015'!$A:$AL,F$4,0),"") | G9: =IFERROR(VLOOKUP($C9,'FO-GC-015'!$A:$AL,G$4,0),"") | H9: =IFERROR(VLOOKUP($C9,'FO-GC-015'!$A:$AL,H$4,0),"") | I9: =IFERROR(VLOOKUP($C9,'FO-GC-015'!$A:$AL,I$4,0),"") | M9: Verificación | N9: , al verificar
B10: =B9+1 -> 6 | C10: =IF(B10<=$E$2,CONCATENATE("NC-",B10),"") | D10: =IFERROR(VLOOKUP($C10,'FO-GC-015'!$A:$AL,D$4,0),"") | E10: =IF(C10="","",CONCATENATE($N$6,$M$2,$N$7,$M$1," al ",$N$8,$M$3,$N$9,G10,$N$10,"""",H10,""",",$N$11,I10,$N$12,F10,$N$13,D10,$N$14)) | F10: =IFERROR(VLOOKUP($C10,'FO-GC-015'!$A:$AL,F$4,0),"") | G10: =IFERROR(VLOOKUP($C10,'FO-GC-015'!$A:$AL,G$4,0),"") | H10: =IFERROR(VLOOKUP($C10,'FO-GC-015'!$A:$AL,H$4,0),"") | I10: =IFERROR(VLOOKUP($C10,'FO-GC-015'!$A:$AL,I$4,0),"") | M10: Evidencia | N10: , se identifica según evidencia observada:
B11: =B10+1 -> 7 | C11: =IF(B11<=$E$2,CONCATENATE("NC-",B11),"") | D11: =IFERROR(VLOOKUP($C11,'FO-GC-015'!$A:$AL,D$4,0),"") | E11: =IF(C11="","",CONCATENATE($N$6,$M$2,$N$7,$M$1," al ",$N$8,$M$3,$N$9,G11,$N$10,"""",H11,""",",$N$11,I11,$N$12,F11,$N$13,D11,$N$14)) | F11: =IFERROR(VLOOKUP($C11,'FO-GC-015'!$A:$AL,F$4,0),"") | G11: =IFERROR(VLOOKUP($C11,'FO-GC-015'!$A:$AL,G$4,0),"") | H11: =IFERROR(VLOOKUP($C11,'FO-GC-015'!$A:$AL,H$4,0),"") | I11: =IFERROR(VLOOKUP($C11,'FO-GC-015'!$A:$AL,I$4,0),"") | L11: Hallazgo | M11: NC 1° Parte | N11: que no se cumple con
B12: =B11+1 -> 8 | C12: =IF(B12<=$E$2,CONCATENATE("NC-",B12),"") | D12: =IFERROR(VLOOKUP($C12,'FO-GC-015'!$A:$AL,D$4,0),"") | E12: =IF(C12="","",CONCATENATE($N$6,$M$2,$N$7,$M$1," al ",$N$8,$M$3,$N$9,G12,$N$10,"""",H12,""",",$N$11,I12,$N$12,F12,$N$13,D12,$N$14)) | F12: =IFERROR(VLOOKUP($C12,'FO-GC-015'!$A:$AL,F$4,0),"") | G12: =IFERROR(VLOOKUP($C12,'FO-GC-015'!$A:$AL,G$4,0),"") | H12: =IFERROR(VLOOKUP($C12,'FO-GC-015'!$A:$AL,H$4,0),"") | I12: =IFERROR(VLOOKUP($C12,'FO-GC-015'!$A:$AL,I$4,0),"") | M12: NC 2° Parte | N12: , dado que
B13: =B12+1 -> 9 | C13: =IF(B13<=$E$2,CONCATENATE("NC-",B13),"") | D13: =IFERROR(VLOOKUP($C13,'FO-GC-015'!$A:$AL,D$4,0),"") | E13: =IF(C13="","",CONCATENATE($N$6,$M$2,$N$7,$M$1," al ",$N$8,$M$3,$N$9,G13,$N$10,"""",H13,""",",$N$11,I13,$N$12,F13,$N$13,D13,$N$14)) | F13: =IFERROR(VLOOKUP($C13,'FO-GC-015'!$A:$AL,F$4,0),"") | G13: =IFERROR(VLOOKUP($C13,'FO-GC-015'!$A:$AL,G$4,0),"") | H13: =IFERROR(VLOOKUP($C13,'FO-GC-015'!$A:$AL,H$4,0),"") | I13: =IFERROR(VLOOKUP($C13,'FO-GC-015'!$A:$AL,I$4,0),"") | M13: Incumplimiento P1 | N13: , incumpliendo el requsito
B14: =B13+1 -> 10 | C14: =IF(B14<=$E$2,CONCATENATE("NC-",B14),"") | D14: =IFERROR(VLOOKUP($C14,'FO-GC-015'!$A:$AL,D$4,0),"") | E14: =IF(C14="","",CONCATENATE($N$6,$M$2,$N$7,$M$1," al ",$N$8,$M$3,$N$9,G14,$N$10,"""",H14,""",",$N$11,I14,$N$12,F14,$N$13,D14,$N$14)) | F14: =IFERROR(VLOOKUP($C14,'FO-GC-015'!$A:$AL,F$4,0),"") | G14: =IFERROR(VLOOKUP($C14,'FO-GC-015'!$A:$AL,G$4,0),"") | H14: =IFERROR(VLOOKUP($C14,'FO-GC-015'!$A:$AL,H$4,0),"") | I14: =IFERROR(VLOOKUP($C14,'FO-GC-015'!$A:$AL,I$4,0),"") | M14: Incumplimiento P2 | N14: de la norma ISO 9001:2015.
B15: =B14+1 -> 11 | C15: =IF(B15<=$E$2,CONCATENATE("NC-",B15),"") | D15: =IFERROR(VLOOKUP($C15,'FO-GC-015'!$A:$AL,D$4,0),"") | E15: =IF(C15="","",CONCATENATE($N$6,$M$2,$N$7,$M$1," al ",$N$8,$M$3,$N$9,G15,$N$10,"""",H15,""",",$N$11,I15,$N$12,F15,$N$13,D15,$N$14)) | F15: =IFERROR(VLOOKUP($C15,'FO-GC-015'!$A:$AL,F$4,0),"") | G15: =IFERROR(VLOOKUP($C15,'FO-GC-015'!$A:$AL,G$4,0),"") | H15: =IFERROR(VLOOKUP($C15,'FO-GC-015'!$A:$AL,H$4,0),"") | I15: =IFERROR(VLOOKUP($C15,'FO-GC-015'!$A:$AL,I$4,0),"")
B16: =B15+1 -> 12 | C16: =IF(B16<=$E$2,CONCATENATE("NC-",B16),"") | D16: =IFERROR(VLOOKUP($C16,'FO-GC-015'!$A:$AL,D$4,0),"") | E16: =IF(C16="","",CONCATENATE($N$6,$M$2,$N$7,$M$1," al ",$N$8,$M$3,$N$9,G16,$N$10,"""",H16,""",",$N$11,I16,$N$12,F16,$N$13,D16,$N$14)) | F16: =IFERROR(VLOOKUP($C16,'FO-GC-015'!$A:$AL,F$4,0),"") | G16: =IFERROR(VLOOKUP($C16,'FO-GC-015'!$A:$AL,G$4,0),"") | H16: =IFERROR(VLOOKUP($C16,'FO-GC-015'!$A:$AL,H$4,0),"") | I16: =IFERROR(VLOOKUP($C16,'FO-GC-015'!$A:$AL,I$4,0),"") | M16: Ejemplo:
B17: =B16+1 -> 13 | C17: =IF(B17<=$E$2,CONCATENATE("NC-",B17),"") | D17: =IFERROR(VLOOKUP($C17,'FO-GC-015'!$A:$AL,D$4,0),"") | E17: =IF(C17="","",CONCATENATE($N$6,$M$2,$N$7,$M$1," al ",$N$8,$M$3,$N$9,G17,$N$10,"""",H17,""",",$N$11,I17,$N$12,F17,$N$13,D17,$N$14)) | F17: =IFERROR(VLOOKUP($C17,'FO-GC-015'!$A:$AL,F$4,0),"") | G17: =IFERROR(VLOOKUP($C17,'FO-GC-015'!$A:$AL,G$4,0),"") | H17: =IFERROR(VLOOKUP($C17,'FO-GC-015'!$A:$AL,H$4,0),"") | I17: =IFERROR(VLOOKUP($C17,'FO-GC-015'!$A:$AL,I$4,0),"") | L17: Datos del Ejemplo | M17: Ciclo | N17: 2022
B18: =B17+1 -> 14 | C18: =IF(B18<=$E$2,CONCATENATE("NC-",B18),"") | D18: =IFERROR(VLOOKUP($C18,'FO-GC-015'!$A:$AL,D$4,0),"") | E18: =IF(C18="","",CONCATENATE($N$6,$M$2,$N$7,$M$1," al ",$N$8,$M$3,$N$9,G18,$N$10,"""",H18,""",",$N$11,I18,$N$12,F18,$N$13,D18,$N$14)) | F18: =IFERROR(VLOOKUP($C18,'FO-GC-015'!$A:$AL,F$4,0),"") | G18: =IFERROR(VLOOKUP($C18,'FO-GC-015'!$A:$AL,G$4,0),"") | H18: =IFERROR(VLOOKUP($C18,'FO-GC-015'!$A:$AL,H$4,0),"") | I18: =IFERROR(VLOOKUP($C18,'FO-GC-015'!$A:$AL,I$4,0),"") | M18: Fecha | N18: xx/xx/xxx
B19: =B18+1 -> 15 | C19: =IF(B19<=$E$2,CONCATENATE("NC-",B19),"") | D19: =IFERROR(VLOOKUP($C19,'FO-GC-015'!$A:$AL,D$4,0),"") | E19: =IF(C19="","",CONCATENATE($N$6,$M$2,$N$7,$M$1," al ",$N$8,$M$3,$N$9,G19,$N$10,"""",H19,""",",$N$11,I19,$N$12,F19,$N$13,D19,$N$14)) | F19: =IFERROR(VLOOKUP($C19,'FO-GC-015'!$A:$AL,F$4,0),"") | G19: =IFERROR(VLOOKUP($C19,'FO-GC-015'!$A:$AL,G$4,0),"") | H19: =IFERROR(VLOOKUP($C19,'FO-GC-015'!$A:$AL,H$4,0),"") | I19: =IFERROR(VLOOKUP($C19,'FO-GC-015'!$A:$AL,I$4,0),"") | M19: Proceso | N19: Sistemas
B20: =B19+1 -> 16 | C20: =IF(B20<=$E$2,CONCATENATE("NC-",B20),"") | D20: =IFERROR(VLOOKUP($C20,'FO-GC-015'!$A:$AL,D$4,0),"") | E20: =IF(C20="","",CONCATENATE($N$6,$M$2,$N$7,$M$1," al ",$N$8,$M$3,$N$9,G20,$N$10,"""",H20,""",",$N$11,I20,$N$12,F20,$N$13,D20,$N$14)) | F20: =IFERROR(VLOOKUP($C20,'FO-GC-015'!$A:$AL,F$4,0),"") | G20: =IFERROR(VLOOKUP($C20,'FO-GC-015'!$A:$AL,G$4,0),"") | H20: =IFERROR(VLOOKUP($C20,'FO-GC-015'!$A:$AL,H$4,0),"") | I20: =IFERROR(VLOOKUP($C20,'FO-GC-015'!$A:$AL,I$4,0),"") | M20: Verificación Realizada | N20: ¿Se cuenta con el acta de seguimeinto?
B21: =B20+1 -> 17 | C21: =IF(B21<=$E$2,CONCATENATE("NC-",B21),"") | D21: =IFERROR(VLOOKUP($C21,'FO-GC-015'!$A:$AL,D$4,0),"") | E21: =IF(C21="","",CONCATENATE($N$6,$M$2,$N$7,$M$1," al ",$N$8,$M$3,$N$9,G21,$N$10,"""",H21,""",",$N$11,I21,$N$12,F21,$N$13,D21,$N$14)) | F21: =IFERROR(VLOOKUP($C21,'FO-GC-015'!$A:$AL,F$4,0),"") | G21: =IFERROR(VLOOKUP($C21,'FO-GC-015'!$A:$AL,G$4,0),"") | H21: =IFERROR(VLOOKUP($C21,'FO-GC-015'!$A:$AL,H$4,0),"") | I21: =IFERROR(VLOOKUP($C21,'FO-GC-015'!$A:$AL,I$4,0),"") | M21: Evidencia Encontrada | N21: acta de Comité de xx/xx/xxxx
B22: =B21+1 -> 18 | C22: =IF(B22<=$E$2,CONCATENATE("NC-",B22),"") | D22: =IFERROR(VLOOKUP($C22,'FO-GC-015'!$A:$AL,D$4,0),"") | E22: =IF(C22="","",CONCATENATE($N$6,$M$2,$N$7,$M$1," al ",$N$8,$M$3,$N$9,G22,$N$10,"""",H22,""",",$N$11,I22,$N$12,F22,$N$13,D22,$N$14)) | F22: =IFERROR(VLOOKUP($C22,'FO-GC-015'!$A:$AL,F$4,0),"") | G22: =IFERROR(VLOOKUP($C22,'FO-GC-015'!$A:$AL,G$4,0),"") | H22: =IFERROR(VLOOKUP($C22,'FO-GC-015'!$A:$AL,H$4,0),"") | I22: =IFERROR(VLOOKUP($C22,'FO-GC-015'!$A:$AL,I$4,0),"") | M22: Referencia Normativa | N22: Ley 30
B23: =B22+1 -> 19 | C23: =IF(B23<=$E$2,CONCATENATE("NC-",B23),"") | D23: =IFERROR(VLOOKUP($C23,'FO-GC-015'!$A:$AL,D$4,0),"") | E23: =IF(C23="","",CONCATENATE($N$6,$M$2,$N$7,$M$1," al ",$N$8,$M$3,$N$9,G23,$N$10,"""",H23,""",",$N$11,I23,$N$12,F23,$N$13,D23,$N$14)) | F23: =IFERROR(VLOOKUP($C23,'FO-GC-015'!$A:$AL,F$4,0),"") | G23: =IFERROR(VLOOKUP($C23,'FO-GC-015'!$A:$AL,G$4,0),"") | H23: =IFERROR(VLOOKUP($C23,'FO-GC-015'!$A:$AL,H$4,0),"") | I23: =IFERROR(VLOOKUP($C23,'FO-GC-015'!$A:$AL,I$4,0),"") | M23: Descripción Hallazgo | N23: la última acta se registró en el 2020 y en 2021 no hay evidencia
B24: =B23+1 -> 20 | C24: =IF(B24<=$E$2,CONCATENATE("NC-",B24),"") | D24: =IFERROR(VLOOKUP($C24,'FO-GC-015'!$A:$AL,D$4,0),"") | E24: =IF(C24="","",CONCATENATE($N$6,$M$2,$N$7,$M$1," al ",$N$8,$M$3,$N$9,G24,$N$10,"""",H24,""",",$N$11,I24,$N$12,F24,$N$13,D24,$N$14)) | F24: =IFERROR(VLOOKUP($C24,'FO-GC-015'!$A:$AL,F$4,0),"") | G24: =IFERROR(VLOOKUP($C24,'FO-GC-015'!$A:$AL,G$4,0),"") | H24: =IFERROR(VLOOKUP($C24,'FO-GC-015'!$A:$AL,H$4,0),"") | I24: =IFERROR(VLOOKUP($C24,'FO-GC-015'!$A:$AL,I$4,0),"") | M24: Requisito ISO 9001 | N24: 4.1.
B25: =B24+1 -> 21 | C25: =IF(B25<=$E$2,CONCATENATE("NC-",B25),"") | D25: =IFERROR(VLOOKUP($C25,'FO-GC-015'!$A:$AL,D$4,0),"") | E25: =IF(C25="","",CONCATENATE($N$6,$M$2,$N$7,$M$1," al ",$N$8,$M$3,$N$9,G25,$N$10,"""",H25,""",",$N$11,I25,$N$12,F25,$N$13,D25,$N$14)) | F25: =IFERROR(VLOOKUP($C25,'FO-GC-015'!$A:$AL,F$4,0),"") | G25: =IFERROR(VLOOKUP($C25,'FO-GC-015'!$A:$AL,G$4,0),"") | H25: =IFERROR(VLOOKUP($C25,'FO-GC-015'!$A:$AL,H$4,0),"") | I25: =IFERROR(VLOOKUP($C25,'FO-GC-015'!$A:$AL,I$4,0),"")
B26: =B25+1 -> 22 | C26: =IF(B26<=$E$2,CONCATENATE("NC-",B26),"") | D26: =IFERROR(VLOOKUP($C26,'FO-GC-015'!$A:$AL,D$4,0),"") | E26: =IF(C26="","",CONCATENATE($N$6,$M$2,$N$7,$M$1," al ",$N$8,$M$3,$N$9,G26,$N$10,"""",H26,""",",$N$11,I26,$N$12,F26,$N$13,D26,$N$14)) | F26: =IFERROR(VLOOKUP($C26,'FO-GC-015'!$A:$AL,F$4,0),"") | G26: =IFERROR(VLOOKUP($C26,'FO-GC-015'!$A:$AL,G$4,0),"") | H26: =IFERROR(VLOOKUP($C26,'FO-GC-015'!$A:$AL,H$4,0),"") | I26: =IFERROR(VLOOKUP($C26,'FO-GC-015'!$A:$AL,I$4,0),"") | L26: Redacción sugerida para el ejemplo:
B27: =B26+1 -> 23 | C27: =IF(B27<=$E$2,CONCATENATE("NC-",B27),"") | D27: =IFERROR(VLOOKUP($C27,'FO-GC-015'!$A:$AL,D$4,0),"") | E27: =IF(C27="","",CONCATENATE($N$6,$M$2,$N$7,$M$1," al ",$N$8,$M$3,$N$9,G27,$N$10,"""",H27,""",",$N$11,I27,$N$12,F27,$N$13,D27,$N$14)) | F27: =IFERROR(VLOOKUP($C27,'FO-GC-015'!$A:$AL,F$4,0),"") | G27: =IFERROR(VLOOKUP($C27,'FO-GC-015'!$A:$AL,G$4,0),"") | H27: =IFERROR(VLOOKUP($C27,'FO-GC-015'!$A:$AL,H$4,0),"") | I27: =IFERROR(VLOOKUP($C27,'FO-GC-015'!$A:$AL,I$4,0),"") | L27: =CONCATENATE(N6,N17,N7,N18," al ",N8,N19,N9,N20,N10,"""",N21,""",",N11,N22,N12,N23,N13,N24,N14) -> #N/A
B28: =B27+1 -> 24 | C28: =IF(B28<=$E$2,CONCATENATE("NC-",B28),"") | D28: =IFERROR(VLOOKUP($C28,'FO-GC-015'!$A:$AL,D$4,0),"") | E28: =IF(C28="","",CONCATENATE($N$6,$M$2,$N$7,$M$1," al ",$N$8,$M$3,$N$9,G28,$N$10,"""",H28,""",",$N$11,I28,$N$12,F28,$N$13,D28,$N$14)) | F28: =IFERROR(VLOOKUP($C28,'FO-GC-015'!$A:$AL,F$4,0),"") | G28: =IFERROR(VLOOKUP($C28,'FO-GC-015'!$A:$AL,G$4,0),"") | H28: =IFERROR(VLOOKUP($C28,'FO-GC-015'!$A:$AL,H$4,0),"") | I28: =IFERROR(VLOOKUP($C28,'FO-GC-015'!$A:$AL,I$4,0),"")
B29: =B28+1 -> 25 | C29: =IF(B29<=$E$2,CONCATENATE("NC-",B29),"") | D29: =IFERROR(VLOOKUP($C29,'FO-GC-015'!$A:$AL,D$4,0),"") | E29: =IF(C29="","",CONCATENATE($N$6,$M$2,$N$7,$M$1," al ",$N$8,$M$3,$N$9,G29,$N$10,"""",H29,""",",$N$11,I29,$N$12,F29,$N$13,D29,$N$14)) | F29: =IFERROR(VLOOKUP($C29,'FO-GC-015'!$A:$AL,F$4,0),"") | G29: =IFERROR(VLOOKUP($C29,'FO-GC-015'!$A:$AL,G$4,0),"") | H29: =IFERROR(VLOOKUP($C29,'FO-GC-015'!$A:$AL,H$4,0),"") | I29: =IFERROR(VLOOKUP($C29,'FO-GC-015'!$A:$AL,I$4,0),"")
B30: =B29+1 -> 26 | C30: =IF(B30<=$E$2,CONCATENATE("NC-",B30),"") | D30: =IFERROR(VLOOKUP($C30,'FO-GC-015'!$A:$AL,D$4,0),"") | E30: =IF(C30="","",CONCATENATE($N$6,$M$2,$N$7,$M$1," al ",$N$8,$M$3,$N$9,G30,$N$10,"""",H30,""",",$N$11,I30,$N$12,F30,$N$13,D30,$N$14)) | F30: =IFERROR(VLOOKUP($C30,'FO-GC-015'!$A:$AL,F$4,0),"") | G30: =IFERROR(VLOOKUP($C30,'FO-GC-015'!$A:$AL,G$4,0),"") | H30: =IFERROR(VLOOKUP($C30,'FO-GC-015'!$A:$AL,H$4,0),"") | I30: =IFERROR(VLOOKUP($C30,'FO-GC-015'!$A:$AL,I$4,0),"")
B31: =B30+1 -> 27 | C31: =IF(B31<=$E$2,CONCATENATE("NC-",B31),"") | D31: =IFERROR(VLOOKUP($C31,'FO-GC-015'!$A:$AL,D$4,0),"") | E31: =IF(C31="","",CONCATENATE($N$6,$M$2,$N$7,$M$1," al ",$N$8,$M$3,$N$9,G31,$N$10,"""",H31,""",",$N$11,I31,$N$12,F31,$N$13,D31,$N$14)) | F31: =IFERROR(VLOOKUP($C31,'FO-GC-015'!$A:$AL,F$4,0),"") | G31: =IFERROR(VLOOKUP($C31,'FO-GC-015'!$A:$AL,G$4,0),"") | H31: =IFERROR(VLOOKUP($C31,'FO-GC-015'!$A:$AL,H$4,0),"") | I31: =IFERROR(VLOOKUP($C31,'FO-GC-015'!$A:$AL,I$4,0),"")
B32: =B31+1 -> 28 | C32: =IF(B32<=$E$2,CONCATENATE("NC-",B32),"") | D32: =IFERROR(VLOOKUP($C32,'FO-GC-015'!$A:$AL,D$4,0),"") | E32: =IF(C32="","",CONCATENATE($N$6,$M$2,$N$7,$M$1," al ",$N$8,$M$3,$N$9,G32,$N$10,"""",H32,""",",$N$11,I32,$N$12,F32,$N$13,D32,$N$14)) | F32: =IFERROR(VLOOKUP($C32,'FO-GC-015'!$A:$AL,F$4,0),"") | G32: =IFERROR(VLOOKUP($C32,'FO-GC-015'!$A:$AL,G$4,0),"") | H32: =IFERROR(VLOOKUP($C32,'FO-GC-015'!$A:$AL,H$4,0),"") | I32: =IFERROR(VLOOKUP($C32,'FO-GC-015'!$A:$AL,I$4,0),"")
B33: =B32+1 -> 29 | C33: =IF(B33<=$E$2,CONCATENATE("NC-",B33),"") | D33: =IFERROR(VLOOKUP($C33,'FO-GC-015'!$A:$AL,D$4,0),"") | E33: =IF(C33="","",CONCATENATE($N$6,$M$2,$N$7,$M$1," al ",$N$8,$M$3,$N$9,G33,$N$10,"""",H33,""",",$N$11,I33,$N$12,F33,$N$13,D33,$N$14)) | F33: =IFERROR(VLOOKUP($C33,'FO-GC-015'!$A:$AL,F$4,0),"") | G33: =IFERROR(VLOOKUP($C33,'FO-GC-015'!$A:$AL,G$4,0),"") | H33: =IFERROR(VLOOKUP($C33,'FO-GC-015'!$A:$AL,H$4,0),"") | I33: =IFERROR(VLOOKUP($C33,'FO-GC-015'!$A:$AL,I$4,0),"")
B34: =B33+1 -> 30 | C34: =IF(B34<=$E$2,CONCATENATE("NC-",B34),"") | D34: =IFERROR(VLOOKUP($C34,'FO-GC-015'!$A:$AL,D$4,0),"") | E34: =IF(C34="","",CONCATENATE($N$6,$M$2,$N$7,$M$1," al ",$N$8,$M$3,$N$9,G34,$N$10,"""",H34,""",",$N$11,I34,$N$12,F34,$N$13,D34,$N$14)) | F34: =IFERROR(VLOOKUP($C34,'FO-GC-015'!$A:$AL,F$4,0),"") | G34: =IFERROR(VLOOKUP($C34,'FO-GC-015'!$A:$AL,G$4,0),"") | H34: =IFERROR(VLOOKUP($C34,'FO-GC-015'!$A:$AL,H$4,0),"") | I34: =IFERROR(VLOOKUP($C34,'FO-GC-015'!$A:$AL,I$4,0),"")
B35: =B34+1 -> 31 | C35: =IF(B35<=$E$2,CONCATENATE("NC-",B35),"") | D35: =IFERROR(VLOOKUP($C35,'FO-GC-015'!$A:$AL,D$4,0),"") | E35: =IF(C35="","",CONCATENATE($N$6,$M$2,$N$7,$M$1," al ",$N$8,$M$3,$N$9,G35,$N$10,"""",H35,""",",$N$11,I35,$N$12,F35,$N$13,D35,$N$14)) | F35: =IFERROR(VLOOKUP($C35,'FO-GC-015'!$A:$AL,F$4,0),"") | G35: =IFERROR(VLOOKUP($C35,'FO-GC-015'!$A:$AL,G$4,0),"") | H35: =IFERROR(VLOOKUP($C35,'FO-GC-015'!$A:$AL,H$4,0),"") | I35: =IFERROR(VLOOKUP($C35,'FO-GC-015'!$A:$AL,I$4,0),"")
B36: =B35+1 -> 32 | C36: =IF(B36<=$E$2,CONCATENATE("NC-",B36),"") | D36: =IFERROR(VLOOKUP($C36,'FO-GC-015'!$A:$AL,D$4,0),"") | E36: =IF(C36="","",CONCATENATE($N$6,$M$2,$N$7,$M$1," al ",$N$8,$M$3,$N$9,G36,$N$10,"""",H36,""",",$N$11,I36,$N$12,F36,$N$13,D36,$N$14)) | F36: =IFERROR(VLOOKUP($C36,'FO-GC-015'!$A:$AL,F$4,0),"") | G36: =IFERROR(VLOOKUP($C36,'FO-GC-015'!$A:$AL,G$4,0),"") | H36: =IFERROR(VLOOKUP($C36,'FO-GC-015'!$A:$AL,H$4,0),"") | I36: =IFERROR(VLOOKUP($C36,'FO-GC-015'!$A:$AL,I$4,0),"")
B37: =B36+1 -> 33 | C37: =IF(B37<=$E$2,CONCATENATE("NC-",B37),"") | D37: =IFERROR(VLOOKUP($C37,'FO-GC-015'!$A:$AL,D$4,0),"") | E37: =IF(C37="","",CONCATENATE($N$6,$M$2,$N$7,$M$1," al ",$N$8,$M$3,$N$9,G37,$N$10,"""",H37,""",",$N$11,I37,$N$12,F37,$N$13,D37,$N$14)) | F37: =IFERROR(VLOOKUP($C37,'FO-GC-015'!$A:$AL,F$4,0),"") | G37: =IFERROR(VLOOKUP($C37,'FO-GC-015'!$A:$AL,G$4,0),"") | H37: =IFERROR(VLOOKUP($C37,'FO-GC-015'!$A:$AL,H$4,0),"") | I37: =IFERROR(VLOOKUP($C37,'FO-GC-015'!$A:$AL,I$4,0),"")
B38: =B37+1 -> 34 | C38: =IF(B38<=$E$2,CONCATENATE("NC-",B38),"") | D38: =IFERROR(VLOOKUP($C38,'FO-GC-015'!$A:$AL,D$4,0),"") | E38: =IF(C38="","",CONCATENATE($N$6,$M$2,$N$7,$M$1," al ",$N$8,$M$3,$N$9,G38,$N$10,"""",H38,""",",$N$11,I38,$N$12,F38,$N$13,D38,$N$14)) | F38: =IFERROR(VLOOKUP($C38,'FO-GC-015'!$A:$AL,F$4,0),"") | G38: =IFERROR(VLOOKUP($C38,'FO-GC-015'!$A:$AL,G$4,0),"") | H38: =IFERROR(VLOOKUP($C38,'FO-GC-015'!$A:$AL,H$4,0),"") | I38: =IFERROR(VLOOKUP($C38,'FO-GC-015'!$A:$AL,I$4,0),"")

Sheet Resumen Obs
C1: Relación de Observaciones Identificadas | L1: Fecha AI | M1: =CONCATENATE(DAY('FO-GC-015'!AJ14),"/",MONTH('FO-GC-015'!AJ14),"/",YEAR('FO-GC-015'!AJ14)) -> 0/1/1900
C2: Total NC: | E2: =COUNTIF('FO-GC-015'!Z:Z,"X") -> 0 | L2: Ciclo | M2: ='FO-GC-015'!C12 -> 0
B3: ID | C3: No. | D3: Req. ISO 9001 | E3: Sugerencia Redacción Observación | F3: Descripción del Hallazgo | G3: Verificación Realizada | H3: Evidencia Encontrada | I3: Referencia Normativa / Documento | L3: Proceso / Programa | M3: ='FO-GC-015'!U11 -> 0
D4: ='FO-GC-015'!AA1 -> 27 | F4: ='FO-GC-015'!AC1 -> 29 | G4: ='FO-GC-015'!F1 -> 6 | H4: ='FO-GC-015'!P1 -> 16 | I4: ='FO-GC-015'!C1 -> 3
B5: 1 | C5: =IF(B5<=$E$2,CONCATENATE("Obs-",B5),"") | D5: =IFERROR(VLOOKUP($C5,'FO-GC-015'!$A:$AL,D$4,0),"") | E5: =IF(C5="","",CONCATENATE($N$6,$M$2,$N$7,$M$1," al ",$N$8,$M$3,$N$9,G5,$N$10,"""",H5,""",",$N$11,I5,$N$12,F5,$N$13,D5,$N$14)) | F5: =IFERROR(VLOOKUP($C5,'FO-GC-015'!$A:$AL,F$4,0),"") | G5: =IFERROR(VLOOKUP($C5,'FO-GC-015'!$A:$AL,G$4,0),"") | H5: =IFERROR(VLOOKUP($C5,'FO-GC-015'!$A:$AL,H$4,0),"") | I5: =IFERROR(VLOOKUP($C5,'FO-GC-015'!$A:$AL,I$4,0),"") | L5: Personalización Hallazgo
B6: =B5+1 -> 2 | C6: =IF(B6<=$E$2,CONCATENATE("Obs-",B6),"") | D6: =IFERROR(VLOOKUP($C6,'FO-GC-015'!$A:$AL,D$4,0),"") | E6: =IF(C6="","",CONCATENATE($N$6,$M$2,$N$7,$M$1," al ",$N$8,$M$3,$N$9,G6,$N$10,"""",H6,""",",$N$11,I6,$N$12,F6,$N$13,D6,$N$14)) | F6: =IFERROR(VLOOKUP($C6,'FO-GC-015'!$A:$AL,F$4,0),"") | G6: =IFERROR(VLOOKUP($C6,'FO-GC-015'!$A:$AL,G$4,0),"") | H6: =IFERROR(VLOOKUP($C6,'FO-GC-015'!$A:$AL,H$4,0),"") | I6: =IFERROR(VLOOKUP($C6,'FO-GC-015'!$A:$AL,I$4,0),"") | L6: Contexto | M6: Incio | N6: En auditoría interna correspondiente al ciclo
B7: =B6+1 -> 3 | C7: =IF(B7<=$E$2,CONCATENATE("Obs-",B7),"") | D7: =IFERROR(VLOOKUP($C7,'FO-GC-015'!$A:$AL,D$4,0),"") | E7: =IF(C7="","",CONCATENATE($N$6,$M$2,$N$7,$M$1," al ",$N$8,$M$3,$N$9,G7,$N$10,"""",H7,""",",$N$11,I7,$N$12,F7,$N$13,D7,$N$14)) | F7: =IFERROR(VLOOKUP($C7,'FO-GC-015'!$A:$AL,F$4,0),"") | G7: =IFERROR(VLOOKUP($C7,'FO-GC-015'!$A:$AL,G$4,0),"") | H7: =IFERROR(VLOOKUP($C7,'FO-GC-015'!$A:$AL,H$4,0),"") | I7: =IFERROR(VLOOKUP($C7,'FO-GC-015'!$A:$AL,I$4,0),"") | M7: Ejecución | N7: , realizada el dia
B8: =B7+1 -> 4 | C8: =IF(B8<=$E$2,CONCATENATE("Obs-",B8),"") | D8: =IFERROR(VLOOKUP($C8,'FO-GC-015'!$A:$AL,D$4,0),"") | E8: =IF(C8="","",CONCATENATE($N$6,$M$2,$N$7,$M$1," al ",$N$8,$M$3,$N$9,G8,$N$10,"""",H8,""",",$N$11,I8,$N$12,F8,$N$13,D8,$N$14)) | F8: =IFERROR(VLOOKUP($C8,'FO-GC-015'!$A:$AL,F$4,0),"") | G8: =IFERROR(VLOOKUP($C8,'FO-GC-015'!$A:$AL,G$4,0),"") | H8: =IFERROR(VLOOKUP($C8,'FO-GC-015'!$A:$AL,H$4,0),"") | I8: =IFERROR(VLOOKUP($C8,'FO-GC-015'!$A:$AL,I$4,0),"") | M8: Categoría | N8: =CONCATENATE(VLOOKUP(M3,Listas!C:F,4,0)," ") -> #N/A
B9: =B8+1 -> 5 | C9: =IF(B9<=$E$2,CONCATENATE("Obs-",B9),"") | D9: =IFERROR(VLOOKUP($C9,'FO-GC-015'!$A:$AL,D$4,0),"") | E9: =IF(C9="","",CONCATENATE($N$6,$M$2,$N$7,$M$1," al ",$N$8,$M$3,$N$9,G9,$N$10,"""",H9,""",",$N$11,I9,$N$12,F9,$N$13,D9,$N$14)) | F9: =IFERROR(VLOOKUP($C9,'FO-GC-015'!$A:$AL,F$4,0),"") | G9: =IFERROR(VLOOKUP($C9,'FO-GC-015'!$A:$AL,G$4,0),"") | H9: =IFERROR(VLOOKUP($C9,'FO-GC-015'!$A:$AL,H$4,0),"") | I9: =IFERROR(VLOOKUP($C9,'FO-GC-015'!$A:$AL,I$4,0),"") | M9: Verificación | N9: , al verificar
B10: =B9+1 -> 6 | C10: =IF(B10<=$E$2,CONCATENATE("Obs-",B10),"") | D10: =IFERROR(VLOOKUP($C10,'FO-GC-015'!$A:$AL,D$4,0),"") | E10: =IF(C10="","",CONCATENATE($N$6,$M$2,$N$7,$M$1," al ",$N$8,$M$3,$N$9,G10,$N$10,"""",H10,""",",$N$11,I10,$N$12,F10,$N$13,D10,$N$14)) | F10: =IFERROR(VLOOKUP($C10,'FO-GC-015'!$A:$AL,F$4,0),"") | G10: =IFERROR(VLOOKUP($C10,'FO-GC-015'!$A:$AL,G$4,0),"") | H10: =IFERROR(VLOOKUP($C10,'FO-GC-015'!$A:$AL,H$4,0),"") | I10: =IFERROR(VLOOKUP($C10,'FO-GC-015'!$A:$AL,I$4,0),"") | M10: Evidencia | N10: , se identifica según evidencia observada:
B11: =B10+1 -> 7 | C11: =IF(B11<=$E$2,CONCATENATE("Obs-",B11),"") | D11: =IFERROR(VLOOKUP($C11,'FO-GC-015'!$A:$AL,D$4,0),"") | E11: =IF(C11="","",CONCATENATE($N$6,$M$2,$N$7,$M$1," al ",$N$8,$M$3,$N$9,G11,$N$10,"""",H11,""",",$N$11,I11,$N$12,F11,$N$13,D11,$N$14)) | F11: =IFERROR(VLOOKUP($C11,'FO-GC-015'!$A:$AL,F$4,0),"") | G11: =IFERROR(VLOOKUP($C11,'FO-GC-015'!$A:$AL,G$4,0),"") | H11: =IFERROR(VLOOKUP($C11,'FO-GC-015'!$A:$AL,H$4,0),"") | I11: =IFERROR(VLOOKUP($C11,'FO-GC-015'!$A:$AL,I$4,0),"") | L11: Hallazgo | M11: NC 1° Parte | N11: que existe cumplimiento parcial de
B12: =B11+1 -> 8 | C12: =IF(B12<=$E$2,CONCATENATE("Obs-",B12),"") | D12: =IFERROR(VLOOKUP($C12,'FO-GC-015'!$A:$AL,D$4,0),"") | E12: =IF(C12="","",CONCATENATE($N$6,$M$2,$N$7,$M$1," al ",$N$8,$M$3,$N$9,G12,$N$10,"""",H12,""",",$N$11,I12,$N$12,F12,$N$13,D12,$N$14)) | F12: =IFERROR(VLOOKUP($C12,'FO-GC-015'!$A:$AL,F$4,0),"") | G12: =IFERROR(VLOOKUP($C12,'FO-GC-015'!$A:$AL,G$4,0),"") | H12: =IFERROR(VLOOKUP($C12,'FO-GC-015'!$A:$AL,H$4,0),"") | I12: =IFERROR(VLOOKUP($C12,'FO-GC-015'!$A:$AL,I$4,0),"") | M12: NC 2° Parte | N12: , dado que
B13: =B12+1 -> 9 | C13: =IF(B13<=$E$2,CONCATENATE("Obs-",B13),"") | D13: =IFERROR(VLOOKUP($C13,'FO-GC-015'!$A:$AL,D$4,0),"") | E13: =IF(C13="","",CONCATENATE($N$6,$M$2,$N$7,$M$1," al ",$N$8,$M$3,$N$9,G13,$N$10,"""",H13,""",",$N$11,I13,$N$12,F13,$N$13,D13,$N$14)) | F13: =IFERROR(VLOOKUP($C13,'FO-GC-015'!$A:$AL,F$4,0),"") | G13: =IFERROR(VLOOKUP($C13,'FO-GC-015'!$A:$AL,G$4,0),"") | H13: =IFERROR(VLOOKUP($C13,'FO-GC-015'!$A:$AL,H$4,0),"") | I13: =IFERROR(VLOOKUP($C13,'FO-GC-015'!$A:$AL,I$4,0),"") | M13: Incumplimiento P1 | N13: , lo cual podría conllevar al incumplimiento del requsito
B14: =B13+1 -> 10 | C14: =IF(B14<=$E$2,CONCATENATE("Obs-",B14),"") | D14: =IFERROR(VLOOKUP($C14,'FO-GC-015'!$A:$AL,D$4,0),"") | E14: =IF(C14="","",CONCATENATE($N$6,$M$2,$N$7,$M$1," al ",$N$8,$M$3,$N$9,G14,$N$10,"""",H14,""",",$N$11,I14,$N$12,F14,$N$13,D14,$N$14)) | F14: =IFERROR(VLOOKUP($C14,'FO-GC-015'!$A:$AL,F$4,0),"") | G14: =IFERROR(VLOOKUP($C14,'FO-GC-015'!$A:$AL,G$4,0),"") | H14: =IFERROR(VLOOKUP($C14,'FO-GC-015'!$A:$AL,H$4,0),"") | I14: =IFERROR(VLOOKUP($C14,'FO-GC-015'!$A:$AL,I$4,0),"") | M14: Incumplimiento P2 | N14: de la norma ISO 9001:2015.
B15: =B14+1 -> 11 | C15: =IF(B15<=$E$2,CONCATENATE("Obs-",B15),"") | D15: =IFERROR(VLOOKUP($C15,'FO-GC-015'!$A:$AL,D$4,0),"") | E15: =IF(C15="","",CONCATENATE($N$6,$M$2,$N$7,$M$1," al ",$N$8,$M$3,$N$9,G15,$N$10,"""",H15,""",",$N$11,I15,$N$12,F15,$N$13,D15,$N$14)) | F15: =IFERROR(VLOOKUP($C15,'FO-GC-015'!$A:$AL,F$4,0),"") | G15: =IFERROR(VLOOKUP($C15,'FO-GC-015'!$A:$AL,G$4,0),"") | H15: =IFERROR(VLOOKUP($C15,'FO-GC-015'!$A:$AL,H$4,0),"") | I15: =IFERROR(VLOOKUP($C15,'FO-GC-015'!$A:$AL,I$4,0),"")
B16: =B15+1 -> 12 | C16: =IF(B16<=$E$2,CONCATENATE("Obs-",B16),"") | D16: =IFERROR(VLOOKUP($C16,'FO-GC-015'!$A:$AL,D$4,0),"") | E16: =IF(C16="","",CONCATENATE($N$6,$M$2,$N$7,$M$1," al ",$N$8,$M$3,$N$9,G16,$N$10,"""",H16,""",",$N$11,I16,$N$12,F16,$N$13,D16,$N$14)) | F16: =IFERROR(VLOOKUP($C16,'FO-GC-015'!$A:$AL,F$4,0),"") | G16: =IFERROR(VLOOKUP($C16,'FO-GC-015'!$A:$AL,G$4,0),"") | H16: =IFERROR(VLOOKUP($C16,'FO-GC-015'!$A:$AL,H$4,0),"") | I16: =IFERROR(VLOOKUP($C16,'FO-GC-015'!$A:$AL,I$4,0),"") | M16: Ejemplo:
B17: =B16+1 -> 13 | C17: =IF(B17<=$E$2,CONCATENATE("Obs-",B17),"") | D17: =IFERROR(VLOOKUP($C17,'FO-GC-015'!$A:$AL,D$4,0),"") | E17: =IF(C17="","",CONCATENATE($N$6,$M$2,$N$7,$M$1," al ",$N$8,$M$3,$N$9,G17,$N$10,"""",H17,""",",$N$11,I17,$N$12,F17,$N$13,D17,$N$14)) | F17: =IFERROR(VLOOKUP($C17,'FO-GC-015'!$A:$AL,F$4,0),"") | G17: =IFERROR(VLOOKUP($C17,'FO-GC-015'!$A:$AL,G$4,0),"") | H17: =IFERROR(VLOOKUP($C17,'FO-GC-015'!$A:$AL,H$4,0),"") | I17: =IFERROR(VLOOKUP($C17,'FO-GC-015'!$A:$AL,I$4,0),"") | L17: Datos del Ejemplo | M17: Ciclo | N17: 2022
B18: =B17+1 -> 14 | C18: =IF(B18<=$E$2,CONCATENATE("Obs-",B18),"") | D18: =IFERROR(VLOOKUP($C18,'FO-GC-015'!$A:$AL,D$4,0),"") | E18: =IF(C18="","",CONCATENATE($N$6,$M$2,$N$7,$M$1," al ",$N$8,$M$3,$N$9,G18,$N$10,"""",H18,""",",$N$11,I18,$N$12,F18,$N$13,D18,$N$14)) | F18: =IFERROR(VLOOKUP($C18,'FO-GC-015'!$A:$AL,F$4,0),"") | G18: =IFERROR(VLOOKUP($C18,'FO-GC-015'!$A:$AL,G$4,0),"") | H18: =IFERROR(VLOOKUP($C18,'FO-GC-015'!$A:$AL,H$4,0),"") | I18: =IFERROR(VLOOKUP($C18,'FO-GC-015'!$A:$AL,I$4,0),"") | M18: Fecha | N18: xx/xx/xxx
B19: =B18+1 -> 15 | C19: =IF(B19<=$E$2,CONCATENATE("Obs-",B19),"") | D19: =IFERROR(VLOOKUP($C19,'FO-GC-015'!$A:$AL,D$4,0),"") | E19: =IF(C19="","",CONCATENATE($N$6,$M$2,$N$7,$M$1," al ",$N$8,$M$3,$N$9,G19,$N$10,"""",H19,""",",$N$11,I19,$N$12,F19,$N$13,D19,$N$14)) | F19: =IFERROR(VLOOKUP($C19,'FO-GC-015'!$A:$AL,F$4,0),"") | G19: =IFERROR(VLOOKUP($C19,'FO-GC-015'!$A:$AL,G$4,0),"") | H19: =IFERROR(VLOOKUP($C19,'FO-GC-015'!$A:$AL,H$4,0),"") | I19: =IFERROR(VLOOKUP($C19,'FO-GC-015'!$A:$AL,I$4,0),"") | M19: Proceso | N19: Sistemas
B20: =B19+1 -> 16 | C20: =IF(B20<=$E$2,CONCATENATE("Obs-",B20),"") | D20: =IFERROR(VLOOKUP($C20,'FO-GC-015'!$A:$AL,D$4,0),"") | E20: =IF(C20="","",CONCATENATE($N$6,$M$2,$N$7,$M$1," al ",$N$8,$M$3,$N$9,G20,$N$10,"""",H20,""",",$N$11,I20,$N$12,F20,$N$13,D20,$N$14)) | F20: =IFERROR(VLOOKUP($C20,'FO-GC-015'!$A:$AL,F$4,0),"") | G20: =IFERROR(VLOOKUP($C20,'FO-GC-015'!$A:$AL,G$4,0),"") | H20: =IFERROR(VLOOKUP($C20,'FO-GC-015'!$A:$AL,H$4,0),"") | I20: =IFERROR(VLOOKUP($C20,'FO-GC-015'!$A:$AL,I$4,0),"") | M20: Verificación Realizada | N20: ¿Se cuenta con el acta de seguimeinto?
B21: =B20+1 -> 17 | C21: =IF(B21<=$E$2,CONCATENATE("Obs-",B21),"") | D21: =IFERROR(VLOOKUP($C21,'FO-GC-015'!$A:$AL,D$4,0),"") | E21: =IF(C21="","",CONCATENATE($N$6,$M$2,$N$7,$M$1," al ",$N$8,$M$3,$N$9,G21,$N$10,"""",H21,""",",$N$11,I21,$N$12,F21,$N$13,D21,$N$14)) | F21: =IFERROR(VLOOKUP($C21,'FO-GC-015'!$A:$AL,F$4,0),"") | G21: =IFERROR(VLOOKUP($C21,'FO-GC-015'!$A:$AL,G$4,0),"") | H21: =IFERROR(VLOOKUP($C21,'FO-GC-015'!$A:$AL,H$4,0),"") | I21: =IFERROR(VLOOKUP($C21,'FO-GC-015'!$A:$AL,I$4,0),"") | M21: Evidencia Encontrada | N21: acta de Comité de xx/xx/xxxx
B22: =B21+1 -> 18 | C22: =IF(B22<=$E$2,CONCATENATE("Obs-",B22),"") | D22: =IFERROR(VLOOKUP($C22,'FO-GC-015'!$A:$AL,D$4,0),"") | E22: =IF(C22="","",CONCATENATE($N$6,$M$2,$N$7,$M$1," al ",$N$8,$M$3,$N$9,G22,$N$10,"""",H22,""",",$N$11,I22,$N$12,F22,$N$13,D22,$N$14)) | F22: =IFERROR(VLOOKUP($C22,'FO-GC-015'!$A:$AL,F$4,0),"") | G22: =IFERROR(VLOOKUP($C22,'FO-GC-015'!$A:$AL,G$4,0),"") | H22: =IFERROR(VLOOKUP($C22,'FO-GC-015'!$A:$AL,H$4,0),"") | I22: =IFERROR(VLOOKUP($C22,'FO-GC-015'!$A:$AL,I$4,0),"") | M22: Referencia Normativa | N22: Ley 30
B23: =B22+1 -> 19 | C23: =IF(B23<=$E$2,CONCATENATE("Obs-",B23),"") | D23: =IFERROR(VLOOKUP($C23,'FO-GC-015'!$A:$AL,D$4,0),"") | E23: =IF(C23="","",CONCATENATE($N$6,$M$2,$N$7,$M$1," al ",$N$8,$M$3,$N$9,G23,$N$10,"""",H23,""",",$N$11,I23,$N$12,F23,$N$13,D23,$N$14)) | F23: =IFERROR(VLOOKUP($C23,'FO-GC-015'!$A:$AL,F$4,0),"") | G23: =IFERROR(VLOOKUP($C23,'FO-GC-015'!$A:$AL,G$4,0),"") | H23: =IFERROR(VLOOKUP($C23,'FO-GC-015'!$A:$AL,H$4,0),"") | I23: =IFERROR(VLOOKUP($C23,'FO-GC-015'!$A:$AL,I$4,0),"") | M23: Descripción Hallazgo | N23: la última acta se registró en el 2020 y en 2021 no hay evidencia
B24: =B23+1 -> 20 | C24: =IF(B24<=$E$2,CONCATENATE("Obs-",B24),"") | D24: =IFERROR(VLOOKUP($C24,'FO-GC-015'!$A:$AL,D$4,0),"") | E24: =IF(C24="","",CONCATENATE($N$6,$M$2,$N$7,$M$1," al ",$N$8,$M$3,$N$9,G24,$N$10,"""",H24,""",",$N$11,I24,$N$12,F24,$N$13,D24,$N$14)) | F24: =IFERROR(VLOOKUP($C24,'FO-GC-015'!$A:$AL,F$4,0),"") | G24: =IFERROR(VLOOKUP($C24,'FO-GC-015'!$A:$AL,G$4,0),"") | H24: =IFERROR(VLOOKUP($C24,'FO-GC-015'!$A:$AL,H$4,0),"") | I24: =IFERROR(VLOOKUP($C24,'FO-GC-015'!$A:$AL,I$4,0),"") | M24: Requisito ISO 9001 | N24: 4.1.
B25: =B24+1 -> 21 | C25: =IF(B25<=$E$2,CONCATENATE("Obs-",B25),"") | D25: =IFERROR(VLOOKUP($C25,'FO-GC-015'!$A:$AL,D$4,0),"") | E25: =IF(C25="","",CONCATENATE($N$6,$M$2,$N$7,$M$1," al ",$N$8,$M$3,$N$9,G25,$N$10,"""",H25,""",",$N$11,I25,$N$12,F25,$N$13,D25,$N$14)) | F25: =IFERROR(VLOOKUP($C25,'FO-GC-015'!$A:$AL,F$4,0),"") | G25: =IFERROR(VLOOKUP($C25,'FO-GC-015'!$A:$AL,G$4,0),"") | H25: =IFERROR(VLOOKUP($C25,'FO-GC-015'!$A:$AL,H$4,0),"") | I25: =IFERROR(VLOOKUP($C25,'FO-GC-015'!$A:$AL,I$4,0),"")
B26: =B25+1 -> 22 | C26: =IF(B26<=$E$2,CONCATENATE("Obs-",B26),"") | D26: =IFERROR(VLOOKUP($C26,'FO-GC-015'!$A:$AL,D$4,0),"") | E26: =IF(C26="","",CONCATENATE($N$6,$M$2,$N$7,$M$1," al ",$N$8,$M$3,$N$9,G26,$N$10,"""",H26,""",",$N$11,I26,$N$12,F26,$N$13,D26,$N$14)) | F26: =IFERROR(VLOOKUP($C26,'FO-GC-015'!$A:$AL,F$4,0),"") | G26: =IFERROR(VLOOKUP($C26,'FO-GC-015'!$A:$AL,G$4,0),"") | H26: =IFERROR(VLOOKUP($C26,'FO-GC-015'!$A:$AL,H$4,0),"") | I26: =IFERROR(VLOOKUP($C26,'FO-GC-015'!$A:$AL,I$4,0),"") | L26: Redacción sugerida para el ejemplo:
B27: =B26+1 -> 23 | C27: =IF(B27<=$E$2,CONCATENATE("Obs-",B27),"") | D27: =IFERROR(VLOOKUP($C27,'FO-GC-015'!$A:$AL,D$4,0),"") | E27: =IF(C27="","",CONCATENATE($N$6,$M$2,$N$7,$M$1," al ",$N$8,$M$3,$N$9,G27,$N$10,"""",H27,""",",$N$11,I27,$N$12,F27,$N$13,D27,$N$14)) | F27: =IFERROR(VLOOKUP($C27,'FO-GC-015'!$A:$AL,F$4,0),"") | G27: =IFERROR(VLOOKUP($C27,'FO-GC-015'!$A:$AL,G$4,0),"") | H27: =IFERROR(VLOOKUP($C27,'FO-GC-015'!$A:$AL,H$4,0),"") | I27: =IFERROR(VLOOKUP($C27,'FO-GC-015'!$A:$AL,I$4,0),"") | L27: =CONCATENATE(N6,N17,N7,N18," al ",N8,N19,N9,N20,N10,"""",N21,""",",N11,N22,N12,N23,N13,N24,N14) -> #N/A
B28: =B27+1 -> 24 | C28: =IF(B28<=$E$2,CONCATENATE("Obs-",B28),"") | D28: =IFERROR(VLOOKUP($C28,'FO-GC-015'!$A:$AL,D$4,0),"") | E28: =IF(C28="","",CONCATENATE($N$6,$M$2,$N$7,$M$1," al ",$N$8,$M$3,$N$9,G28,$N$10,"""",H28,""",",$N$11,I28,$N$12,F28,$N$13,D28,$N$14)) | F28: =IFERROR(VLOOKUP($C28,'FO-GC-015'!$A:$AL,F$4,0),"") | G28: =IFERROR(VLOOKUP($C28,'FO-GC-015'!$A:$AL,G$4,0),"") | H28: =IFERROR(VLOOKUP($C28,'FO-GC-015'!$A:$AL,H$4,0),"") | I28: =IFERROR(VLOOKUP($C28,'FO-GC-015'!$A:$AL,I$4,0),"")
B29: =B28+1 -> 25 | C29: =IF(B29<=$E$2,CONCATENATE("Obs-",B29),"") | D29: =IFERROR(VLOOKUP($C29,'FO-GC-015'!$A:$AL,D$4,0),"") | E29: =IF(C29="","",CONCATENATE($N$6,$M$2,$N$7,$M$1," al ",$N$8,$M$3,$N$9,G29,$N$10,"""",H29,""",",$N$11,I29,$N$12,F29,$N$13,D29,$N$14)) | F29: =IFERROR(VLOOKUP($C29,'FO-GC-015'!$A:$AL,F$4,0),"") | G29: =IFERROR(VLOOKUP($C29,'FO-GC-015'!$A:$AL,G$4,0),"") | H29: =IFERROR(VLOOKUP($C29,'FO-GC-015'!$A:$AL,H$4,0),"") | I29: =IFERROR(VLOOKUP($C29,'FO-GC-015'!$A:$AL,I$4,0),"")
B30: =B29+1 -> 26 | C30: =IF(B30<=$E$2,CONCATENATE("Obs-",B30),"") | D30: =IFERROR(VLOOKUP($C30,'FO-GC-015'!$A:$AL,D$4,0),"") | E30: =IF(C30="","",CONCATENATE($N$6,$M$2,$N$7,$M$1," al ",$N$8,$M$3,$N$9,G30,$N$10,"""",H30,""",",$N$11,I30,$N$12,F30,$N$13,D30,$N$14)) | F30: =IFERROR(VLOOKUP($C30,'FO-GC-015'!$A:$AL,F$4,0),"") | G30: =IFERROR(VLOOKUP($C30,'FO-GC-015'!$A:$AL,G$4,0),"") | H30: =IFERROR(VLOOKUP($C30,'FO-GC-015'!$A:$AL,H$4,0),"") | I30: =IFERROR(VLOOKUP($C30,'FO-GC-015'!$A:$AL,I$4,0),"")
B31: =B30+1 -> 27 | C31: =IF(B31<=$E$2,CONCATENATE("Obs-",B31),"") | D31: =IFERROR(VLOOKUP($C31,'FO-GC-015'!$A:$AL,D$4,0),"") | E31: =IF(C31="","",CONCATENATE($N$6,$M$2,$N$7,$M$1," al ",$N$8,$M$3,$N$9,G31,$N$10,"""",H31,""",",$N$11,I31,$N$12,F31,$N$13,D31,$N$14)) | F31: =IFERROR(VLOOKUP($C31,'FO-GC-015'!$A:$AL,F$4,0),"") | G31: =IFERROR(VLOOKUP($C31,'FO-GC-015'!$A:$AL,G$4,0),"") | H31: =IFERROR(VLOOKUP($C31,'FO-GC-015'!$A:$AL,H$4,0),"") | I31: =IFERROR(VLOOKUP($C31,'FO-GC-015'!$A:$AL,I$4,0),"")
B32: =B31+1 -> 28 | C32: =IF(B32<=$E$2,CONCATENATE("Obs-",B32),"") | D32: =IFERROR(VLOOKUP($C32,'FO-GC-015'!$A:$AL,D$4,0),"") | E32: =IF(C32="","",CONCATENATE($N$6,$M$2,$N$7,$M$1," al ",$N$8,$M$3,$N$9,G32,$N$10,"""",H32,""",",$N$11,I32,$N$12,F32,$N$13,D32,$N$14)) | F32: =IFERROR(VLOOKUP($C32,'FO-GC-015'!$A:$AL,F$4,0),"") | G32: =IFERROR(VLOOKUP($C32,'FO-GC-015'!$A:$AL,G$4,0),"") | H32: =IFERROR(VLOOKUP($C32,'FO-GC-015'!$A:$AL,H$4,0),"") | I32: =IFERROR(VLOOKUP($C32,'FO-GC-015'!$A:$AL,I$4,0),"")
B33: =B32+1 -> 29 | C33: =IF(B33<=$E$2,CONCATENATE("Obs-",B33),"") | D33: =IFERROR(VLOOKUP($C33,'FO-GC-015'!$A:$AL,D$4,0),"") | E33: =IF(C33="","",CONCATENATE($N$6,$M$2,$N$7,$M$1," al ",$N$8,$M$3,$N$9,G33,$N$10,"""",H33,""",",$N$11,I33,$N$12,F33,$N$13,D33,$N$14)) | F33: =IFERROR(VLOOKUP($C33,'FO-GC-015'!$A:$AL,F$4,0),"") | G33: =IFERROR(VLOOKUP($C33,'FO-GC-015'!$A:$AL,G$4,0),"") | H33: =IFERROR(VLOOKUP($C33,'FO-GC-015'!$A:$AL,H$4,0),"") | I33: =IFERROR(VLOOKUP($C33,'FO-GC-015'!$A:$AL,I$4,0),"")
B34: =B33+1 -> 30 | C34: =IF(B34<=$E$2,CONCATENATE("Obs-",B34),"") | D34: =IFERROR(VLOOKUP($C34,'FO-GC-015'!$A:$AL,D$4,0),"") | E34: =IF(C34="","",CONCATENATE($N$6,$M$2,$N$7,$M$1," al ",$N$8,$M$3,$N$9,G34,$N$10,"""",H34,""",",$N$11,I34,$N$12,F34,$N$13,D34,$N$14)) | F34: =IFERROR(VLOOKUP($C34,'FO-GC-015'!$A:$AL,F$4,0),"") | G34: =IFERROR(VLOOKUP($C34,'FO-GC-015'!$A:$AL,G$4,0),"") | H34: =IFERROR(VLOOKUP($C34,'FO-GC-015'!$A:$AL,H$4,0),"") | I34: =IFERROR(VLOOKUP($C34,'FO-GC-015'!$A:$AL,I$4,0),"")
B35: =B34+1 -> 31 | C35: =IF(B35<=$E$2,CONCATENATE("Obs-",B35),"") | D35: =IFERROR(VLOOKUP($C35,'FO-GC-015'!$A:$AL,D$4,0),"") | E35: =IF(C35="","",CONCATENATE($N$6,$M$2,$N$7,$M$1," al ",$N$8,$M$3,$N$9,G35,$N$10,"""",H35,""",",$N$11,I35,$N$12,F35,$N$13,D35,$N$14)) | F35: =IFERROR(VLOOKUP($C35,'FO-GC-015'!$A:$AL,F$4,0),"") | G35: =IFERROR(VLOOKUP($C35,'FO-GC-015'!$A:$AL,G$4,0),"") | H35: =IFERROR(VLOOKUP($C35,'FO-GC-015'!$A:$AL,H$4,0),"") | I35: =IFERROR(VLOOKUP($C35,'FO-GC-015'!$A:$AL,I$4,0),"")
B36: =B35+1 -> 32 | C36: =IF(B36<=$E$2,CONCATENATE("Obs-",B36),"") | D36: =IFERROR(VLOOKUP($C36,'FO-GC-015'!$A:$AL,D$4,0),"") | E36: =IF(C36="","",CONCATENATE($N$6,$M$2,$N$7,$M$1," al ",$N$8,$M$3,$N$9,G36,$N$10,"""",H36,""",",$N$11,I36,$N$12,F36,$N$13,D36,$N$14)) | F36: =IFERROR(VLOOKUP($C36,'FO-GC-015'!$A:$AL,F$4,0),"") | G36: =IFERROR(VLOOKUP($C36,'FO-GC-015'!$A:$AL,G$4,0),"") | H36: =IFERROR(VLOOKUP($C36,'FO-GC-015'!$A:$AL,H$4,0),"") | I36: =IFERROR(VLOOKUP($C36,'FO-GC-015'!$A:$AL,I$4,0),"")
B37: =B36+1 -> 33 | C37: =IF(B37<=$E$2,CONCATENATE("Obs-",B37),"") | D37: =IFERROR(VLOOKUP($C37,'FO-GC-015'!$A:$AL,D$4,0),"") | E37: =IF(C37="","",CONCATENATE($N$6,$M$2,$N$7,$M$1," al ",$N$8,$M$3,$N$9,G37,$N$10,"""",H37,""",",$N$11,I37,$N$12,F37,$N$13,D37,$N$14)) | F37: =IFERROR(VLOOKUP($C37,'FO-GC-015'!$A:$AL,F$4,0),"") | G37: =IFERROR(VLOOKUP($C37,'FO-GC-015'!$A:$AL,G$4,0),"") | H37: =IFERROR(VLOOKUP($C37,'FO-GC-015'!$A:$AL,H$4,0),"") | I37: =IFERROR(VLOOKUP($C37,'FO-GC-015'!$A:$AL,I$4,0),"")
B38: =B37+1 -> 34 | C38: =IF(B38<=$E$2,CONCATENATE("Obs-",B38),"") | D38: =IFERROR(VLOOKUP($C38,'FO-GC-015'!$A:$AL,D$4,0),"") | E38: =IF(C38="","",CONCATENATE($N$6,$M$2,$N$7,$M$1," al ",$N$8,$M$3,$N$9,G38,$N$10,"""",H38,""",",$N$11,I38,$N$12,F38,$N$13,D38,$N$14)) | F38: =IFERROR(VLOOKUP($C38,'FO-GC-015'!$A:$AL,F$4,0),"") | G38: =IFERROR(VLOOKUP($C38,'FO-GC-015'!$A:$AL,G$4,0),"") | H38: =IFERROR(VLOOKUP($C38,'FO-GC-015'!$A:$AL,H$4,0),"") | I38: =IFERROR(VLOOKUP($C38,'FO-GC-015'!$A:$AL,I$4,0),"")

Sheet Eq. Auditor
E1: Equipo Auditor FUP - Ciclo: | G1: 2022 | M1: =SUM(M$3:M$61) -> 18 | N1: =SUM(N$3:N$61) -> 32 | O1: =SUM(O$3:O$61) -> 0 | P1: =SUM(P$3:P$61) -> 47 | Q1: =SUM(Q$3:Q$61) -> 5
E2: Id | F2: Nombre y Apellido | G2: Cargo | H2: Correo Electrónico | I2: Asignación | J2: Disp. Inter | K2: CATEGORIA | L2: Exp. | M2: AI - *P 2020 | N2: AI - *P 2021 | O2: AI - A 2021 | P2: AI - *P 2022 | Q2: AI - A 2022 | R2: AI - *P 2023 | S2: AI - A 2023
A3: =E3 -> 1 | B3: =IFERROR(CONCATENATE(IF(MID(VLOOKUP(A3,C:I,7,0),1,1)="P","*",""),VLOOKUP(A3,C:F,4,0)),"") -> *Aida Marcela Correa Benavides | C3: =IF(J3="Si",COUNTIF(J$3:J3,"Si"),"") -> 1 | D3: =TEXT(ISEVEN(E3),0) -> FALSO | E3: =IF(F3="","",COUNTA(F$3:F3)) -> 1 | F3: Aida Marcela Correa Benavides | G3: Compras | H3: compras@fup.edu.co | I3: Principal | J3: Si | K3: ORO | L3: =SUM(M3:T3) -> 9 | N3: 2 | P3: 2 | R3: 3 | S3: 2
A4: =E4 -> 2 | B4: =IFERROR(CONCATENATE(IF(MID(VLOOKUP(A4,C:I,7,0),1,1)="P","*",""),VLOOKUP(A4,C:F,4,0)),"") -> Alex Fabián Rivera Muñoz | C4: =IF(J4="Si",COUNTIF(J$3:J4,"Si"),"") -> 2 | D4: =TEXT(ISEVEN(E4),0) -> VERDADERO | E4: =IF(F4="","",COUNTA(F$3:F4)) -> 2 | F4: Alex Fabián Rivera Muñoz | G4: Docente | H4: alex.rivera@docente.fup.edu.co | I4: Asistente | J4: Si | L4: =SUM(M4:T4) -> 0 | P4: =IFERROR(VLOOKUP(CONCATENATE(IF(MID($I4,1,1)="P","*",""),$F4),'[1]Programación x Auditor'!$C:$E,2,0),"") -> 0 | Q4: =IFERROR(VLOOKUP(CONCATENATE(IF(MID($I4,1,1)="P","*",""),$F4),'[1]Programación x Auditor'!$C:$E,3,0),"") -> 0
A5: =E5 -> 3 | B5: =IFERROR(CONCATENATE(IF(MID(VLOOKUP(A5,C:I,7,0),1,1)="P","*",""),VLOOKUP(A5,C:F,4,0)),"") -> Alexander Luna Nieto | C5: =IF(J5="Si",COUNTIF(J$3:J5,"Si"),"") -> 3 | D5: =TEXT(ISEVEN(E5),0) -> FALSO | E5: =IF(F5="","",COUNTA(F$3:F5)) -> 3 | F5: Alexander Luna Nieto | G5: Docente | H5: alexander.luna@docente.fup.edu.co | I5: Asistente | J5: Si | K5: PLATA | L5: =SUM(M5:T5) -> 6 | N5: 2 | P5: 2 | S5: 2
A6: =E6 -> 4 | B6: =IFERROR(CONCATENATE(IF(MID(VLOOKUP(A6,C:I,7,0),1,1)="P","*",""),VLOOKUP(A6,C:F,4,0)),"") -> Ana Baos | C6: =IF(J6="Si",COUNTIF(J$3:J6,"Si"),"") -> 4 | D6: =TEXT(ISEVEN(E6),0) -> VERDADERO | E6: =IF(F6="","",COUNTA(F$3:F6)) -> 4 | F6: Ana Baos | G6: Apoyo leac | H6: apoyo.leac@fup.edu.co | I6: Asistente | J6: Si | K6: PLATA | L6: =SUM(M6:T6) -> 4 | M6: 2 | P6: =IFERROR(VLOOKUP(CONCATENATE(IF(MID($I6,1,1)="P","*",""),$F6),'[1]Programación x Auditor'!$C:$E,2,0),"") -> 0 | S6: 2
A7: =E7 -> 5 | B7: =IFERROR(CONCATENATE(IF(MID(VLOOKUP(A7,C:I,7,0),1,1)="P","*",""),VLOOKUP(A7,C:F,4,0)),"") -> Andrea Karina Ballagan Estrada | C7: =IF(J7="Si",COUNTIF(J$3:J7,"Si"),"") -> 5 | D7: =TEXT(ISEVEN(E7),0) -> FALSO | E7: =IF(F7="","",COUNTA(F$3:F7)) -> 5 | F7: Andrea Karina Ballagan Estrada | G7: Auxiliar Académica | H7: auxiliaracademico.tsocial@fup.edu.co | I7: Asistente | J7: Si | K7: PLATA | L7: =SUM(M7:T7) -> 5 | P7: 2 | Q7: =IFERROR(VLOOKUP(CONCATENATE(IF(MID($I7,1,1)="P","*",""),$F7),'[1]Programación x Auditor'!$C:$E,3,0),"") -> 1 | S7: 2
A8: =E8 -> 6 | B8: =IFERROR(CONCATENATE(IF(MID(VLOOKUP(A8,C:I,7,0),1,1)="P","*",""),VLOOKUP(A8,C:F,4,0)),"") -> *Carlos Andrés Durán Enríquez | C8: =IF(J8="Si",COUNTIF(J$3:J8,"Si"),"") -> 6 | D8: =TEXT(ISEVEN(E8),0) -> VERDADERO | E8: =IF(F8="","",COUNTA(F$3:F8)) -> 6 | F8: Carlos Andrés Durán Enríquez | G8: Decano Facultad Ciencias Ambientales y Agrarias | H8: decanatura.ambientalesyagrarias@fup.edu.co | I8: Principal | J8: Si | K8: ORO | L8: =SUM(M8:T8) -> 8 | N8: 2 | P8: 2 | R8: 2 | S8: 2
A9: =E9 -> 7 | B9: =IFERROR(CONCATENATE(IF(MID(VLOOKUP(A9,C:I,7,0),1,1)="P","*",""),VLOOKUP(A9,C:F,4,0)),"") -> *Carlos Fernando Mina Zape | C9: =IF(J9="Si",COUNTIF(J$3:J9,"Si"),"") -> 7 | D9: =TEXT(ISEVEN(E9),0) -> FALSO | E9: =IF(F9="","",COUNTA(F$3:F9)) -> 7 | F9: Carlos Fernando Mina Zape | G9: Director Programa de Psicologia | H9: psicologia@fup.edu.co | I9: Principal | J9: Si | K9: ORO | L9: =SUM(M9:T9) -> 5 | N9: 2 | P9: 2 | S9: 1
A10: =E10 -> 8 | B10: =IFERROR(CONCATENATE(IF(MID(VLOOKUP(A10,C:I,7,0),1,1)="P","*",""),VLOOKUP(A10,C:F,4,0)),"") -> *Clara Eugenia Satizábal Serna | C10: =IF(J10="Si",COUNTIF(J$3:J10,"Si"),"") -> 8 | D10: =TEXT(ISEVEN(E10),0) -> VERDADERO | E10: =IF(F10="","",COUNTA(F$3:F10)) -> 8 | F10: Clara Eugenia Satizábal Serna | G10: Directora Programa de Ingeniería de Sistemas | H10: sistemas@fup.edu.co | I10: Principal | J10: Si | K10: ORO | L10: =SUM(M10:T10) -> 5 | M10: 2 | P10: 2 | R10: 1
A11: =E11 -> 9 | B11: =IFERROR(CONCATENATE(IF(MID(VLOOKUP(A11,C:I,7,0),1,1)="P","*",""),VLOOKUP(A11,C:F,4,0)),"") -> *Daisy Ximena Valencia Palomino | C11: =IF(J11="Si",COUNTIF(J$3:J11,"Si"),"") -> 9 | D11: =TEXT(ISEVEN(E11),0) -> FALSO | E11: =IF(F11="","",COUNTA(F$3:F11)) -> 9 | F11: Daisy Ximena Valencia Palomino | G11: Decana Ciencias Sociales | H11: decanatura.cienciassociales@fup.edu.co | I11: Principal | J11: Si | K11: ORO | L11: =SUM(M11:T11) -> 7 | N11: 3 | P11: 2 | R11: 2
A12: =E12 -> 10 | B12: =IFERROR(CONCATENATE(IF(MID(VLOOKUP(A12,C:I,7,0),1,1)="P","*",""),VLOOKUP(A12,C:F,4,0)),"") -> *Daniel Andres Feriz Garcia | C12: =IF(J12="Si",COUNTIF(J$3:J12,"Si"),"") -> 10 | D12: =TEXT(ISEVEN(E12),0) -> VERDADERO | E12: =IF(F12="","",COUNTA(F$3:F12)) -> 10 | F12: Daniel Andres Feriz Garcia | G12: Director investigación | H12: investigacion@fup.edu.co | I12: Principal | J12: Si | K12: ORO | L12: =SUM(M12:T12) -> 9 | M12: 2 | N12: 2 | P12: 2 | R12: 2 | S12: 1
A13: =E13 -> 11 | B13: =IFERROR(CONCATENATE(IF(MID(VLOOKUP(A13,C:I,7,0),1,1)="P","*",""),VLOOKUP(A13,C:F,4,0)),"") -> *Depsi Johana Córdoba Mompotes | C13: =IF(J13="Si",COUNTIF(J$3:J13,"Si"),"") -> 11 | D13: =TEXT(ISEVEN(E13),0) -> FALSO | E13: =IF(F13="","",COUNTA(F$3:F13)) -> 11 | F13: Depsi Johana Córdoba Mompotes | G13: Coordinadora de Gestión Curricular | H13: coord.gestioncurricular@fup.edu.co | I13: Principal | J13: Si | K13: PLATA | L13: =SUM(M13:T13) -> 5 | P13: 2 | R13: 3
A14: =E14 -> 12 | B14: =IFERROR(CONCATENATE(IF(MID(VLOOKUP(A14,C:I,7,0),1,1)="P","*",""),VLOOKUP(A14,C:F,4,0)),"") -> *Diego Fabian Bolaños Sarria | C14: =IF(J14="Si",COUNTIF(J$3:J14,"Si"),"") -> 12 | D14: =TEXT(ISEVEN(E14),0) -> VERDADERO | E14: =IF(F14="","",COUNTA(F$3:F14)) -> 12 | F14: Diego Fabian Bolaños Sarria | G14: Decano Facultad de Ingenierías | H14: decanatura.ingenieriasyarquitectura@fup.edu.co | I14: Principal | J14: Si | K14: ORO | L14: =SUM(M14:T14) -> 7 | M14: 2 | N14: 2 | P14: 2 | R14: 1
A15: =E15 -> 13 | B15: =IFERROR(CONCATENATE(IF(MID(VLOOKUP(A15,C:I,7,0),1,1)="P","*",""),VLOOKUP(A15,C:F,4,0)),"") -> Gabriela Andrea Rivera Macias | C15: =IF(J15="Si",COUNTIF(J$3:J15,"Si"),"") -> 13 | D15: =TEXT(ISEVEN(E15),0) -> FALSO | E15: =IF(F15="","",COUNTA(F$3:F15)) -> 13 | F15: Gabriela Andrea Rivera Macias | G15: Docente Tiempo Completo | H15: gabriela.rivera@docente.fup.edu.co | I15: Asistente | J15: Si | L15: =SUM(M15:T15) -> 4 | M15: 2 | N15: 2 | P15: =IFERROR(VLOOKUP(CONCATENATE(IF(MID($I15,1,1)="P","*",""),$F15),'[1]Programación x Auditor'!$C:$E,2,0),"") -> 0 | Q15: =IFERROR(VLOOKUP(CONCATENATE(IF(MID($I15,1,1)="P","*",""),$F15),'[1]Programación x Auditor'!$C:$E,3,0),"") -> 0
A16: =E16 -> 14 | B16: =IFERROR(CONCATENATE(IF(MID(VLOOKUP(A16,C:I,7,0),1,1)="P","*",""),VLOOKUP(A16,C:F,4,0)),"") -> Jaime Vente Garcés | C16: =IF(J16="Si",COUNTIF(J$3:J16,"Si"),"") -> 14 | D16: =TEXT(ISEVEN(E16),0) -> VERDADERO | E16: =IF(F16="","",COUNTA(F$3:F16)) -> 14 | F16: Jaime Vente Garcés | G16: Docente TC | H16: jaime.vente@docente.fup.edu.co | I16: Asistente | J16: Si | K16: PLATA | L16: =SUM(M16:T16) -> 3 | P16: 2 | Q16: =IFERROR(VLOOKUP(CONCATENATE(IF(MID($I16,1,1)="P","*",""),$F16),'[1]Programación x Auditor'!$C:$E,3,0),"") -> 1
A17: =E17 -> 15 | B17: =IFERROR(CONCATENATE(IF(MID(VLOOKUP(A17,C:I,7,0),1,1)="P","*",""),VLOOKUP(A17,C:F,4,0)),"") -> José Fernando Ruíz López | C17: =IF(J17="Si",COUNTIF(J$3:J17,"Si"),"") -> 15 | D17: =TEXT(ISEVEN(E17),0) -> FALSO | E17: =IF(F17="","",COUNTA(F$3:F17)) -> 15 | F17: José Fernando Ruíz López | G17: Docente | H17: jose.ruiz@docente.fup.edu.co | I17: Asistente | J17: Si | L17: =SUM(M17:T17) -> 3 | P17: =IFERROR(VLOOKUP(CONCATENATE(IF(MID($I17,1,1)="P","*",""),$F17),'[1]Programación x Auditor'!$C:$E,2,0),"") -> 0 | Q17: =IFERROR(VLOOKUP(CONCATENATE(IF(MID($I17,1,1)="P","*",""),$F17),'[1]Programación x Auditor'!$C:$E,3,0),"") -> 1 | S17: 2
A18: =E18 -> 16 | B18: =IFERROR(CONCATENATE(IF(MID(VLOOKUP(A18,C:I,7,0),1,1)="P","*",""),VLOOKUP(A18,C:F,4,0)),"") -> *Juan David Cortés León | C18: =IF(J18="Si",COUNTIF(J$3:J18,"Si"),"") -> 16 | D18: =TEXT(ISEVEN(E18),0) -> VERDADERO | E18: =IF(F18="","",COUNTA(F$3:F18)) -> 16 | F18: Juan David Cortés León | G18: Coordinador Academico | H18: coordinacion.arquitectura@fup.edu.co | I18: Principal | J18: Si | K18: PLATA | L18: =SUM(M18:T18) -> 7 | P18: 2 | Q18: =IFERROR(VLOOKUP(CONCATENATE(IF(MID($I18,1,1)="P","*",""),$F18),'[1]Programación x Auditor'!$C:$E,3,0),"") -> 0 | R18: 3 | S18: 2
A19: =E19 -> 17 | B19: =IFERROR(CONCATENATE(IF(MID(VLOOKUP(A19,C:I,7,0),1,1)="P","*",""),VLOOKUP(A19,C:F,4,0)),"") -> *Julian Camilo Ortega Gomez | C19: =IF(J19="Si",COUNTIF(J$3:J19,"Si"),"") -> 17 | D19: =TEXT(ISEVEN(E19),0) -> FALSO | E19: =IF(F19="","",COUNTA(F$3:F19)) -> 17 | F19: Julian Camilo Ortega Gomez | G19: Docente - Coordinador de Egresados Ingeniería Industrial | H19: julian.ortega@docente.fup.edu.co | I19: Principal | J19: Si | K19: PLATA | L19: =SUM(M19:T19) -> 5 | N19: 2 | P19: =IFERROR(VLOOKUP(CONCATENATE(IF(MID($I19,1,1)="P","*",""),$F19),'[1]Programación x Auditor'!$C:$E,2,0),"") -> 1 | Q19: =IFERROR(VLOOKUP(CONCATENATE(IF(MID($I19,1,1)="P","*",""),$F19),'[1]Programación x Auditor'!$C:$E,3,0),"") -> 0 | S19: 2
A20: =E20 -> 18 | B20: =IFERROR(CONCATENATE(IF(MID(VLOOKUP(A20,C:I,7,0),1,1)="P","*",""),VLOOKUP(A20,C:F,4,0)),"") -> *Julio Cesar Garcia Buitron | C20: =IF(J20="Si",COUNTIF(J$3:J20,"Si"),"") -> 18 | D20: =TEXT(ISEVEN(E20),0) -> VERDADERO | E20: =IF(F20="","",COUNTA(F$3:F20)) -> 18 | F20: Julio Cesar Garcia Buitron | G20: Contador | H20: contador@fup.edu.co | I20: Principal | J20: Si | K20: ORO | L20: =SUM(M20:T20) -> 7 | M20: 2 | N20: 2 | P20: 1 | R20: 2
A21: =E21 -> 19 | B21: =IFERROR(CONCATENATE(IF(MID(VLOOKUP(A21,C:I,7,0),1,1)="P","*",""),VLOOKUP(A21,C:F,4,0)),"") -> Karen Jisset Zuñiga Ramos | C21: =IF(J21="Si",COUNTIF(J$3:J21,"Si"),"") -> 19 | D21: =TEXT(ISEVEN(E21),0) -> FALSO | E21: =IF(F21="","",COUNTA(F$3:F21)) -> 19 | F21: Karen Jisset Zuñiga Ramos | G21: Coordinadora Trabajo Social Sede Norte | H21: trabajo.social.santander@fup.edu.co | I21: Asistente | J21: Si | K21: ORO | L21: =SUM(M21:T21) -> 5 | N21: 2 | P21: 1 | S21: 2
A22: =E22 -> 20 | B22: =IFERROR(CONCATENATE(IF(MID(VLOOKUP(A22,C:I,7,0),1,1)="P","*",""),VLOOKUP(A22,C:F,4,0)),"") -> *Karen Viviana Quiñones Mosquera | C22: =IF(J22="Si",COUNTIF(J$3:J22,"Si"),"") -> 20 | D22: =TEXT(ISEVEN(E22),0) -> VERDADERO | E22: =IF(F22="","",COUNTA(F$3:F22)) -> 20 | F22: Karen Viviana Quiñones Mosquera | G22: COORDINADORA DE GESTION PARA LA INVESTIGACION | H22: coor.gestiondeinvestigacion@fup.edu.co | I22: Principal | J22: Si | K22: ORO | L22: =SUM(M22:T22) -> 8 | N22: 1 | P22: 2 | R22: 3 | S22: 2
A23: =E23 -> 21 | B23: =IFERROR(CONCATENATE(IF(MID(VLOOKUP(A23,C:I,7,0),1,1)="P","*",""),VLOOKUP(A23,C:F,4,0)),"") -> *Kener Mauricio Quina Velarde | C23: =IF(J23="Si",COUNTIF(J$3:J23,"Si"),"") -> 21 | D23: =TEXT(ISEVEN(E23),0) -> FALSO | E23: =IF(F23="","",COUNTA(F$3:F23)) -> 21 | F23: Kener Mauricio Quina Velarde | G23: Auxiliar de Planeación | H23: auxiliar.planeacion@fup.edu.co | I23: Principal | J23: Si | K23: PLATA | L23: =SUM(M23:T23) -> 8 | P23: 2 | Q23: =IFERROR(VLOOKUP(CONCATENATE(IF(MID($I23,1,1)="P","*",""),$F23),'[1]Programación x Auditor'!$C:$E,3,0),"") -> 0 | R23: 3 | S23: 3
A24: =E24 -> 22 | B24: =IFERROR(CONCATENATE(IF(MID(VLOOKUP(A24,C:I,7,0),1,1)="P","*",""),VLOOKUP(A24,C:F,4,0)),"") -> Laura María Orozco García | C24: =IF(J24="Si",COUNTIF(J$3:J24,"Si"),"") -> 22 | D24: =TEXT(ISEVEN(E24),0) -> VERDADERO | E24: =IF(F24="","",COUNTA(F$3:F24)) -> 22 | F24: Laura María Orozco García | G24: Docente - Coordinadora Autoevaluación Ing. Sistemas | H24: laura.orozco@docente.fup.edu.co | I24: Asistente | J24: Si | L24: =SUM(M24:T24) -> 0 | P24: =IFERROR(VLOOKUP(CONCATENATE(IF(MID($I24,1,1)="P","*",""),$F24),'[1]Programación x Auditor'!$C:$E,2,0),"") -> 0 | Q24: =IFERROR(VLOOKUP(CONCATENATE(IF(MID($I24,1,1)="P","*",""),$F24),'[1]Programación x Auditor'!$C:$E,3,0),"") -> 0
A25: =E25 -> 23 | B25: =IFERROR(CONCATENATE(IF(MID(VLOOKUP(A25,C:I,7,0),1,1)="P","*",""),VLOOKUP(A25,C:F,4,0)),"") -> *Liliana Erazo | C25: =IF(J25="Si",COUNTIF(J$3:J25,"Si"),"") -> 23 | D25: =TEXT(ISEVEN(E25),0) -> FALSO | E25: =IF(F25="","",COUNTA(F$3:F25)) -> 23 | F25: Liliana Erazo | G25: Asistente Administrativo | H25: asistente.posgrados@fup.edu.co | I25: Principal | J25: Si | K25: ORO | L25: =SUM(M25:T25) -> 8 | M25: 2 | N25: 1 | P25: 2 | R25: 3
A26: =E26 -> 24 | B26: =IFERROR(CONCATENATE(IF(MID(VLOOKUP(A26,C:I,7,0),1,1)="P","*",""),VLOOKUP(A26,C:F,4,0)),"") -> Martha Lucia Bolaños Imbachi | C26: =IF(J26="Si",COUNTIF(J$3:J26,"Si"),"") -> 24 | D26: =TEXT(ISEVEN(E26),0) -> VERDADERO | E26: =IF(F26="","",COUNTA(F$3:F26)) -> 24 | F26: Martha Lucia Bolaños Imbachi | G26: Docente | H26: martha.bolanos@docente.fup.edu.co | I26: Asistente | J26: Si | K26: BRONCE | L26: =SUM(M26:T26) -> 0 | P26: =IFERROR(VLOOKUP(CONCATENATE(IF(MID($I26,1,1)="P","*",""),$F26),'[1]Programación x Auditor'!$C:$E,2,0),"") -> 0 | Q26: =IFERROR(VLOOKUP(CONCATENATE(IF(MID($I26,1,1)="P","*",""),$F26),'[1]Programación x Auditor'!$C:$E,3,0),"") -> 0
A27: =E27 -> 25 | B27: =IFERROR(CONCATENATE(IF(MID(VLOOKUP(A27,C:I,7,0),1,1)="P","*",""),VLOOKUP(A27,C:F,4,0)),"") -> Miguel Dario Calvachy | C27: =IF(J27="Si",COUNTIF(J$3:J27,"Si"),"") -> 25 | D27: =TEXT(ISEVEN(E27),0) -> FALSO | E27: =IF(F27="","",COUNTA(F$3:F27)) -> 25 | F27: Miguel Dario Calvachy | G27: Docente | H27: miguel.calvachy@docente.fup.edu.co | I27: Asistente | J27: Si | K27: PLATA | L27: =SUM(M27:T27) -> 5 | M27: 2 | N27: 2 | P27: =IFERROR(VLOOKUP(CONCATENATE(IF(MID($I27,1,1)="P","*",""),$F27),'[1]Programación x Auditor'!$C:$E,2,0),"") -> 0 | Q27: =IFERROR(VLOOKUP(CONCATENATE(IF(MID($I27,1,1)="P","*",""),$F27),'[1]Programación x Auditor'!$C:$E,3,0),"") -> 0 | S27: 1
A28: =E28 -> 26 | B28: =IFERROR(CONCATENATE(IF(MID(VLOOKUP(A28,C:I,7,0),1,1)="P","*",""),VLOOKUP(A28,C:F,4,0)),"") -> Natalia Córdoba Claros | C28: =IF(J28="Si",COUNTIF(J$3:J28,"Si"),"") -> 26 | D28: =TEXT(ISEVEN(E28),0) -> VERDADERO | E28: =IF(F28="","",COUNTA(F$3:F28)) -> 26 | F28: Natalia Córdoba Claros | G28: Docente | H28: natalia.cordoba@docente.fup.edu.co | I28: Asistente | J28: Si | K28: PLATA | L28: =SUM(M28:T28) -> 6 | P28: 2 | Q28: =IFERROR(VLOOKUP(CONCATENATE(IF(MID($I28,1,1)="P","*",""),$F28),'[1]Programación x Auditor'!$C:$E,3,0),"") -> 1 | R28: 3
A29: =E29 -> 27 | B29: =IFERROR(CONCATENATE(IF(MID(VLOOKUP(A29,C:I,7,0),1,1)="P","*",""),VLOOKUP(A29,C:F,4,0)),"") -> *Neiby Alejandra López Montenegro | C29: =IF(J29="Si",COUNTIF(J$3:J29,"Si"),"") -> 27 | D29: =TEXT(ISEVEN(E29),0) -> FALSO | E29: =IF(F29="","",COUNTA(F$3:F29)) -> 27 | F29: Neiby Alejandra López Montenegro | G29: Coordinación Académica Ingenierías | H29: coordinacionacademica.ingenierias@fup.edu.co | I29: Principal | J29: Si | K29: ORO | L29: =SUM(M29:T29) -> 7 | N29: 2 | P29: 2 | R29: 3
A30: =E30 -> 28 | B30: =IFERROR(CONCATENATE(IF(MID(VLOOKUP(A30,C:I,7,0),1,1)="P","*",""),VLOOKUP(A30,C:F,4,0)),"") -> *Omar Andrés Acosta Caicedo | C30: =IF(J30="Si",COUNTIF(J$3:J30,"Si"),"") -> 28 | D30: =TEXT(ISEVEN(E30),0) -> VERDADERO | E30: =IF(F30="","",COUNTA(F$3:F30)) -> 28 | F30: Omar Andrés Acosta Caicedo | G30: Director de Programa Ingenieria Industrial | H30: industrial@fup.edu.co | I30: Principal | J30: Si | K30: ORO | L30: =SUM(M30:T30) -> 7 | P30: 2 | R30: 3 | S30: 2
A31: =E31 -> 29 | B31: =IFERROR(CONCATENATE(IF(MID(VLOOKUP(A31,C:I,7,0),1,1)="P","*",""),VLOOKUP(A31,C:F,4,0)),"") -> Oscar Eduardo Torres Fernandez | C31: =IF(J31="Si",COUNTIF(J$3:J31,"Si"),"") -> 29 | D31: =TEXT(ISEVEN(E31),0) -> FALSO | E31: =IF(F31="","",COUNTA(F$3:F31)) -> 29 | F31: Oscar Eduardo Torres Fernandez | G31: Docente TC | H31: oscar.torres@docente.fup.edu.co | I31: Asistente | J31: Si | L31: =SUM(M31:T31) -> 1 | P31: =IFERROR(VLOOKUP(CONCATENATE(IF(MID($I31,1,1)="P","*",""),$F31),'[1]Programación x Auditor'!$C:$E,2,0),"") -> 0 | Q31: =IFERROR(VLOOKUP(CONCATENATE(IF(MID($I31,1,1)="P","*",""),$F31),'[1]Programación x Auditor'!$C:$E,3,0),"") -> 1
A32: =E32 -> 30 | B32: =IFERROR(CONCATENATE(IF(MID(VLOOKUP(A32,C:I,7,0),1,1)="P","*",""),VLOOKUP(A32,C:F,4,0)),"") -> Sandra Johanna Pinzón Hermosa | C32: =IF(J32="Si",COUNTIF(J$3:J32,"Si"),"") -> 30 | D32: =TEXT(ISEVEN(E32),0) -> VERDADERO | E32: =IF(F32="","",COUNTA(F$3:F32)) -> 30 | F32: Sandra Johanna Pinzón Hermosa | G32: Coordinadora Académica Prog. Administración de Empresas | H32: coordinacionacademica.faceca@fup.edu.co | I32: Asistente | J32: Si | L32: =SUM(M32:T32) -> 8 | N32: 2 | P32: 2 | R32: 3 | S32: 1
A33: =E33 -> 31 | B33: =IFERROR(CONCATENATE(IF(MID(VLOOKUP(A33,C:I,7,0),1,1)="P","*",""),VLOOKUP(A33,C:F,4,0)),"") -> Tatiana Mejia Rondon | C33: =IF(J33="Si",COUNTIF(J$3:J33,"Si"),"") -> 31 | D33: =TEXT(ISEVEN(E33),0) -> FALSO | E33: =IF(F33="","",COUNTA(F$3:F33)) -> 31 | F33: Tatiana Mejia Rondon | G33: Coordinadora trabajo social | H33: coordinacion.tsocial@fup.edu.co | J33: Si | K33: PLATA | L33: =SUM(M33:T33) -> 7 | P33: 2 | R33: 3 | S33: 2
A34: =E34 -> 32 | B34: =IFERROR(CONCATENATE(IF(MID(VLOOKUP(A34,C:I,7,0),1,1)="P","*",""),VLOOKUP(A34,C:F,4,0)),"") -> *Wadys Montilla Ortega | C34: =IF(J34="Si",COUNTIF(J$3:J34,"Si"),"") -> 32 | D34: =TEXT(ISEVEN(E34),0) -> VERDADERO | E34: =IF(F34="","",COUNTA(F$3:F34)) -> 32 | F34: Wadys Montilla Ortega | G34: Coordinador Académico General | H34: direccion.docencia@fup.edu.co | I34: Principal | J34: Si | K34: ORO | L34: =SUM(M34:T34) -> 7 | M34: 2 | N34: 1 | P34: 2 | R34: 2
A35: =E35 -> 33 | B35: =IFERROR(CONCATENATE(IF(MID(VLOOKUP(A35,C:I,7,0),1,1)="P","*",""),VLOOKUP(A35,C:F,4,0)),"") -> *Yaqueline Rivera López | C35: =IF(J35="Si",COUNTIF(J$3:J35,"Si"),"") -> 33 | D35: =TEXT(ISEVEN(E35),0) -> FALSO | E35: =IF(F35="","",COUNTA(F$3:F35)) -> 33 | F35: Yaqueline Rivera López | G35: Coordinador de Registro Calificado | H35: registro.calificado@fup.edu.co | I35: Principal | J35: Si | K35: PLATA | L35: =SUM(M35:T35) -> 5 | P35: 2 | R35: 3
A36: =E36 -> 34 | B36: =IFERROR(CONCATENATE(IF(MID(VLOOKUP(A36,C:I,7,0),1,1)="P","*",""),VLOOKUP(A36,C:F,4,0)),"") -> *Luisa Marcela Toro Medina | C36: =IF(J36="Si",COUNTIF(J$3:J36,"Si"),"") -> 34 | E36: =IF(F36="","",COUNTA(F$3:F36)) -> 34 | F36: Luisa Marcela Toro Medina | G36: Coordinadora Autoevaluacion | H36: coord.autoevaluacion@fup.edu.co | I36: Principal | J36: Si | K36: PLATA | L36: =SUM(M36:T36) -> 3 | R36: 3
A37: =E37 -> 35 | B37: =IFERROR(CONCATENATE(IF(MID(VLOOKUP(A37,C:I,7,0),1,1)="P","*",""),VLOOKUP(A37,C:F,4,0)),"") -> Nora Fernanda Arciniegas Sanchez | C37: =IF(J37="Si",COUNTIF(J$3:J37,"Si"),"") -> 35 | E37: =IF(F37="","",COUNTA(F$3:F37)) -> 35 | F37: Nora Fernanda Arciniegas Sanchez | G37: Docente | H37: fernanda.arciniegas@docente.fup.edu.co | I37: Asistente | J37: Si | K37: BRONCE | L37: 0
A38: =E38 -> 36 | B38: =IFERROR(CONCATENATE(IF(MID(VLOOKUP(A38,C:I,7,0),1,1)="P","*",""),VLOOKUP(A38,C:F,4,0)),"") -> Jeferson Esteban Cordoba Molano | C38: =IF(J38="Si",COUNTIF(J$3:J38,"Si"),"") -> 36 | E38: =IF(F38="","",COUNTA(F$3:F38)) -> 36 | F38: Jeferson Esteban Cordoba Molano | G38: Auxiliar Contable | H38: auxiliar2.tesoreria@fup.edu.co | I38: Asistente | J38: Si | K38: BRONCE | L38: 0
A39: =E39 -> 37 | B39: =IFERROR(CONCATENATE(IF(MID(VLOOKUP(A39,C:I,7,0),1,1)="P","*",""),VLOOKUP(A39,C:F,4,0)),"") -> Diana Carolina Vasquez Zambrano | C39: =IF(J39="Si",COUNTIF(J$3:J39,"Si"),"") -> 37 | E39: =IF(F39="","",COUNTA(F$3:F39)) -> 37 | F39: Diana Carolina Vasquez Zambrano | G39: Auxiliar | H39: auxiliaradministrativa.secretariageneral@fup.edu.co | I39: Asistente | J39: Si | K39: BRONCE | L39: 0
A40: =E40 -> 38 | B40: =IFERROR(CONCATENATE(IF(MID(VLOOKUP(A40,C:I,7,0),1,1)="P","*",""),VLOOKUP(A40,C:F,4,0)),"") -> Yudi Andrea Acalo Higon | C40: =IF(J40="Si",COUNTIF(J$3:J40,"Si"),"") -> 38 | E40: =IF(F40="","",COUNTA(F$3:F40)) -> 38 | F40: Yudi Andrea Acalo Higon | G40: Directora | H40: trabajo.social@fup.edu.co | I40: Asistente | J40: Si | K40: BRONCE | L40: 0
A41: =E41 -> 39 | B41: =IFERROR(CONCATENATE(IF(MID(VLOOKUP(A41,C:I,7,0),1,1)="P","*",""),VLOOKUP(A41,C:F,4,0)),"") -> Jorge Eduardo Rengifo Lozada | C41: =IF(J41="Si",COUNTIF(J$3:J41,"Si"),"") -> 39 | E41: =IF(F41="","",COUNTA(F$3:F41)) -> 39 | F41: Jorge Eduardo Rengifo Lozada | G41: Auxiliar | H41: auxiliar.grados@fup.edu.co | I41: Asistente | J41: Si | K41: BRONCE | L41: 0
A42: =E42 -> 40 | B42: =IFERROR(CONCATENATE(IF(MID(VLOOKUP(A42,C:I,7,0),1,1)="P","*",""),VLOOKUP(A42,C:F,4,0)),"") -> Arnol Arias Hoyos | C42: =IF(J42="Si",COUNTIF(J$3:J42,"Si"),"") -> 40 | E42: =IF(F42="","",COUNTA(F$3:F42)) -> 40 | F42: Arnol Arias Hoyos | G42: Coordinador | H42: laboratorios@fup.edu.co | I42: Asistente | J42: Si | K42: BRONCE | L42: 0
A43: =E43 -> 41 | B43: =IFERROR(CONCATENATE(IF(MID(VLOOKUP(A43,C:I,7,0),1,1)="P","*",""),VLOOKUP(A43,C:F,4,0)),"") -> Cristian Libardo Idrobo Posada | C43: =IF(J43="Si",COUNTIF(J$3:J43,"Si"),"") -> 41 | E43: =IF(F43="","",COUNTA(F$3:F43)) -> 41 | F43: Cristian Libardo Idrobo Posada | G43: Auxiliar Ingeneria | H43: auxacademica.ingenierias@fup.edu.co | I43: Asistente | J43: Si | K43: BRONCE | L43: 0
A44: =E44 -> 42 | B44: =IFERROR(CONCATENATE(IF(MID(VLOOKUP(A44,C:I,7,0),1,1)="P","*",""),VLOOKUP(A44,C:F,4,0)),"") -> Sergio Andrés Lozano Niño | C44: =IF(J44="Si",COUNTIF(J$3:J44,"Si"),"") -> 42 | E44: =IF(F44="","",COUNTA(F$3:F44)) -> 42 | F44: Sergio Andrés Lozano Niño | G44: Director Planeacion | H44: planeacion@fup.edu.co | I44: Asistente | J44: Si | K44: BRONCE | L44: 0
A45: =E45 -> 43 | B45: =IFERROR(CONCATENATE(IF(MID(VLOOKUP(A45,C:I,7,0),1,1)="P","*",""),VLOOKUP(A45,C:F,4,0)),"") -> Lina Fernanda Gutiérrez Montoya | C45: =IF(J45="Si",COUNTIF(J$3:J45,"Si"),"") -> 43 | E45: =IF(F45="","",COUNTA(F$3:F45)) -> 43 | F45: Lina Fernanda Gutiérrez Montoya | G45: Auxiliar Contable | H45: auxiliar5.contabilidad@fup.edu.co | I45: Asistente | J45: Si | K45: BRONCE | L45: 0
A46: =E46 -> 44 | B46: =IFERROR(CONCATENATE(IF(MID(VLOOKUP(A46,C:I,7,0),1,1)="P","*",""),VLOOKUP(A46,C:F,4,0)),"") -> Fabian Felipe Mera Hurtado | C46: =IF(J46="Si",COUNTIF(J$3:J46,"Si"),"") -> 44 | E46: =IF(F46="","",COUNTA(F$3:F46)) -> 44 | F46: Fabian Felipe Mera Hurtado | G46: Auxiliar de Soporte | H46: soporte.tic2@fup.edu.co | I46: Asistente | J46: Si | K46: BRONCE | L46: 0
A47: =E47 -> 45 | B47: =IFERROR(CONCATENATE(IF(MID(VLOOKUP(A47,C:I,7,0),1,1)="P","*",""),VLOOKUP(A47,C:F,4,0)),"") -> Yeni Fernanda Castrillón Sánchez | C47: =IF(J47="Si",COUNTIF(J$3:J47,"Si"),"") -> 45 | E47: =IF(F47="","",COUNTA(F$3:F47)) -> 45 | F47: Yeni Fernanda Castrillón Sánchez | G47: Asistente | H47: auxiliar.sidi@fup.edu.co | I47: Asistente | J47: Si | K47: BRONCE | L47: 0
A48: =E48 -> 46 | B48: =IFERROR(CONCATENATE(IF(MID(VLOOKUP(A48,C:I,7,0),1,1)="P","*",""),VLOOKUP(A48,C:F,4,0)),"") -> Diego Fernando Ordoñez Trullo | C48: =IF(J48="Si",COUNTIF(J$3:J48,"Si"),"") -> 46 | E48: =IF(F48="","",COUNTA(F$3:F48)) -> 46 | F48: Diego Fernando Ordoñez Trullo | G48: Director de Programa | H48: derecho.popayan@fup.edu.co | I48: Asistente | J48: Si | K48: BRONCE | L48: 0
... A56: =E56 -> 54 | B56: =IFERROR(CONCATENATE(IF(MID(VLOOKUP(A56,C:I,7,0),1,1)="P","*",""),VLOOKUP(A56,C:F,4,0)),"") -> Laura Melissa Muñoz Burbano | C56: =IF(J56="Si",COUNTIF(J$3:J56,"Si"),"") -> 54 | E56: =IF(F56="","",COUNTA(F$3:F56)) -> 54 | F56: Laura Melissa Muñoz Burbano | G56: Profesional VRA | H56: profesional.viceacad@fup.edu.co | I56: Asistente | J56: Si | K56: BRONCE | L56: 0
C57: =IF(J57="Si",COUNTIF(J$3:J57,"Si"),"") | D57: =TEXT(ISEVEN(E57),0) -> #VALUE! | E57: =IF(F57="","",COUNTA(F$3:F57)) | P57: =IFERROR(VLOOKUP(CONCATENATE(IF(MID($I57,1,1)="P","*",""),$F57),'[1]Programación x Auditor'!$C:$E,2,0),"") | Q57: =IFERROR(VLOOKUP(CONCATENATE(IF(MID($I57,1,1)="P","*",""),$F57),'[1]Programación x Auditor'!$C:$E,3,0),"") | R57: 3
C58: =IF(J58="Si",COUNTIF(J$3:J58,"Si"),"")
C59: =IF(J59="Si",COUNTIF(J$3:J59,"Si"),"")
C60: =IF(J60="Si",COUNTIF(J$3:J60,"Si"),"") | F60: Auditor Líder | I60: *** | L60: =SUM(M60:T60) -> 0
C61: =IF(J61="Si",COUNTIF(J$3:J61,"Si"),"") | F61: Equipo Auditor | I61: *** | K61: tenemos | L61: =SUM(M61:T61) -> 0
I62: BRONCE | J62: =COUNTIF(K3:K56,I62) -> 21 | K62: 17
I63: PLATA | J63: =COUNTIF(K3:K56,I63) -> 13 | K63: 18
I64: ORO | J64: =COUNTIF(K3:K56,I64) -> 14 | K64: 9
I65: TOTAL | J65: =SUM(J62:J64) -> 48

Sheet Listas
C2: Auditorias Internas de Calidad Programadas
C3: Proceso / Subproceso / Programa Académico | D3: Cargo Líder de Proceso | E3: ID | F3: Categoría | H3: Nombre Sede "Abreviado" | I3: Nombre Sede | J3: Auditores
A4: =TEXT(ISEVEN(E4),0) -> #VALUE! | C4: Docencia | D4: Director Docencia | E4: DO | F4: proceso | H4: Claustro San José | I4: Claustro San José | J4: *Aida Marcela Correa Benavides
A5: =TEXT(ISEVEN(E5),0) -> #VALUE! | C5: Registro Académico | D5: Coordinador Registro Académico | E5: RA | F5: proceso | H5: Claustro San Camilo | I5: Claustro San Camilo | J5: Ana Adela Baos
A6: =TEXT(ISEVEN(E6),0) -> #VALUE! | C6: Gestión Curricular | D6: Coordinador Gestión Curricular | E6: CU | F6: proceso | H6: Los Robles | I6: Los Robles | J6: Andrea Karina Ballagan Estrada
A7: =TEXT(ISEVEN(E7),0) -> #VALUE! | C7: Investigación, Desarrollo e Innovación | D7: Director Investigación | E7: IN | F7: proceso | H7: Alvaro Ulcué Chocué | I7: Monseñor Samuel Silverio | J7: *Carlos Andrés Durán Enríquez
A8: =TEXT(ISEVEN(E8),0) -> #VALUE! | C8: Extensión y Proyección Social | D8: Director Extensión y Proyección Social | E8: EP | F8: proceso | I8: Arquitectura | J8: *Daisy Ximena Valencia Palomino
A9: =TEXT(ISEVEN(E9),0) -> #VALUE! | C9: Emprendimiento | D9: Coordinador Emprendimiento | E9: EM | F9: proceso | I9: Derecho | J9: *Depsi Johana Córdoba Mompotes
A10: =TEXT(ISEVEN(E10),0) -> #VALUE! | C10: Gestión de Egresados | D10: Coordinador Egresados | E10: GE | F10: proceso | I10: Alvaro Ulcué Chocué | J10: *Diego Fabian Bolaños Sarria
A11: =TEXT(ISEVEN(E11),0) -> #VALUE! | C11: Educación Continuada | D11: Coordinador Educación Continua | E11: EC | F11: proceso | J11: *Gabriela Andrea Rivera Macias
A12: =TEXT(ISEVEN(E12),0) -> #VALUE! | C12: Escuela de Formación para el TDH | D12: Director EFTDH | E12: EF | F12: proceso | J12: *Julio Cesar Garcia Buitron
A13: =TEXT(ISEVEN(E13),0) -> #VALUE! | C13: Direccionamiento Estratégico | D13: Rector | E13: DE | F13: proceso | J13: *Karen Viviana Quiñones Mosquera
A14: =TEXT(ISEVEN(E14),0) -> #VALUE! | C14: Planeación Institucional | D14: Director Planeación Institucional | E14: PL | F14: proceso | J14: *Liliana Erazo
A15: =TEXT(ISEVEN(E15),0) -> #VALUE! | C15: Gestión de Sistemas de Información | D15: Director GSI | E15: SI | F15: proceso | J15: *Omar Andrés Acosta Caicedo
A16: =TEXT(ISEVEN(E16),0) -> #VALUE! | C16: Gestión de Calidad | D16: Coordinador Calidad | E16: GC | F16: proceso | J16: *Tatiana Mejia Rondon
A17: =TEXT(ISEVEN(E17),0) -> #VALUE! | C17: Aseguramiento de la Calidad | D17: Director Aseguramiento de la Calidad | E17: AC | F17: proceso | J17: *Wadys Montilla Ortega
A18: =TEXT(ISEVEN(E18),0) -> #VALUE! | C18: Autoevaluación Institucional | D18: Coordinador Autoevaluación | E18: AU | F18: proceso | J18: *Luisa Marcela Toro Medina
A19: =TEXT(ISEVEN(E19),0) -> #VALUE! | C19: Registro Calificado | D19: Coordinador Registro Calificado | E19: RC | F19: proceso | J19: Jeferson Esteban Cordoba Molano
A20: =TEXT(ISEVEN(E20),0) -> #VALUE! | C20: Visibilidad Nacional e Internacional | E20: VN | F20: proceso | J20: Diana Carolina Vasquez Zambrano
A21: =TEXT(ISEVEN(E21),0) -> #VALUE! | C21: Relaciones Interinstitucionales - ORI | D21: Director ORI | E21: VN | F21: proceso | J21: Yudi Andrea Acalo Higon
A22: =TEXT(ISEVEN(E22),0) -> #VALUE! | C22: Mercadeo - Admisiones | D22: Coordinador Mercadeo - Admisiones | E22: MA | F22: proceso | J22: Arnol Arias Hoyos
A23: =TEXT(ISEVEN(E23),0) -> #VALUE! | C23: Comunicaciones Institucional | D23: Coordinador Comunicaciones Institucional | E23: CO | F23: proceso | J23: Lina Fernanda Gutiérrez Montoya
A24: =TEXT(ISEVEN(E24),0) -> #VALUE! | C24: Bienestar Institucional | D24: Director Bienestar | E24: BI | F24: proceso | J24: Fabian Felipe Mera Hurtado
A25: =TEXT(ISEVEN(E25),0) -> #VALUE! | C25: Gestión Humana | D25: Directo talento Humano | E25: GH | F25: proceso | J25: Diego Fernando Ordoñez Trullo
A26: =TEXT(ISEVEN(E26),0) -> #VALUE! | C26: Gestión del Talento Humano | D26: Directo talento Humano | E26: TH | F26: proceso | J26: Angela Milena Velásquez Vargas
A27: =TEXT(ISEVEN(E27),0) -> #VALUE! | C27: Gestión de Seguridad y Salud en el Trabajo | D27: Coordiandor Gestión de SST | E27: ST | F27: proceso | J27: Julieth Alexandra Chacón Paja
A28: =TEXT(ISEVEN(E28),0) -> #VALUE! | C28: Gestión Administrativa y Financiera | E28: GF | F28: proceso | J28: *Maria Camila Toro Gonzalez
A29: =TEXT(ISEVEN(E29),0) -> #VALUE! | C29: Gestión Financiera | D29: Vicerrector Administrativo | E29: GF | F29: proceso | J29: Juan Manuel Prado Quintero
A30: =TEXT(ISEVEN(E30),0) -> #VALUE! | C30: Gestión Administrativa | D30: Coordinador Gestión Administrativo | E30: GA | F30: proceso | J30: Laura Melissa Muñoz Burbano
A31: =TEXT(ISEVEN(E31),0) -> #VALUE! | C31: Gestión Contable y Tesorería | D31: Contador | E31: CT | F31: proceso
A32: =TEXT(ISEVEN(E32),0) -> #VALUE! | C32: Gestión Legal y Documental | E32: GL | F32: proceso
A33: =TEXT(ISEVEN(E33),0) -> #VALUE! | C33: Gestión Legal | D33: Secretaria General | E33: GL | F33: proceso
A34: =TEXT(ISEVEN(E34),0) -> #VALUE! | C34: Gestión Documental | D34: Coordiandor gestión Documental | E34: GD | F34: proceso
A35: =TEXT(ISEVEN(E35),0) -> #VALUE! | C35: Gestión de Recursos | E35: GR | F35: proceso
A36: =TEXT(ISEVEN(E36),0) -> #VALUE! | C36: Recursos Educativos | D36: Coordinador recursos Educativos | E36: RE | F36: proceso
A37: =TEXT(ISEVEN(E37),0) -> #VALUE! | C37: Recursos Tecnológicos | D37: Director GTI | E37: RT | F37: proceso
A38: =TEXT(ISEVEN(E38),0) -> #VALUE! | C38: Recursos Físicos | D38: Coordinador Recursos Físicos | E38: RF | F38: proceso
A39: =TEXT(ISEVEN(E39),0) -> #VALUE! | C39: Prog. Administración de Empresas | D39: Director de Programa | E39: PRO-1 | F39: programa
A40: =TEXT(ISEVEN(E40),0) -> #VALUE! | C40: Prog. Arquitectura | D40: Director de Programa | E40: PRO-2 | F40: programa
A41: =TEXT(ISEVEN(E41),0) -> #VALUE! | C41: Prog. Derecho | D41: Director de Programa | E41: PRO-3 | F41: programa
A42: =TEXT(ISEVEN(E42),0) -> #VALUE! | C42: Prog. Licenciatura Ed. Art. y Cultural | D42: Director de Programa | E42: PRO-4 | F42: programa
A43: =TEXT(ISEVEN(E43),0) -> #VALUE! | C43: Prog. Psicología | D43: Director de Programa | E43: PRO-5 | F43: programa
A44: =TEXT(ISEVEN(E44),0) -> #VALUE! | C44: Prog. Trabajo Social | D44: Director de Programa | E44: PRO-6 | F44: programa
A45: =TEXT(ISEVEN(E45),0) -> #VALUE! | D45: Director de Programa | E45: PRO-7 | F45: programa
A46: =TEXT(ISEVEN(E46),0) -> #VALUE! | C46: PPN - Prog. Ecología | D46: Director de Programa | E46: PRO-8 | F46: programa
A47: =TEXT(ISEVEN(E47),0) -> #VALUE! | C47: PPN - Prog. Ingeniería de Sistemas | D47: Director de Programa | E47: PRO-9 | F47: programa
A48: =TEXT(ISEVEN(E48),0) -> #VALUE! | C48: PPN - Prog. Ingeneiría Industrial | D48: Director de Programa | E48: PRO-10 | F48: programa
A49: =TEXT(ISEVEN(E49),0) -> #VALUE! | C49: PPN - Prog. Contaduría Pública | D49: Director de Programa | E49: PRO-11 | F49: programa
A50: =TEXT(ISEVEN(E50),0) -> #VALUE! | C50: PPN - Prog. Comunicación Social | D50: Director de Programa | E50: PRO-12 | F50: programa
A51: =TEXT(ISEVEN(E51),0) -> #VALUE! | C51: PPN - Prog. Ingenieria Agroecológica | D51: Director de Programa | E51: PRO-13 | F51: programa
A52: =TEXT(ISEVEN(E52),0) -> #VALUE! | C52: STQ - Prog. Arquitectura | D52: Director de Programa | E52: PRO-14 | F52: programa
A53: =TEXT(ISEVEN(E53),0) -> #VALUE! | C53: STQ - Prog. Derecho | D53: Director de Programa | E53: PRO-15 | F53: programa
A54: =TEXT(ISEVEN(E54),0) -> #VALUE! | C54: STQ - Prog. Licenciatura Ed. Art. y Cultural | D54: Director de Programa | E54: PRO-16 | F54: programa
C55: STQ - Prog. Psicología | D55: Director de Programa | E55: PRO-17 | F55: programa
C56: STQ - Prog. Trabajo Social | D56: Director de Programa | E56: PRO-18 | F56: programa
C57: STQ - Prog. Ingeniería Industrial | D57: Director de Programa | E57: PRO-19 | F57: programa
C62: PPN - Prog. Psicología
C63: PPN - Prog. Trabajo Social
